Workbook
Name UPDATE: '[1]Data Sheet'!$E$1

Sheet Assumption Sheet
B2: As per Management Guidance | N2: FY2025
M3: Q1
B4: FY2025 | C4: Q1 | D4: Q2 | F4: Q3 | G4: Q4 | H4: Forecast for FY2026 | M4: Key Driver | N4: Assumption / Analysis (One Line)
B5: Volume % growth | C5: 0.07 | D5: -0.005 | F5: 0.016 | G5: 0.021 | H5: ~7% | M5: Revenue Growth | N5: Expected to improve gradually, supported by rural recovery, festive demand, and stronger institutional activity. | P5: Rank | Q5: Initiative | R5: Major Competitors Without Comparable Offering
B6: Value growth% | C6: -0.03 | D6: -0.067 | F6: -0.078 | G6: -0.041 | H6: ~3% | M6: Volume Growth | N6: Expected to remain strong (9–11%) driven by wider distribution, rural demand, and festive season. | P6: 1 | Q6: Beautiful Homes Painting Services (600+ cities) | R6: Birla Opus, Berger Paints, Kansai Nerolac, Indigo Paints, Akzo Nobel India
B7: Distribution Network | C7: 1.65 Lakhs | D7: 1,67 lakhs | F7: 1,69 Lakhs | G7: 1,69 Lakhs | M7: Value Growth | N7: Expected to recover gradually as price hikes and an improved product mix offset the impact of earlier price cuts. | P7: 2 | Q7: Beautiful Homes Stores (74 stores, 53 cities) | R7: Birla Opus, Berger Paints, Kansai Nerolac, Indigo Paints, Akzo Nobel India
B8: Capacity Expansion | C8: +300000 KL | D8: 0 | F8: 0 | G8: 0 | M8: Pricing | N8: Moderate price increases are expected to offset raw material inflation and support profitability. | P8: 3 | Q8: Nilaya Anthology (Luxury Design Destination) | R8: Birla Opus, Berger Paints, Kansai Nerolac, Indigo Paints, Akzo Nobel India
B9: Home Décor | C9: 61 | D9: 62 | F9: 64 | G9: 72 | M9: Product Mix | N9: Expected to improve with a higher contribution from premium products, leading to better realizations. | P9: 4 | Q9: Chromacosm (5,300+ shade colour system) | R9: Birla Opus, Indigo Paints
B10: EBITDA Amrgin | C10: ~19% | D10: ~19% | F10: ~19% | G10: ~19% | H10: ~19% | M10: Rural Demand | N10: Expected to strengthen due to improved monsoon, better farm income, and recovery in Tier III & IV markets. | P10: 5 | Q10: AI Colour Visualizer & Digital Colour Consultancy (1,000+ consultation locations) | R10: Berger Paints, Birla Opus, Indigo Paints, Kansai Nerolac
M11: Premiumization | N11: Premium portfolio is expected to gain traction, supporting higher margins and revenue quality. | P11: 6 | Q11: Innovation Platform (300+ launches, 130+ patents, 14% revenue from innovation) | R11: Indigo Paints, Birla Opus
M12: Distribution Network | N12: Continued expansion of retail touchpoints is expected to drive market penetration and long-term volume growth. | P12: 7 | Q12: Backward Integration (White Cement + VAM-VAE projects) | R12: Berger Paints, Indigo Paints, Akzo Nobel India
B13: FY2026 | C13: Q1 | D13: Q2 | F13: Q3 | G13: Q4 | H13: Forecast for FY2027 | M13: Capacity Utilization | N13: Existing manufacturing capacity is sufficient to support future growth without major capacity constraints.
B14: Volume % growth | C14: 0.042 | D14: 0.109 | F14: 0.079 | G14: 0.124 | H14: ~9% | M14: Home Décor Business | N14: Expected to grow faster than the core paint business through store expansion and cross-selling opportunities.
B15: Value growth% | C15: -0.2 | D15: 0.067 | F15: 0.028 | G15: 0.102 | H15: ~5% | M15: Industrial Business | N15: Expected to deliver steady growth supported by strong automotive and industrial coatings demand. | P15: Rank | Q15: Initiative | R15: Berger Paints | S15: Kansai Nerolac | T15: Birla Opus | U15: Indigo Paints | V15: Akzo Nobel (Dulux) | W15: Competitive Position
B16: Distribution Network | C16: 1,70 lakhs | D16: 1,70 lakhs | F16: 1,70 lakhs | G16: 1,70 lakhs | H16: 1,70 lakhs | M16: International Business | N16: Growth is expected to remain moderate due to macroeconomic weakness and currency headwinds in key markets. | P16: 1 | Q16: Beautiful Homes Painting Services (600+ cities) | R16: Similar offering but much smaller | S16: Similar offering but much smaller | T16: Early stage / Limited | U16: Similar offering but much smaller | V16: Similar offering but much smaller | W16: Asian Paints is the clear market leader by scale and integration
B17: Capacity Expansion | C17: 100 | D17: 0 | H17: 700 | M17: Gross Margin | N17: Expected to remain stable at healthy levels, supported by pricing actions and sourcing efficiencies despite inflation. | P17: 2 | Q17: Beautiful Homes Stores (74 stores across 53 cities) | R17: No comparable offering | S17: No comparable offering | T17: No comparable offering | U17: No comparable offering | V17: No comparable offering | W17: Unique competitive moat | X17: 4% of Total Revenue
B18: home Décor | C18: 72 | D18: 73 | F18: 74 | G18: 74 | M18: Operating Expenses | N18: Operating expenses are expected to remain elevated in the near term due to investments in people and distribution. | P18: 3 | Q18: Nilaya Anthology (Luxury Design Destination) | R18: No comparable offering | S18: No comparable offering | T18: No comparable offering | U18: No comparable offering | V18: No comparable offering | W18: Unique competitive moat
B19: Forecasted EBITDA margin for next Quarter | C19: ~19% | D19: ~19% | F19: ~19% | G19: ~19% | H19: ~19% | M19: EBITDA Margin | N19: Expected to remain within management's target range of 18–20% as operating leverage improves. | P19: 4 | Q19: Chromacosm (5,300+ shade colour system) | R19: Similar colour system, but smaller | S19: Similar colour system, but smaller | T19: Similar colour system, but smaller | U19: Similar colour system, but smaller | V19: Similar colour system, but smaller | W19: Industry-leading scale and colour database
C20: As per CEO: single digit growth rate for both value and volume in near term | M20: Working Capital | N20: Working capital efficiency is expected to remain strong, supported by disciplined inventory and dealer management. | P20: 5 | Q20: AI Colour Visualizer & Digital Colour Consultancy (1,000+ consultation locations) | R20: Similar tool but smaller ecosystem | S20: Similar tool but smaller ecosystem | T20: Similar tool but smaller ecosystem | U20: Similar tool but smaller ecosystem | V20: Similar tool but smaller ecosystem | W20: Largest digital consultation ecosystem in India
C21: we would anticipate that the gap between the volume and the value would remain in that zone of about 4-5%. | M21: Capital Expenditure | N21: Capex is expected to normalize, with investments focused on maintenance and Home Décor expansion rather than new manufacturing capacity. | P21: 6 | Q21: Innovation Platform (300+ launches, 130+ patents, 14–17% revenue from innovation) | R21: Strong R&D but lower commercialisation | S21: Strong R&D but lower commercialisation | T21: Early-stage innovation platform | U21: Smaller innovation pipeline | V21: Strong R&D but lower commercialisation | W21: Industry leader in innovation commercialisation
C22: FY2025 | H22: FY2026 | P22: 7 | Q22: Backward Integration (White Cement + VAM + VAE projects) | R22: No comparable backward integration | S22: No comparable backward integration | T22: No comparable backward integration | U22: No comparable backward integration | V22: No comparable backward integration | W22: Unique cost-efficiency and supply-chain advantage
B23: Metric | C23: Q1 FY25 | D23: Q2 FY25 | F23: Q3 FY25 | G23: Q4 FY25 | H23: Q1 FY26 | I23: Q2 FY26 | J23: Q3 FY26 | K23: Q4 FY26
B24: Gross Margin | M24: Q2
B25: Product Mix | C25: Economy | D25: Economy | F25: Economy | G25: Economy + Premium | H25: Economy + Premium | I25: Economy + Premium | J25: Economy + PreLux | K25: Economy + PreLux | M25: Key Driver | N25: Q2 FY25 Assumption / Analysis (One Line)
B26: Pricing Approach | C26: Price Cut | D26: Price Cut | F26: Price Cut | G26: Price Cut | H26: Stable | I26: Stable | J26: Stable | K26: Price Hike | M26: Revenue Growth | N26: Revenue growth is expected to recover gradually as demand improves with better rural sentiment, government spending and wedding season, although near-term recovery remains cautious.
B27: Innovation % of revenue | C27: 0.12 | D27: 0.12 | F27: 0.12 | G27: 0.12 | H27: 0.14 | I27: 0.15 | J27: 0.16 | K27: 0.17 | M27: Volume Growth | N27: Management now expects single-digit volume growth for FY25, reflecting weaker consumer demand and extended monsoon disruptions.
B28: Inflation/ Deflation | C28: Deflation | D28: Deflation | F28: Deflation | G28: Deflation | H28: Deflation | I28: Deflation | J28: Deflation | K28: Deflation | M28: Value Growth | N28: Value growth is expected to remain under pressure in the near term due to earlier price reductions, adverse product mix and higher competitive discounting, with gradual improvement from Q3 onwards.
B29: The VAM-VAE project will bring to us very strong innovation capabilities in the market and really change the fabric of the market from the area of looking at green paints in a strong manner. That's something which we feel is a very strong catalyst for us going forward | M29: Pricing | N29: The 1.2% price hike taken in Q2 is expected to fully flow through from Q3, supporting realizations and partially offsetting raw material inflation.
M30: Product Mix | N30: Product mix is expected to improve gradually as premium products recover and demand normalizes, supporting realizations and margins.
M31: Rural Demand | N31: Rural markets continue to outperform urban markets and are expected to strengthen further following a good monsoon and higher government spending.
M32: Urban Demand | N32: Urban demand is expected to remain weak in the near term due to subdued consumer sentiment and slower discretionary spending.
M33: Premiumization | N33: Premium portfolio expansion through product innovation and upgraded offerings is expected to improve realizations over the medium term.
M34: Distribution Network | N34: Continued expansion beyond 1.67 lakh retail touchpoints is expected to support long-term market penetration and volume growth.
B35: Indian real Estate | E35: Indian GDP growth forecast | M35: Services Business | N35: Beautiful Homes Painting Services and Trusted Contractor Services continue to gain traction, strengthening customer engagement and recurring business.
H36: Indian real estate | M36: Institutional Business | N36: Projects and institutional business is expected to improve gradually as construction activity and government projects recover.
M37: Innovation | N37: Continuous product innovation and new product launches are expected to support premiumization and differentiation, with new products contributing around 12% of revenue.
M38: Capacity Expansion | N38: Brownfield capacity expansion is largely complete, while backward integration projects remain on track, reducing future supply constraints.
M39: Home Décor Business | N39: Home Décor is expected to continue outperforming the core paint business over the long term despite temporary demand softness.
M40: Industrial Business | N40: Industrial coatings are expected to remain a key growth driver, supported by healthy automotive OEM, refinish and protective coatings demand.
H41: Source: mordor intelligence | M41: International Business | N41: International business is expected to recover gradually as Bangladesh stabilizes and Nepal improves, although currency volatility remains a key risk.
M42: Raw Material Costs | N42: Raw material inflation is expected to soften, although volatility in crude oil prices remains an important risk to margins.
B43: Source:IMARC | M43: Gross Margin | N43: Gross margins are expected to recover gradually from Q3, supported by price hikes, easing input costs and improving product mix.
M44: Operating Expenses | N44: Employee and sales expenses are expected to normalize as revenue growth improves, resulting in better operating leverage.
M45: EBITDA Margin | N45: EBITDA margins are expected to recover toward management's 18–20% guidance as pricing benefits and operating leverage improve.
M46: Working Capital | N46: Working capital discipline is expected to remain strong, with management maintaining optimal dealer inventory and protecting dealer ROI.
M47: Capital Expenditure | N47: Future capex is expected to focus on backward integration, Home Décor expansion and maintenance rather than major paint capacity additions.
E48: Source: EY | M48: Competitive Intensity | N48: Competitive intensity is expected to remain elevated in the near term, particularly in economy paints, waterproofing and putty, resulting in continued pricing pressure.
E49: Growth rate from 2027 to 2030 | F49: 6.5% to 6.7% | M49: Outlook | N49: Management remains cautiously optimistic, expecting demand to improve in H2 supported by rural recovery, weddings, infrastructure spending and easing raw material costs.
B51: Number of Households | M51: Q3
H52: Industrial growth | M52: Key Driver | N52: One-Line Analysis / Assumption
H53: India's industrial and manufacturing sector is forecast to grow at a compound annual growth rate (CAGR) of around 4.8% to reach an industrial market size of over USD 520 billion by 2030. | M53: Revenue Growth | N53: Revenue growth is expected to recover gradually, supported by improving rural demand, B2B recovery and industrial growth despite continued urban weakness.
E54: Lower middle---> 2.6% CAGR over 12 yrs | M54: Decorative Paint Demand | N54: Decorative demand remained weak due to muted consumer sentiment, weak festive spending and slower urban consumption.
E55: Upper Middle---> +8.81% CAGR | H55: Source: yahoo Finance | M55: Volume Growth | N55: Volume growth remained positive at 1.6%, indicating resilient underlying demand despite a challenging market environment.
E56: High income---> +11.33% CAGR | M56: Value Growth | N56: Value declined due to downtrading and lower realizations as consumers shifted toward economy products.
E57: <------As per WEF | H57: Inflation Forecast | M57: Pricing | N57: Previous price hikes supported realizations, while future pricing will depend on raw material costs and market conditions.
M58: Downtrading / Product Mix | N58: Consumer preference shifted towards lower-priced products, adversely impacting value growth and profitability.
M59: Rural Demand | N59: Rural demand remained relatively resilient and is expected to benefit from good monsoons and higher government spending.
M60: Urban Demand | N60: Urban demand continues to remain under pressure due to weak discretionary consumption.
B61: Source: World Economic Forum | M61: Distribution Expansion | N61: Continued expansion to around 1.69 lakh retail touchpoints strengthens long-term market reach and penetration.
M62: Painting Services | N62: Beautiful Homes Painting Services continued to gain strong customer acceptance, supporting premium service revenues.
M63: Institutional / Projects Business | N63: Institutional demand improved on the back of stronger factory, builder and government project activity.
B64: Automotive growth | M64: Innovation | N64: New product launches contributed over 12% of revenue, reinforcing premiumization and product differentiation.
H65: Source: The Global Economy | M65: Premiumization | N65: The company continues investing in premium and luxury products to improve long-term realizations and margins.
M66: Home Décor | N66: Home Décor continues expanding strategically despite slower growth caused by weak urban demand.
M67: Industrial Business | N67: Industrial coatings outperformed decorative paints, driven by auto, refinish and protective coatings.
M68: International Business | N68: International business delivered strong constant currency growth, led by Asia and the Middle East despite African currency headwinds.
M69: Capacity / Backward Integration | N69: Backward integration projects remain on track and are expected to enhance long-term cost efficiency.
M70: Raw Material Costs | N70: Sequential margin improvement was supported by material price deflation and sourcing efficiencies.
M71: Gross Margin | N71: Gross margins improved sequentially but remained below last year's level due to weaker product mix.
M72: Operating Expenses | N72: Operating deleverage from weak revenue growth continued to pressure profitability.
M73: EBITDA / PBDIT Margin | N73: Management reiterated its medium-term PBDIT margin guidance of 18–20% despite the challenging demand environment.
B74: Source: grand view research | M74: Working Capital | N74: Efficient inventory management and an expanding distribution network are expected to support healthy working capital.
B75: CAGR | C75: =(8.5/6.9)^(1/5)-1 -> 0.042590989 | M75: Capital Expenditure | N75: Capital expenditure remains focused on backward integration and strengthening long-term manufacturing capabilities.
M76: Competitive Intensity | N76: The industry remains competitive, but management continues prioritizing brand strength and profitability over aggressive price-led growth.
M77: Management Outlook | N77: Management remains cautiously optimistic, expecting gradual recovery over the next two quarters supported by rural demand, industrial growth and government spending.
M79: Reason for ubran slow Consumption (FY2025) | N79: . Bulk of this slowdown was on account of weak urban consumption on the back of tepid wage growth and consistent inflation impacting their disposable incomes. Rural consumption, on the other hand, exhibited pick-up with support from above-normal overall monsoon and higher agriculture output and prices. Like in other major economies, domestic headline inflation softened falling from 5.4% in the previous financial year to a six-year low of 4.6% in FY 2024-25. Tighter monetary policy, particularly restrictions on credit flows to non-productive sectors, also weighed on leveraged consumption. However, with inflation easing and fiscal support increasing, the consumption outlook is expected to improve in the near term.
B80: White Cement Plant
B81: 1. Wall putty | C81: Operatinal in FY2026 | D81: 30 to 80 BPS in gross Margin | F81: benefit in FY2027-28 | M81: Perception of Management for Future growth of Customer Segment (FY2025) | N81: Amidst this uncertain global backdrop of higher trade protectionism and trade conflicts, the focus will be on India’s domestic consumption driven growth story. Rural consumption is expected to remain healthy with tailwinds from favourable monsoon, farm and non-farm wage growth and continued focus from Central and State governments on rural-focused welfare spends. Slowing trend in urban consumption is also expected to wane after almost two years and the budgetary support in terms of lower personal income taxes for the lower-income and middle-income households is expected to provide a boost to consumption. Tighter fiscal and loosening monetary policy is further expected to support fall in interest rates in the domestic economy and with rebound in public capex cycle by the Government, its trickle-down effect in terms of rural and urban wages will support consumption trends in the near term.
B82: 2. texture Finsihes
B83: 3. Waterproofing | M83: Q4 Initiative | N83: One-Line Equity Research Summary
B84: 4. Premium Decorative Products | M84: Demand Environment | N84: Demand remained weak, with urban markets continuing to lag while rural markets showed relatively better resilience.
M85: Distribution Expansion | N85: Continued expansion to 1.69 lakh retail touchpoints reinforces long-term market penetration and competitive advantage.
B86: VAM - VAE project | M86: Painting Services | N86: Beautiful Homes Painting Services continues to strengthen customer engagement and generate recurring business opportunities.
B87: 1. Emulsion | C87: operational in FY2027 | D87: 80 to 150 BPS in GM | F87: benefit in FY2028-29 | M87: B2B / Institutional Business | N87: Institutional and government projects emerged as an important growth engine amid weak retail demand.
B88: 2. Adhesives | M88: Innovation | N88: Innovation remains a key differentiator, with new products contributing approximately 14% of Q4 revenue.
B89: 3. Pain Binders | M89: Backward Integration | N89: Investments in White Cement and VAM-VAE are expected to enhance long-term cost competitiveness and product differentiation.
M90: Premiumization | N90: Premiumization efforts continue through advanced formulations, regional packaging and warranty-led branding.
M91: Value Segment Strategy | N91: The company strengthened its economy portfolio through Ace and Tractor campaigns to capture value-conscious consumers.
B92: Product Category | C92: % of T revenue | M92: Brand Building | N92: The 'Har Ghar Kuch Kehta Hai' campaign reinforces Asian Paints' leadership by emphasizing trust, durability and emotional brand connect.
B93: Interior Emulsions | C93: 35–40% | D93: Capex will help | G93: Crude Oil | M93: Home Décor Expansion | N93: Management continues investing in Home Décor despite near-term weakness, reflecting confidence in the long-term opportunity.
B94: Exterior Emulsions | C94: 18–22% | D94: Capex will help | G94: FY2025 | M94: Nilaya Luxury Strategy | N94: Nilaya Anthology positions Asian Paints in the luxury home décor segment, expanding beyond traditional paints.
B95: International Business | C95: 10–11% | G95: Q1 | H95: 84 | M95: Industrial Business | N95: Industrial coatings continued outperforming decorative paints, providing stability to consolidated earnings.
B96: Industrial Coatings | C96: 9–10% | G96: Q2 | H96: 80 | M96: International Business | N96: International growth remained mixed, with strong Middle East and Asia performance offset by African currency headwinds.
B97: Waterproofing | C97: 8–10% | D97: Capex will help | G97: Q3 | H97: 73 | M97: Margin Management | N97: Gross margin improved through raw material deflation and operational efficiencies despite continued pricing pressure.
B98: Enamels & Wood Finishes | C98: 8–10% | G98: Q4 | H98: 75 | M98: Competitive Strategy | N98: Management remains focused on defending market leadership through brand, distribution, innovation and cost leadership rather than aggressive discounting.
B99: Construction Chemicals & Putty | C99: 6–8% | D99: Capex will help | M99: FY26 Outlook | N99: Management expects a gradual demand recovery supported by infrastructure spending, rural demand and a normal monsoon while remaining cautiously optimistic.
B100: Home Décor | C100: 3–4%
B101: Adhesives & Sealants | C101: 2–4% | D101: Capex will help
M102: FY2025
M103: Theme | N103: One-Line Summary
...

Sheet Assumption 2
C2: Year | D2: 2016 | E2: =D2+1 -> 2017 | F2: =E2+1 -> 2018 | G2: =F2+1 -> 2019 | H2: =G2+1 -> 2020 | I2: =H2+1 -> 2021 | J2: =I2+1 -> 2022 | K2: =J2+1 -> 2023 | L2: =K2+1 -> 2024 | ... N2: =M2+1 -> 2026
C3: Decorative Segment
C4: Volume Growth | D4: 0.1 | E4: 0.06 | F4: 0.11 | G4: 0.13 | H4: 0.107 | I4: 0.125 | J4: 0.31 | K4: 0.14 | L4: 0.094 | M4: 0.025 | N4: 0.09
C6: Market Share Asian Paints | D6: out of 100 for each
C7: North India | D7: 0.48
C8: South India | D8: 0.41
C9: West India | D9: 0.33
C10: East India | D10: 0.32
C12: North
C13: Delhi NCR Region
D14: 2021 | E14: =D14+1 -> 2022 | F14: =E14+1 -> 2023 | G14: =F14+1 -> 2024 | H14: =G14+1 -> 2025 | I14: E2026
C15: NCR residential area sold(MSF) | D15: 34 | E15: 51 | F15: 72 | G15: 78 | H15: 103 | I15: 120 | J15: CAGR past 6 years
C16: y.o.y Growth | E16: =E15/D15-1 -> 0.5 | F16: =F15/E15-1 -> 0.41176471 | G16: =G15/F15-1 -> 0.083333333 | H16: =H15/G15-1 -> 0.32051282 | I16: =I15/H15-1 -> 0.16504854 | J16: =(I15/D15)^(1/5)-1 -> 0.28688715
C17: Luxury share of area sold | D17: 0.24 | H17: 0.58 | I17: H1-48%
C18: (Source: ICRA and Propequity)
C19: Note:
C20: 1. FY2026 as per ICRA its is expcted to touch 120 MSF which could be 16.5% y.o.y
C21: 2. For FY2027 growth will remain flattish as market has already achieved a good number
C22: 3.Demand is normalising after a period of exceptionally strong growth. NCR recorded very strong growth in FY2025 and is estimated to grow another 12–15% in FY2026, so the FY2027 forecast reflects a return to a more sustainable growth rate rather than a deterioration in underlying demand.
C23: South
C24: Bangluru
D25: 2021 | E25: =D25+1 -> 2022 | F25: =E25+1 -> 2023 | G25: =F25+1 -> 2024 | H25: =G25+1 -> 2025 | I25: E2026
C26: Bengluru Residential area sold (MSF) | D26: 50 | E26: 72 | F26: 80 | G26: 102 | H26: 99 | I26: 104 | J26: CAGR past 6 years
C27: y.o.y Growth | E27: =E26/D26-1 -> 0.44 | F27: =F26/E26-1 -> 0.11111111 | G27: =G26/F26-1 -> 0.275 | H27: =H26/G26-1 -> -0.029411765 | I27: =I26/H26-1 -> 0.050505051 | J27: =(I26/D26)^(1/5)-1 -> 0.15774434
C28: Shares of luxury launches | D28: 0.19 | H28: 0.37 | I28: H1-49%
C29: (Source: ICRA and Propequity)
C30: Note:
C31: 1.Demand for mid-income and luxury homes remains healthy, but the recent slowdown in luxury sales velocity means overall housing volumes are unlikely to maintain their earlier rapid growth rate.
C33: West
C34: Mumbai metropolitan
D35: 2021 | E35: =D35+1 -> 2022 | F35: =E35+1 -> 2023 | G35: =F35+1 -> 2024 | H35: =G35+1 -> 2025 | I35: E2026
C36: Mumbai Residential area sold (MSF) | D36: 150 | E36: 155 | F36: 163 | G36: 170 | H36: 160 | I36: 152 | J36: CAGR past 6 years
C37: y.o.y Growth | E37: =E36/D36-1 -> 0.033333333 | F37: =F36/E36-1 -> 0.051612903 | G37: =G36/F36-1 -> 0.042944785 | H37: =H36/G36-1 -> -0.058823529 | I37: =I36/H36-1 -> -0.05 | J37: =(I36/D36)^(1/5)-1 -> 0.0026525572
C38: Luxury share of area sold | D38: 0.31 | H38: 0.37 | I38: 9m-44%
C39: (Source: ICRA and Propequity)
C40: Note:
C41: 1. FY2027 the residential area sold is to decline 0-3%
C42: 2.MMR is more mature than the other two markets, so affordability is becoming a bigger constraint. Higher property prices are reducing absorption in the affordable and mid-income segments. Luxury demand remains resilient, but it is not sufficient to offset the weakness in the broader market, which is why ICRA expects a marginal 0–3% contraction in FY2027.

Sheet Financials>

Sheet HistoricalFS
B2: ="Historical Financial Statement"&" - "&Datasheet!$B$1 -> Historical Financial Statement - ASIAN PAINTS LTD
B3: Years | C3: 42825 | D3: 43190 | E3: 43555 | F3: 43921 | G3: 44286 | H3: 44651 | I3: 45016 | J3: 45382 | K3: 45747 | L3: 46112 | M3: LTM
A5: # | B5: Income Statement | V5: 11 | W5: =V5+1 -> 12 | X5: =W5+1 -> 13 | Y5: =X5+1 -> 14 | Z5: =Y5+1 -> 15 | AA5: =Z5+1 -> 16 | AB5: =AA5+1 -> 17 | AC5: =AB5+1 -> 18 | AD5: =AC5+1 -> 19 | ... AL5: =AK5+1 -> 27
B6: Sales | C6: =IFERROR(Datasheet!B17,0) -> 15061.99 | D6: =IFERROR(Datasheet!C17,0) -> 16824.55 | E6: =IFERROR(Datasheet!D17,0) -> 19240.13 | F6: =IFERROR(Datasheet!E17,0) -> 20211.25 | G6: =IFERROR(Datasheet!F17,0) -> 21712.79 | H6: =IFERROR(Datasheet!G17,0) -> 29101.28 | I6: =IFERROR(Datasheet!H17,0) -> 34488.59 | J6: =IFERROR(Datasheet!I17,0) -> 35494.73 | ... L6: =IFERROR(Datasheet!K17,0) -> 35583.54 | M6: =L6 -> 35583.54 | V6: 7722 | W6: 9632 | X6: 10938 | Y6: 12715 | Z6: 14183 | AA6: 15534 | AB6: 15061.99 | AC6: 16824.55 | AD6: 19240.13 | AE6: 20211.25 | AF6: 21712.79 | AG6: 29101.28 | AH6: 34488.59 | AI6: 35494.73 | AJ6: 33905.62 | AK6: 35583.54 | AL6: 35583.54
B7: Sales Growth | C7: - | D7: =D6/C6-1 -> 0.11702039 | E7: =E6/D6-1 -> 0.14357472 | F7: =F6/E6-1 -> 0.050473671 | G7: =G6/F6-1 -> 0.074292288 | H7: =H6/G6-1 -> 0.34028285 | I7: =I6/H6-1 -> 0.18512278 | J7: =J6/I6-1 -> 0.029173127 | K7: =K6/J6-1 -> -0.044770308 | L7: =L6/K6-1 -> 0.049487961 | M7: =L7 -> 0.049487961 | W7: =W6/V6-1 -> 0.24734525 | X7: =X6/W6-1 -> 0.1355897 | Y7: =Y6/X6-1 -> 0.16246114 | Z7: =Z6/Y6-1 -> 0.11545419 | AA7: =AA6/Z6-1 -> 0.095254883 | AB7: =AB6/AA6-1 -> -0.030385606 | AC7: =AC6/AB6-1 -> 0.11702039 | AD7: =AD6/AC6-1 -> 0.14357472 | ... AL7: =AL6/AK6-1 -> 0
B9: COGS | C9: =IFERROR(SUM(Datasheet!B18,Datasheet!B20:B22)-1*Datasheet!B19,0) -> 9732.66 | D9: =IFERROR(SUM(Datasheet!C18,Datasheet!C20:C22)-1*Datasheet!C19,0) -> 11194.17 | E9: =IFERROR(SUM(Datasheet!D18,Datasheet!D20:D22)-1*Datasheet!D19,0) -> 12905.81 | F9: =IFERROR(SUM(Datasheet!E18,Datasheet!E20:E22)-1*Datasheet!E19,0) -> 13158.02 | G9: =IFERROR(SUM(Datasheet!F18,Datasheet!F20:F22)-1*Datasheet!F19,0) -> 14035.07 | H9: =IFERROR(SUM(Datasheet!G18,Datasheet!G20:G22)-1*Datasheet!G19,0) -> 20590.57 | I9: =IFERROR(SUM(Datasheet!H18,Datasheet!H20:H22)-1*Datasheet!H19,0) -> 23766.7 | J9: =IFERROR(SUM(Datasheet!I18,Datasheet!I20:I22)-1*Datasheet!I19,0) -> 23009.99 | ... L9: =IFERROR(SUM(Datasheet!K18,Datasheet!K20:K22)-1*Datasheet!K19,0) -> 23489.63 | M9: =L9 -> 23489.63
B10: COGS % Sales | C10: =C9/C6 -> 0.64617358 | D10: =D9/D6 -> 0.66534736 | E10: =E9/E6 -> 0.67077561 | F10: =F9/F6 -> 0.65102455 | G10: =G9/G6 -> 0.64639643 | H10: =H9/H6 -> 0.7075486 | I10: =I9/I6 -> 0.68911776 | J10: =J9/J6 -> 0.64826497 | ... M10: =M9/M6 -> 0.66012628
B12: Gross Profit | C12: =C6-C9 -> 5329.33 | D12: =D6-D9 -> 5630.38 | E12: =E6-E9 -> 6334.32 | F12: =F6-F9 -> 7053.23 | G12: =G6-G9 -> 7677.72 | H12: =H6-H9 -> 8510.71 | I12: =I6-I9 -> 10721.89 | J12: =J6-J9 -> 12484.74 | ... M12: =M6-M9 -> 12093.91
B13: Gross Margins | C13: =C12/C6 -> 0.35382642 | D13: =D12/D6 -> 0.33465264 | E13: =E12/E6 -> 0.32922439 | F13: =F12/F6 -> 0.34897545 | G13: =G12/G6 -> 0.35360357 | H13: =H12/H6 -> 0.2924514 | I13: =I12/I6 -> 0.31088224 | J13: =J12/J6 -> 0.35173503 | ... M13: =M12/M6 -> 0.33987372
B15: Other Operating Expenses | C15: =IFERROR(SUM(Datasheet!B23:B24),0) -> 2335.57 | D15: =IFERROR(SUM(Datasheet!C23:C24),0) -> 2426.37 | E15: =IFERROR(SUM(Datasheet!D23:D24),0) -> 2569.38 | F15: =IFERROR(SUM(Datasheet!E23:E24),0) -> 2891.46 | G15: =IFERROR(SUM(Datasheet!F23:F24),0) -> 2822.12 | H15: =IFERROR(SUM(Datasheet!G23:G24),0) -> 3707.1 | I15: =IFERROR(SUM(Datasheet!H23:H24),0) -> 4462.05 | J15: =IFERROR(SUM(Datasheet!I23:I24),0) -> 4899.76 | ... L15: =IFERROR(SUM(Datasheet!K23:K24),0) -> 5394.18 | M15: =L15 -> 5394.18
B16: Oth Op Exp % Sales | C16: =C15/C6 -> 0.15506384 | D16: =D15/D6 -> 0.14421604 | E16: =E15/E6 -> 0.13354276 | F16: =F15/F6 -> 0.14306191 | G16: =G15/G6 -> 0.12997501 | H16: =H15/H6 -> 0.12738615 | I16: =I15/I6 -> 0.12937757 | J16: =J15/J6 -> 0.1380419 | ... M16: =M15/M6 -> 0.151592
B18: EBITDA | C18: =IFERROR(C12-C15,0) -> 2993.76 | D18: =IFERROR(D12-D15,0) -> 3204.01 | E18: =IFERROR(E12-E15,0) -> 3764.94 | F18: =IFERROR(F12-F15,0) -> 4161.77 | G18: =IFERROR(G12-G15,0) -> 4855.6 | H18: =IFERROR(H12-H15,0) -> 4803.61 | I18: =IFERROR(I12-I15,0) -> 6259.84 | J18: =IFERROR(J12-J15,0) -> 7584.98 | ... M18: =IFERROR(M12-M15,0) -> 6699.73
B19: EBITDA Margins | C19: =C18/C6 -> 0.19876258 | D19: =D18/D6 -> 0.19043659 | E19: =E18/E6 -> 0.19568163 | F19: =F18/F6 -> 0.20591354 | G19: =G18/G6 -> 0.22362856 | H19: =H18/H6 -> 0.16506525 | I19: =I18/I6 -> 0.18150467 | J19: =J18/J6 -> 0.21369313 | ... M19: =M18/M6 -> 0.18828172
B21: Interest | C21: =IFERROR(Datasheet!B27,0) -> 37.33 | D21: =IFERROR(Datasheet!C27,0) -> 41.47 | E21: =IFERROR(Datasheet!D27,0) -> 110.47 | F21: =IFERROR(Datasheet!E27,0) -> 102.33 | G21: =IFERROR(Datasheet!F27,0) -> 91.63 | H21: =IFERROR(Datasheet!G27,0) -> 95.41 | I21: =IFERROR(Datasheet!H27,0) -> 144.45 | J21: =IFERROR(Datasheet!I27,0) -> 205.17 | ... L21: =IFERROR(Datasheet!K27,0) -> 195.41 | M21: =L21 -> 195.41
B22: Interest % Debt | C22: =IFERROR(C21/SUM(C49,C50),0) -> 0.0077749776 | D22: =IFERROR(D21/SUM(D49,D50),0) -> 0.0077466959 | E22: =IFERROR(E21/SUM(E49,E50),0) -> 0.016297621 | F22: =IFERROR(F21/SUM(F49,F50),0) -> 0.017032829 | G22: =IFERROR(G21/SUM(G49,G50),0) -> 0.012137951 | H22: =IFERROR(H21/SUM(H49,H50),0) -> 0.010430891 | I22: =IFERROR(I21/SUM(I49,I50),0) -> 0.014759224 | J22: =IFERROR(J21/SUM(J49,J50),0) -> 0.018363889 | ... L22: =IFERROR(L21/SUM(L49,L50),0) -> 0.014863286 | M22: =L22 -> 0.014863286
B24: Depreciation | C24: =IFERROR(Datasheet!B26,0) -> 334.79 | D24: =IFERROR(Datasheet!C26,0) -> 360.47 | E24: =IFERROR(Datasheet!D26,0) -> 622.14 | F24: =IFERROR(Datasheet!E26,0) -> 780.5 | G24: =IFERROR(Datasheet!F26,0) -> 791.27 | H24: =IFERROR(Datasheet!G26,0) -> 816.36 | I24: =IFERROR(Datasheet!H26,0) -> 858.02 | J24: =IFERROR(Datasheet!I26,0) -> 853 | ... L24: =IFERROR(Datasheet!K26,0) -> 1228.85 | M24: =L24 -> 1228.85
B25: Depreciation % Gross Block | C25: =C24/'Raw FS'!E26 -> 0.085536536 | D25: =D24/'Raw FS'!F26 -> 0.07661424 | E25: =E24/'Raw FS'!G26 -> 0.076420587 | F25: =F24/'Raw FS'!H26 -> 0.094240522 | G25: =G24/'Raw FS'!I26 -> 0.094288608 | H25: =H24/'Raw FS'!J26 -> 0.095614898 | I25: =I24/'Raw FS'!K26 -> 0.088675072 | J25: =J24/'Raw FS'!L26 -> 0.073395285 | ... L25: =L24/'Raw FS'!N26 -> 0.08023309 | M25: =L25 -> 0.08023309
B27: Earnings Before Tax | C27: =IFERROR(C18-SUM(C21,C24),0) -> 2621.64 | D27: =IFERROR(D18-SUM(D21,D24),0) -> 2802.07 | E27: =IFERROR(E18-SUM(E21,E24),0) -> 3032.33 | F27: =IFERROR(F18-SUM(F21,F24),0) -> 3278.94 | G27: =IFERROR(G18-SUM(G21,G24),0) -> 3972.7 | H27: =IFERROR(H18-SUM(H21,H24),0) -> 3891.84 | I27: =IFERROR(I18-SUM(I21,I24),0) -> 5257.37 | J27: =IFERROR(J18-SUM(J21,J24),0) -> 6526.81 | ... M27: =IFERROR(M18-SUM(M21,M24),0) -> 5275.47
B28: EBT % Sales | C28: =C27/C6 -> 0.17405668 | D28: =D27/D6 -> 0.1665465 | E28: =E27/E6 -> 0.15760444 | F28: =F27/F6 -> 0.16223341 | G28: =G27/G6 -> 0.18296589 | H28: =H27/H6 -> 0.13373432 | I28: =I27/I6 -> 0.15243795 | J28: =J27/J6 -> 0.1838811 | ... M28: =M27/M6 -> 0.14825591
B30: Tax | C30: =IFERROR(Datasheet!B29,0) -> 943.29 | D30: =IFERROR(Datasheet!C29,0) -> 1040.96 | E30: =IFERROR(Datasheet!D29,0) -> 1098.06 | F30: =IFERROR(Datasheet!E29,0) -> 854.85 | G30: =IFERROR(Datasheet!F29,0) -> 1097.6 | H30: =IFERROR(Datasheet!G29,0) -> 1102.91 | I30: =IFERROR(Datasheet!H29,0) -> 1493.5 | J30: =IFERROR(Datasheet!I29,0) -> 1790.08 | ... L30: =IFERROR(Datasheet!K29,0) -> 1608.75 | M30: =L30 -> 1608.75
B31: Effective Tax Rate | C31: =C30/C27 -> 0.35980913 | D31: =D30/D27 -> 0.37149679 | E31: =E30/E27 -> 0.36211758 | F31: =F30/F27 -> 0.26070925 | G31: =G30/G27 -> 0.27628565 | H31: =H30/H27 -> 0.28339038 | I31: =I30/I27 -> 0.2840774 | J31: =J30/J27 -> 0.27426568 | ... M31: =M30/M27 -> 0.30494913
B33: Net Profit | C33: =IFERROR(C27-C30,0) -> 1678.35 | D33: =IFERROR(D27-D30,0) -> 1761.11 | E33: =IFERROR(E27-E30,0) -> 1934.27 | F33: =IFERROR(F27-F30,0) -> 2424.09 | G33: =IFERROR(G27-G30,0) -> 2875.1 | H33: =IFERROR(H27-H30,0) -> 2788.93 | I33: =IFERROR(I27-I30,0) -> 3763.87 | J33: =IFERROR(J27-J30,0) -> 4736.73 | ... M33: =IFERROR(M27-M30,0) -> 3666.72
B34: Net Margins | C34: =C33/C6 -> 0.1114295 | D34: =D33/D6 -> 0.10467501 | E34: =E33/E6 -> 0.1005331 | F34: =F33/F6 -> 0.11993766 | G34: =G33/G6 -> 0.13241504 | H34: =H33/H6 -> 0.095835303 | I34: =I33/I6 -> 0.10913377 | J34: =J33/J6 -> 0.13344882 | ... M34: =M33/M6 -> 0.1030454
B36: No. of Equity Shares | C36: =IFERROR(Datasheet!B93,0) -> 95.92 | D36: =IFERROR(Datasheet!C93,0) -> 95.92 | E36: =IFERROR(Datasheet!D93,0) -> 95.92 | F36: =IFERROR(Datasheet!E93,0) -> 95.92 | G36: =IFERROR(Datasheet!F93,0) -> 95.92 | H36: =IFERROR(Datasheet!G93,0) -> 95.92 | I36: =IFERROR(Datasheet!H93,0) -> 95.92 | J36: =IFERROR(Datasheet!I93,0) -> 95.92 | ... L36: =IFERROR(Datasheet!K93,0) -> 95.92 | M36: 29.47
B38: Earnings per share | C38: =IFERROR(C33/C36,0) -> 17.497394 | D38: =IFERROR(D33/D36,0) -> 18.360196 | E38: =IFERROR(E33/E36,0) -> 20.16545 | F38: =IFERROR(F33/F36,0) -> 25.271997 | G38: =IFERROR(G33/G36,0) -> 29.973937 | H38: =IFERROR(H33/H36,0) -> 29.075584 | I38: =IFERROR(I33/I36,0) -> 39.239679 | J38: =IFERROR(J33/J36,0) -> 49.382089 | ... L38: =IFERROR(L33/L36,0) -> 38.226856 | M38: =L38 -> 38.226856
B39: EPS Growth % | D39: =IFERROR(D38/C38-1,0) -> 0.049310335 | E39: =IFERROR(E38/D38-1,0) -> 0.098324352 | F39: =IFERROR(F38/E38-1,0) -> 0.25323249 | G39: =IFERROR(G38/F38-1,0) -> 0.18605332 | H39: =IFERROR(H38/G38-1,0) -> -0.029971131 | I39: =IFERROR(I38/H38-1,0) -> 0.34957493 | J39: =IFERROR(J38/I38-1,0) -> 0.25847333 | K39: =IFERROR(K38/J38-1,0) -> -0.29075755 | L39: =IFERROR(L38/K38-1,0) -> 0.091451381 | M39: =L39 -> 0.091451381
B41: Dividend per share | C41: =IFERROR(Datasheet!B31/Datasheet!B93,0) -> 10.300042 | D41: =IFERROR(Datasheet!C31/Datasheet!C93,0) -> 8.6999583 | E41: =IFERROR(Datasheet!D31/Datasheet!D93,0) -> 10.5 | F41: =IFERROR(Datasheet!E31/Datasheet!E93,0) -> 12 | G41: =IFERROR(Datasheet!F31/Datasheet!F93,0) -> 17.849979 | H41: =IFERROR(Datasheet!G31/Datasheet!G93,0) -> 19.150021 | I41: =IFERROR(Datasheet!H31/Datasheet!H93,0) -> 25.650021 | J41: =IFERROR(Datasheet!I31/Datasheet!I93,0) -> 33.300042 | ... L41: =IFERROR(Datasheet!K31/Datasheet!K93,0) -> 27.5 | M41: =L41 -> 27.5
B42: Dividend payout ratio | C42: =IFERROR(C41/C38,0) -> 0.58866148 | D42: =IFERROR(D41/D38,0) -> 0.47384888 | E42: =IFERROR(E41/E38,0) -> 0.52069256 | F42: =IFERROR(F41/F38,0) -> 0.47483386 | G42: =IFERROR(G41/G38,0) -> 0.59551668 | H42: =IFERROR(H41/H38,0) -> 0.65862894 | I42: =IFERROR(I41/I38,0) -> 0.65367561 | J42: =IFERROR(J41/J38,0) -> 0.6743344 | ... M42: =IFERROR(M41/M38,0) -> 0.71938954
B44: Retained Earnings | C44: =IFERROR(IF(C38>C41,1-C42,0),0) -> 0.41133852 | D44: =IFERROR(IF(D38>D41,1-D42,0),0) -> 0.52615112 | E44: =IFERROR(IF(E38>E41,1-E42,0),0) -> 0.47930744 | F44: =IFERROR(IF(F38>F41,1-F42,0),0) -> 0.52516614 | G44: =IFERROR(IF(G38>G41,1-G42,0),0) -> 0.40448332 | H44: =IFERROR(IF(H38>H41,1-H42,0),0) -> 0.34137106 | I44: =IFERROR(IF(I38>I41,1-I42,0),0) -> 0.34632439 | J44: =IFERROR(IF(J38>J41,1-J42,0),0) -> 0.3256656 | ... L44: =IFERROR(IF(L38>L41,1-L42,0),0) -> 0.28061046 | M44: =L44 -> 0.28061046
A46: # | B46: Balance Sheet
B47: Equity Share Capital | C47: =IFERROR(Datasheet!B57,0) -> 95.92 | D47: =IFERROR(Datasheet!C57,0) -> 95.92 | E47: =IFERROR(Datasheet!D57,0) -> 95.92 | F47: =IFERROR(Datasheet!E57,0) -> 95.92 | G47: =IFERROR(Datasheet!F57,0) -> 95.92 | H47: =IFERROR(Datasheet!G57,0) -> 95.92 | I47: =IFERROR(Datasheet!H57,0) -> 95.92 | J47: =IFERROR(Datasheet!I57,0) -> 95.92 | ... L47: =IFERROR(Datasheet!K57,0) -> 95.92 | M47: =L47 -> 95.92
B48: Reserves | C48: =IFERROR(Datasheet!B58,0) -> 7507.97 | D48: =IFERROR(Datasheet!C58,0) -> 8314.31 | E48: =IFERROR(Datasheet!D58,0) -> 9374.63 | F48: =IFERROR(Datasheet!E58,0) -> 10034.24 | G48: =IFERROR(Datasheet!F58,0) -> 12710.37 | H48: =IFERROR(Datasheet!G58,0) -> 13715.64 | I48: =IFERROR(Datasheet!H58,0) -> 15896.31 | J48: =IFERROR(Datasheet!I58,0) -> 18632.38 | ... L48: =IFERROR(Datasheet!K58,0) -> 21275.67 | M48: =L48 -> 21275.67
B49: Borrowings | C49: =IFERROR(Datasheet!B59,0) -> 560.34 | D49: =IFERROR(Datasheet!C59,0) -> 533.43 | E49: =IFERROR(Datasheet!D59,0) -> 1319.6 | F49: =IFERROR(Datasheet!E59,0) -> 1118.5 | G49: =IFERROR(Datasheet!F59,0) -> 1093.12 | H49: =IFERROR(Datasheet!G59,0) -> 1586.88 | I49: =IFERROR(Datasheet!H59,0) -> 1932.62 | J49: =IFERROR(Datasheet!I59,0) -> 2474.38 | ... L49: =IFERROR(Datasheet!K59,0) -> 3928.93 | M49: =L49 -> 3928.93
B50: Other Liabilities | C50: =IFERROR(Datasheet!B60,0) -> 4240.96 | D50: =IFERROR(Datasheet!C60,0) -> 4819.82 | E50: =IFERROR(Datasheet!D60,0) -> 5458.69 | F50: =IFERROR(Datasheet!E60,0) -> 4889.31 | G50: =IFERROR(Datasheet!F60,0) -> 6455.93 | H50: =IFERROR(Datasheet!G60,0) -> 7559.99 | I50: =IFERROR(Datasheet!H60,0) -> 7854.48 | J50: =IFERROR(Datasheet!I60,0) -> 8698.09 | ... L50: =IFERROR(Datasheet!K60,0) -> 9218.23 | M50: =L50 -> 9218.23
B51: Total Liabilities | C51: =SUM(C47:C50) -> 12405.19 | D51: =SUM(D47:D50) -> 13763.48 | E51: =SUM(E47:E50) -> 16248.84 | F51: =SUM(F47:F50) -> 16137.97 | G51: =SUM(G47:G50) -> 20355.34 | H51: =SUM(H47:H50) -> 22958.43 | I51: =SUM(I47:I50) -> 25779.33 | J51: =SUM(J47:J50) -> 29900.77 | ... L51: =SUM(L47:L50) -> 34518.75 | M51: =L51 -> 34518.75
B53: Fixed Assets Net Block | C53: =IFERROR(Datasheet!B62,0) -> 3303.74 | D53: =IFERROR(Datasheet!C62,0) -> 3732.24 | E53: =IFERROR(Datasheet!D62,0) -> 6496.56 | F53: =IFERROR(Datasheet!E62,0) -> 6272.31 | G53: =IFERROR(Datasheet!F62,0) -> 5858.52 | H53: =IFERROR(Datasheet!G62,0) -> 5519.06 | I53: =IFERROR(Datasheet!H62,0) -> 5770.46 | J53: =IFERROR(Datasheet!I62,0) -> 7146.62 | ... L53: =IFERROR(Datasheet!K62,0) -> 9640.28 | M53: =L53 -> 9640.28
B54: Capital Work in Progress | C54: =IFERROR(Datasheet!B63,0) -> 257.54 | D54: =IFERROR(Datasheet!C63,0) -> 1405.11 | E54: =IFERROR(Datasheet!D63,0) -> 209.67 | F54: =IFERROR(Datasheet!E63,0) -> 140.24 | G54: =IFERROR(Datasheet!F63,0) -> 182.98 | H54: =IFERROR(Datasheet!G63,0) -> 426.43 | I54: =IFERROR(Datasheet!H63,0) -> 1019.59 | J54: =IFERROR(Datasheet!I63,0) -> 2698.37 | ... L54: =IFERROR(Datasheet!K63,0) -> 1848.67 | M54: =L54 -> 1848.67
B55: Investments | C55: =IFERROR(Datasheet!B64,0) -> 2651.99 | D55: =IFERROR(Datasheet!C64,0) -> 2140.7 | E55: =IFERROR(Datasheet!D64,0) -> 2568.58 | F55: =IFERROR(Datasheet!E64,0) -> 2018.85 | G55: =IFERROR(Datasheet!F64,0) -> 4736.8 | H55: =IFERROR(Datasheet!G64,0) -> 3247.53 | I55: =IFERROR(Datasheet!H64,0) -> 4261.71 | J55: =IFERROR(Datasheet!I64,0) -> 4587.92 | ... L55: =IFERROR(Datasheet!K64,0) -> 7061.74 | M55: =L55 -> 7061.74
B56: Other Assets | C56: =IFERROR(Datasheet!B65-SUM(Datasheet!B67:B69),0) -> 1317.17 | D56: =IFERROR(Datasheet!C65-SUM(Datasheet!C67:C69),0) -> 1691.84 | E56: =IFERROR(Datasheet!D65-SUM(Datasheet!D67:D69),0) -> 1471.96 | F56: =IFERROR(Datasheet!E65-SUM(Datasheet!E67:E69),0) -> 1738.71 | G56: =IFERROR(Datasheet!F65-SUM(Datasheet!F67:F69),0) -> 2565.52 | H56: =IFERROR(Datasheet!G65-SUM(Datasheet!G67:G69),0) -> 2876.66 | I56: =IFERROR(Datasheet!H65-SUM(Datasheet!H67:H69),0) -> 3036.17 | J56: =IFERROR(Datasheet!I65-SUM(Datasheet!I67:I69),0) -> 3571.39 | ... L56: =IFERROR(Datasheet!K65-SUM(Datasheet!K67:K69),0) -> 4688.89 | M56: =L56 -> 4688.89
B57: Total Non Current Assets | C57: =SUM(C53:C56) -> 7530.44 | D57: =SUM(D53:D56) -> 8969.89 | E57: =SUM(E53:E56) -> 10746.77 | F57: =SUM(F53:F56) -> 10170.11 | G57: =SUM(G53:G56) -> 13343.82 | H57: =SUM(H53:H56) -> 12069.68 | I57: =SUM(I53:I56) -> 14087.93 | J57: =SUM(J53:J56) -> 18004.3 | ... L57: =SUM(L53:L56) -> 23239.58 | M57: =L57 -> 23239.58
B59: Receivables | C59: =IFERROR(Datasheet!B67,0) -> 1446.6 | D59: =IFERROR(Datasheet!C67,0) -> 1730.63 | E59: =IFERROR(Datasheet!D67,0) -> 1907.33 | F59: =IFERROR(Datasheet!E67,0) -> 1795.22 | G59: =IFERROR(Datasheet!F67,0) -> 2602.17 | H59: =IFERROR(Datasheet!G67,0) -> 3871.44 | I59: =IFERROR(Datasheet!H67,0) -> 4636.94 | J59: =IFERROR(Datasheet!I67,0) -> 4889.05 | ... L59: =IFERROR(Datasheet!K67,0) -> 4461.8 | M59: =L59 -> 4461.8
B60: Inventory | C60: =IFERROR(Datasheet!B68,0) -> 2626.94 | D60: =IFERROR(Datasheet!C68,0) -> 2658.31 | E60: =IFERROR(Datasheet!D68,0) -> 3149.86 | F60: =IFERROR(Datasheet!E68,0) -> 3389.81 | G60: =IFERROR(Datasheet!F68,0) -> 3798.6 | H60: =IFERROR(Datasheet!G68,0) -> 6152.98 | I60: =IFERROR(Datasheet!H68,0) -> 6210.64 | J60: =IFERROR(Datasheet!I68,0) -> 5923.41 | ... L60: =IFERROR(Datasheet!K68,0) -> 5743.69 | M60: =L60 -> 5743.69
B61: Cash & Bank | C61: =IFERROR(Datasheet!B69,0) -> 801.21 | D61: =IFERROR(Datasheet!C69,0) -> 404.65 | E61: =IFERROR(Datasheet!D69,0) -> 444.88 | F61: =IFERROR(Datasheet!E69,0) -> 782.83 | G61: =IFERROR(Datasheet!F69,0) -> 610.75 | H61: =IFERROR(Datasheet!G69,0) -> 864.33 | I61: =IFERROR(Datasheet!H69,0) -> 843.82 | J61: =IFERROR(Datasheet!I69,0) -> 1084.01 | ... L61: =IFERROR(Datasheet!K69,0) -> 1073.68 | M61: =L61 -> 1073.68
B62: Total Current Assets | C62: =SUM(C59:C61) -> 4874.75 | D62: =SUM(D59:D61) -> 4793.59 | E62: =SUM(E59:E61) -> 5502.07 | F62: =SUM(F59:F61) -> 5967.86 | G62: =SUM(G59:G61) -> 7011.52 | H62: =SUM(H59:H61) -> 10888.75 | I62: =SUM(I59:I61) -> 11691.4 | J62: =SUM(J59:J61) -> 11896.47 | ... L62: =SUM(L59:L61) -> 11279.17 | M62: =L62 -> 11279.17
B64: Total Assets | C64: =IFERROR(SUM(C57,C62),0) -> 12405.19 | D64: =IFERROR(SUM(D57,D62),0) -> 13763.48 | E64: =IFERROR(SUM(E57,E62),0) -> 16248.84 | F64: =IFERROR(SUM(F57,F62),0) -> 16137.97 | G64: =IFERROR(SUM(G57,G62),0) -> 20355.34 | H64: =IFERROR(SUM(H57,H62),0) -> 22958.43 | I64: =IFERROR(SUM(I57,I62),0) -> 25779.33 | J64: =IFERROR(SUM(J57,J62),0) -> 29900.77 | ... M64: =IFERROR(SUM(M57,M62),0) -> 34518.75
B66: CHECK | C66: =C51-C64 -> 0 | D66: =D51-D64 -> 0 | E66: =E51-E64 -> 0 | F66: =F51-F64 -> 0 | G66: =G51-G64 -> 0 | H66: =H51-H64 -> 0 | I66: =I51-I64 -> 0 | J66: =J51-J64 -> 0 | ... M66: =M51-M64 -> 0
A68: # | B68: Cash Flow Statement
B69: Operating Activities
B70: Profit from operations | C70: ='Raw FS'!E45 -> 3056 | D70: ='Raw FS'!F45 -> 3274 | E70: ='Raw FS'!G45 -> 3861 | F70: ='Raw FS'!H45 -> 4380 | G70: ='Raw FS'!I45 -> 4970 | H70: ='Raw FS'!J45 -> 4957 | I70: ='Raw FS'!K45 -> 6460 | J70: ='Raw FS'!L45 -> 7929 | ... L70: ='Raw FS'!N45 -> 7186 | M70: =L70 -> 7186
B71: Receivables | C71: ='Raw FS'!E46 -> -475 | D71: ='Raw FS'!F46 -> -483 | E71: ='Raw FS'!G46 -> -205 | F71: ='Raw FS'!H46 -> 160 | G71: ='Raw FS'!I46 -> -849 | H71: ='Raw FS'!J46 -> -1326 | I71: ='Raw FS'!K46 -> -834 | J71: ='Raw FS'!L46 -> -362 | ... L71: ='Raw FS'!N46 -> -274 | M71: =L71 -> -274
B72: Inventory | C72: ='Raw FS'!E47 -> -629 | D72: ='Raw FS'!F47 -> -39 | E72: ='Raw FS'!G47 -> -492 | F72: ='Raw FS'!H47 -> -251 | G72: ='Raw FS'!I47 -> -409 | H72: ='Raw FS'!J47 -> -2354 | I72: ='Raw FS'!K47 -> -56 | J72: ='Raw FS'!L47 -> 315 | ... L72: ='Raw FS'!N47 -> 976 | M72: =L72 -> 976
B73: Payables | C73: ='Raw FS'!E48 -> 501 | D73: ='Raw FS'!F48 -> 442 | E73: ='Raw FS'!G48 -> 287 | F73: ='Raw FS'!H48 -> -241 | G73: ='Raw FS'!I48 -> 1143 | H73: ='Raw FS'!J48 -> 644 | I73: ='Raw FS'!K48 -> -539 | J73: ='Raw FS'!L48 -> 269 | ... L73: ='Raw FS'!N48 -> 396 | M73: =L73 -> 396
B74: Other WC items | C74: ='Raw FS'!E49 -> 0 | D74: ='Raw FS'!F49 -> 0 | E74: ='Raw FS'!G49 -> 0 | F74: ='Raw FS'!H49 -> 0 | G74: ='Raw FS'!I49 -> -92 | H74: ='Raw FS'!J49 -> 242 | I74: ='Raw FS'!K49 -> 657 | J74: ='Raw FS'!L49 -> -212 | ... L74: ='Raw FS'!N49 -> 378 | M74: =L74 -> 378
B75: Working capital changes | C75: ='Raw FS'!E50 -> -603 | D75: ='Raw FS'!F50 -> -80 | E75: ='Raw FS'!G50 -> -410 | F75: ='Raw FS'!H50 -> -331 | G75: ='Raw FS'!I50 -> -206 | H75: ='Raw FS'!J50 -> -2795 | I75: ='Raw FS'!K50 -> -772 | J75: ='Raw FS'!L50 -> 10 | ... L75: ='Raw FS'!N50 -> 1476 | M75: =L75 -> 1476
B76: Direct taxes | C76: ='Raw FS'!E51 -> -925 | D76: ='Raw FS'!F51 -> -1081 | E76: ='Raw FS'!G51 -> -982 | F76: ='Raw FS'!H51 -> -1011 | G76: ='Raw FS'!I51 -> -1080 | H76: ='Raw FS'!J51 -> -1176 | I76: ='Raw FS'!K51 -> -1494 | J76: ='Raw FS'!L51 -> -1835 | ... L76: ='Raw FS'!N51 -> -1574 | M76: =L76 -> -1574
B77: Cash from Operating Activities | C77: =IFERROR(SUM(C70,C75,C76),0) -> 1528 | D77: =IFERROR(SUM(D70,D75,D76),0) -> 2113 | E77: =IFERROR(SUM(E70,E75,E76),0) -> 2469 | F77: =IFERROR(SUM(F70,F75,F76),0) -> 3038 | G77: =IFERROR(SUM(G70,G75,G76),0) -> 3684 | H77: =IFERROR(SUM(H70,H75,H76),0) -> 986 | I77: =IFERROR(SUM(I70,I75,I76),0) -> 4194 | J77: =IFERROR(SUM(J70,J75,J76),0) -> 6104 | ... M77: =IFERROR(SUM(M70,M75,M76),0) -> 7088
B80: Investing Activities
B81: Fixed assets purchased | C81: ='Raw FS'!E53 -> -684 | D81: ='Raw FS'!F53 -> -1426 | E81: ='Raw FS'!G53 -> -1151 | F81: ='Raw FS'!H53 -> -414 | G81: ='Raw FS'!I53 -> -289 | H81: ='Raw FS'!J53 -> -551 | I81: ='Raw FS'!K53 -> -1446 | J81: ='Raw FS'!L53 -> -2496 | ... L81: ='Raw FS'!N53 -> -1487 | M81: =L81 -> -1487
B82: Fixed assets sold | C82: ='Raw FS'!E54 -> 17 | D82: ='Raw FS'!F54 -> 17 | E82: ='Raw FS'!G54 -> 17 | F82: ='Raw FS'!H54 -> 37 | G82: ='Raw FS'!I54 -> 28 | H82: ='Raw FS'!J54 -> 40 | I82: ='Raw FS'!K54 -> 26 | J82: ='Raw FS'!L54 -> 5 | ... L82: ='Raw FS'!N54 -> 3 | M82: =L82 -> 3
B83: Investments purchased | C83: ='Raw FS'!E55 -> -153 | D83: ='Raw FS'!F55 -> -320 | E83: ='Raw FS'!G55 -> -573 | F83: ='Raw FS'!H55 -> -25 | G83: ='Raw FS'!I55 -> -140 | H83: ='Raw FS'!J55 -> 0 | I83: ='Raw FS'!K55 -> -146 | J83: ='Raw FS'!L55 -> -212 | ... L83: ='Raw FS'!N55 -> 0 | M83: =L83 -> 0
B84: Investments sold | C84: ='Raw FS'!E56 -> 357 | D84: ='Raw FS'!F56 -> 362 | E84: ='Raw FS'!G56 -> 733 | F84: ='Raw FS'!H56 -> 118 | G84: ='Raw FS'!I56 -> 272 | H84: ='Raw FS'!J56 -> 207 | I84: ='Raw FS'!K56 -> 446 | J84: ='Raw FS'!L56 -> 240 | ... L84: ='Raw FS'!N56 -> 1197 | M84: =L84 -> 1197
B85: Interest received | C85: ='Raw FS'!E57 -> 32 | D85: ='Raw FS'!F57 -> 39 | E85: ='Raw FS'!G57 -> 40 | F85: ='Raw FS'!H57 -> 65 | G85: ='Raw FS'!I57 -> 73 | H85: ='Raw FS'!J57 -> 77 | I85: ='Raw FS'!K57 -> 87 | J85: ='Raw FS'!L57 -> 135 | ... L85: ='Raw FS'!N57 -> 153 | M85: =L85 -> 153
B86: Dividends received | C86: ='Raw FS'!E58 -> 74 | D86: ='Raw FS'!F58 -> 38 | E86: ='Raw FS'!G58 -> 40 | F86: ='Raw FS'!H58 -> 27 | G86: ='Raw FS'!I58 -> 8 | H86: ='Raw FS'!J58 -> 15 | I86: ='Raw FS'!K58 -> 56 | J86: ='Raw FS'!L58 -> 129 | ... L86: ='Raw FS'!N58 -> 118 | M86: =L86 -> 118
B87: Investment in group cos | C87: ='Raw FS'!E59 -> 0 | D87: ='Raw FS'!F59 -> 0 | E87: ='Raw FS'!G59 -> 0 | F87: ='Raw FS'!H59 -> 0 | G87: ='Raw FS'!I59 -> 0 | H87: ='Raw FS'!J59 -> 0 | I87: ='Raw FS'!K59 -> -180 | J87: ='Raw FS'!L59 -> 0 | ... L87: ='Raw FS'!N59 -> 0 | M87: =L87 -> 0
B88: Redemp n Canc of Shares | C88: ='Raw FS'!E60 -> 0 | D88: ='Raw FS'!F60 -> 141 | E88: ='Raw FS'!G60 -> 0 | F88: ='Raw FS'!H60 -> 17 | G88: ='Raw FS'!I60 -> 0 | H88: ='Raw FS'!J60 -> 0 | I88: ='Raw FS'!K60 -> 0 | J88: ='Raw FS'!L60 -> 0 | ... L88: ='Raw FS'!N60 -> 0 | M88: =L88 -> 0
B89: Acquisition of companies | C89: ='Raw FS'!E61 -> 0 | D89: ='Raw FS'!F61 -> -525 | E89: ='Raw FS'!G61 -> 0 | F89: ='Raw FS'!H61 -> 0 | G89: ='Raw FS'!I61 -> 0 | H89: ='Raw FS'!J61 -> 0 | I89: ='Raw FS'!K61 -> 0 | J89: ='Raw FS'!L61 -> 0 | ... L89: ='Raw FS'!N61 -> 0 | M89: =L89 -> 0
B90: Other investing items | C90: ='Raw FS'!E62 -> -324 | D90: ='Raw FS'!F62 -> 118 | E90: ='Raw FS'!G62 -> -24 | F90: ='Raw FS'!H62 -> -343 | G90: ='Raw FS'!I62 -> -493 | H90: ='Raw FS'!J62 -> -105 | I90: ='Raw FS'!K62 -> -126 | J90: ='Raw FS'!L62 -> -350 | ... L90: ='Raw FS'!N62 -> -1312 | M90: =L90 -> -1312
B91: Cash From Investing Activities | C91: =IFERROR(SUM(C81:C90),0) -> -681 | D91: =IFERROR(SUM(D81:D90),0) -> -1556 | E91: =IFERROR(SUM(E81:E90),0) -> -918 | F91: =IFERROR(SUM(F81:F90),0) -> -518 | G91: =IFERROR(SUM(G81:G90),0) -> -541 | H91: =IFERROR(SUM(H81:H90),0) -> -317 | I91: =IFERROR(SUM(I81:I90),0) -> -1283 | J91: =IFERROR(SUM(J81:J90),0) -> -2549 | ... M91: =IFERROR(SUM(M81:M90),0) -> -1328
B94: Financing Activities
B95: Proceeds from shares | C95: ='Raw FS'!E64 -> 0 | D95: ='Raw FS'!F64 -> 0 | E95: ='Raw FS'!G64 -> 0 | F95: ='Raw FS'!H64 -> 0 | G95: ='Raw FS'!I64 -> 0 | H95: ='Raw FS'!J64 -> 0 | I95: ='Raw FS'!K64 -> 0 | J95: ='Raw FS'!L64 -> 1 | ... L95: ='Raw FS'!N64 -> 0 | M95: =L95 -> 0
B96: Proceeds from borrowings | C96: ='Raw FS'!E65 -> 271 | D96: ='Raw FS'!F65 -> 10 | E96: ='Raw FS'!G65 -> 243 | F96: ='Raw FS'!H65 -> 18 | G96: ='Raw FS'!I65 -> 155 | H96: ='Raw FS'!J65 -> 418 | I96: ='Raw FS'!K65 -> 254 | J96: ='Raw FS'!L65 -> 101 | ... L96: ='Raw FS'!N65 -> 1279 | M96: =L96 -> 1279
B97: Repayment of borrowings | C97: ='Raw FS'!E66 -> -58 | D97: ='Raw FS'!F66 -> -54 | E97: ='Raw FS'!G66 -> -26 | F97: ='Raw FS'!H66 -> -482 | G97: ='Raw FS'!I66 -> -14 | H97: ='Raw FS'!J66 -> -8 | I97: ='Raw FS'!K66 -> -25 | J97: ='Raw FS'!L66 -> -98 | ... L97: ='Raw FS'!N66 -> -452 | M97: =L97 -> -452
B98: Interest paid fin | C98: ='Raw FS'!E67 -> -36 | D98: ='Raw FS'!F67 -> -35 | E98: ='Raw FS'!G67 -> -106 | F98: ='Raw FS'!H67 -> -101 | G98: ='Raw FS'!I67 -> -89 | H98: ='Raw FS'!J67 -> -94 | I98: ='Raw FS'!K67 -> -142 | J98: ='Raw FS'!L67 -> -191 | ... L98: ='Raw FS'!N67 -> -228 | M98: =L98 -> -228
B99: Dividends paid | C99: ='Raw FS'!E68 -> -947 | D99: ='Raw FS'!F68 -> -1218 | E99: ='Raw FS'!G68 -> -1049 | F99: ='Raw FS'!H68 -> -2121 | G99: ='Raw FS'!I68 -> -499 | H99: ='Raw FS'!J68 -> -1763 | I99: ='Raw FS'!K68 -> -1936 | J99: ='Raw FS'!L68 -> -2551 | ... L99: ='Raw FS'!N68 -> -2425 | M99: =L99 -> -2425
B100: Financial liabilities | C100: ='Raw FS'!E69 -> 0 | D100: ='Raw FS'!F69 -> 0 | E100: ='Raw FS'!G69 -> -180 | F100: ='Raw FS'!H69 -> -179 | G100: ='Raw FS'!I69 -> -203 | H100: ='Raw FS'!J69 -> -221 | I100: ='Raw FS'!K69 -> -256 | J100: ='Raw FS'!L69 -> -286 | ... L100: ='Raw FS'!N69 -> -340 | M100: =L100 -> -340
B101: Other financing items | C101: ='Raw FS'!E70 -> 13 | D101: ='Raw FS'!F70 -> -82 | E101: ='Raw FS'!G70 -> 0 | F101: ='Raw FS'!H70 -> -6 | G101: ='Raw FS'!I70 -> 0 | H101: ='Raw FS'!J70 -> -140 | I101: ='Raw FS'!K70 -> -36 | J101: ='Raw FS'!L70 -> 41 | ... L101: ='Raw FS'!N70 -> -210 | M101: =L101 -> -210
B102: Cash from Financing Activities | C102: =IFERROR(SUM(C95:C101),0) -> -757 | D102: =IFERROR(SUM(D95:D101),0) -> -1379 | E102: =IFERROR(SUM(E95:E101),0) -> -1118 | F102: =IFERROR(SUM(F95:F101),0) -> -2871 | G102: =IFERROR(SUM(G95:G101),0) -> -650 | H102: =IFERROR(SUM(H95:H101),0) -> -1808 | I102: =IFERROR(SUM(I95:I101),0) -> -2141 | J102: =IFERROR(SUM(J95:J101),0) -> -2983 | ... M102: =IFERROR(SUM(M95:M101),0) -> -2376
B103: NET CASH FLOW | C103: =IFERROR(C77+C91+C102,0) -> 90 | D103: =IFERROR(D77+D91+D102,0) -> -822 | E103: =IFERROR(E77+E91+E102,0) -> 433 | F103: =IFERROR(F77+F91+F102,0) -> -351 | G103: =IFERROR(G77+G91+G102,0) -> 2493 | H103: =IFERROR(H77+H91+H102,0) -> -1139 | I103: =IFERROR(I77+I91+I102,0) -> 770 | J103: =IFERROR(J77+J91+J102,0) -> 572 | ... L103: =IFERROR(L77+L91+L102,0) -> 3384 | M103: 3676

Sheet Ratio Analysis
B2: ="Ratio Analysis"&" - "&Datasheet!$B$1 -> Ratio Analysis - ASIAN PAINTS LTD
B3: Years | C3: 42825 | D3: 43190 | E3: 43555 | F3: 43921 | G3: 44286 | H3: 44651 | I3: 45016 | J3: 45382 | K3: 45747 | L3: 46112 | M3: Trend | N3: Mean | O3: Median
B5: Sales Growth | C5: =IFERROR(HistoricalFS!C7,0) -> - | D5: =IFERROR(HistoricalFS!D7,0) -> 0.11702039 | E5: =IFERROR(HistoricalFS!E7,0) -> 0.14357472 | F5: =IFERROR(HistoricalFS!F7,0) -> 0.050473671 | G5: =IFERROR(HistoricalFS!G7,0) -> 0.074292288 | H5: =IFERROR(HistoricalFS!H7,0) -> 0.34028285 | I5: =IFERROR(HistoricalFS!I7,0) -> 0.18512278 | J5: =IFERROR(HistoricalFS!J7,0) -> 0.029173127 | ... L5: =IFERROR(HistoricalFS!L7,0) -> 0.049487961 | N5: =IFERROR(AVERAGE(D5:L5),0) -> 0.10496194 | O5: =IFERROR(MEDIAN(D5:L5),0) -> 0.074292288
B6: EBITDA Growth | C6: - | D6: =IFERROR(HistoricalFS!D18/HistoricalFS!C18-1,0) -> 0.070229411 | E6: =IFERROR(HistoricalFS!E18/HistoricalFS!D18-1,0) -> 0.17507124 | F6: =IFERROR(HistoricalFS!F18/HistoricalFS!E18-1,0) -> 0.10540141 | G6: =IFERROR(HistoricalFS!G18/HistoricalFS!F18-1,0) -> 0.16671512 | H6: =IFERROR(HistoricalFS!H18/HistoricalFS!G18-1,0) -> -0.010707225 | I6: =IFERROR(HistoricalFS!I18/HistoricalFS!H18-1,0) -> 0.30315325 | J6: =IFERROR(HistoricalFS!J18/HistoricalFS!I18-1,0) -> 0.21168912 | K6: =IFERROR(HistoricalFS!K18/HistoricalFS!J18-1,0) -> -0.20814425 | L6: =IFERROR(HistoricalFS!L18/HistoricalFS!K18-1,0) -> 0.11546716 | N6: =IFERROR(AVERAGE(D6:L6),0) -> 0.10320836 | O6: =IFERROR(MEDIAN(D6:L6),0) -> 0.11546716
B7: EBIT Growth | C7: - | D7: =IFERROR(SUM(HistoricalFS!D27,HistoricalFS!D21)/SUM(HistoricalFS!C27,HistoricalFS!C21)-1,0) -> 0.069414096 | E7: =IFERROR(SUM(HistoricalFS!E27,HistoricalFS!E21)/SUM(HistoricalFS!D27,HistoricalFS!D21)-1,0) -> 0.10524206 | F7: =IFERROR(SUM(HistoricalFS!F27,HistoricalFS!F21)/SUM(HistoricalFS!E27,HistoricalFS!E21)-1,0) -> 0.075878198 | G7: =IFERROR(SUM(HistoricalFS!G27,HistoricalFS!G21)/SUM(HistoricalFS!F27,HistoricalFS!F21)-1,0) -> 0.20201285 | H7: =IFERROR(SUM(HistoricalFS!H27,HistoricalFS!H21)/SUM(HistoricalFS!G27,HistoricalFS!G21)-1,0) -> -0.018964995 | I7: =IFERROR(SUM(HistoricalFS!I27,HistoricalFS!I21)/SUM(HistoricalFS!H27,HistoricalFS!H21)-1,0) -> 0.35477334 | J7: =IFERROR(SUM(HistoricalFS!J27,HistoricalFS!J21)/SUM(HistoricalFS!I27,HistoricalFS!I21)-1,0) -> 0.24624293 | K7: =IFERROR(SUM(HistoricalFS!K27,HistoricalFS!K21)/SUM(HistoricalFS!J27,HistoricalFS!J21)-1,0) -> -0.26026667 | L7: =IFERROR(SUM(HistoricalFS!L27,HistoricalFS!L21)/SUM(HistoricalFS!K27,HistoricalFS!K21)-1,0) -> 0.098598959 | N7: =IFERROR(AVERAGE(D7:L7),0) -> 0.096992308 | O7: =IFERROR(MEDIAN(D7:L7),0) -> 0.098598959
B8: Net Profit Growth | C8: - | D8: =IFERROR(HistoricalFS!D33/HistoricalFS!C33-1,0) -> 0.049310335 | E8: =IFERROR(HistoricalFS!E33/HistoricalFS!D33-1,0) -> 0.098324352 | F8: =IFERROR(HistoricalFS!F33/HistoricalFS!E33-1,0) -> 0.25323249 | G8: =IFERROR(HistoricalFS!G33/HistoricalFS!F33-1,0) -> 0.18605332 | H8: =IFERROR(HistoricalFS!H33/HistoricalFS!G33-1,0) -> -0.029971131 | I8: =IFERROR(HistoricalFS!I33/HistoricalFS!H33-1,0) -> 0.34957493 | J8: =IFERROR(HistoricalFS!J33/HistoricalFS!I33-1,0) -> 0.25847333 | K8: =IFERROR(HistoricalFS!K33/HistoricalFS!J33-1,0) -> -0.29075755 | L8: =IFERROR(HistoricalFS!L33/HistoricalFS!K33-1,0) -> 0.091451381 | N8: =IFERROR(AVERAGE(D8:L8),0) -> 0.10729905 | O8: =IFERROR(MEDIAN(D8:L8),0) -> 0.098324352
B9: Dividend Growth | C9: - | D9: =IFERROR(HistoricalFS!D41/HistoricalFS!C41-1,0) -> -0.15534727 | E9: =IFERROR(HistoricalFS!E41/HistoricalFS!D41-1,0) -> 0.20690234 | F9: =IFERROR(HistoricalFS!F41/HistoricalFS!E41-1,0) -> 0.14285714 | G9: =IFERROR(HistoricalFS!G41/HistoricalFS!F41-1,0) -> 0.48749826 | H9: =IFERROR(HistoricalFS!H41/HistoricalFS!G41-1,0) -> 0.072831553 | I9: =IFERROR(HistoricalFS!I41/HistoricalFS!H41-1,0) -> 0.33942522 | J9: =IFERROR(HistoricalFS!J41/HistoricalFS!I41-1,0) -> 0.29824618 | K9: =IFERROR(HistoricalFS!K41/HistoricalFS!J41-1,0) -> -0.25525494 | L9: =IFERROR(HistoricalFS!L41/HistoricalFS!K41-1,0) -> 0.1088691 | N9: =IFERROR(AVERAGE(D9:L9),0) -> 0.13844751 | O9: =IFERROR(MEDIAN(D9:L9),0) -> 0.14285714
B11: Gross Margins | C11: =IFERROR(HistoricalFS!C13,0) -> 0.35382642 | D11: =IFERROR(HistoricalFS!D13,0) -> 0.33465264 | E11: =IFERROR(HistoricalFS!E13,0) -> 0.32922439 | F11: =IFERROR(HistoricalFS!F13,0) -> 0.34897545 | G11: =IFERROR(HistoricalFS!G13,0) -> 0.35360357 | H11: =IFERROR(HistoricalFS!H13,0) -> 0.2924514 | I11: =IFERROR(HistoricalFS!I13,0) -> 0.31088224 | J11: =IFERROR(HistoricalFS!J13,0) -> 0.35173503 | ... L11: =IFERROR(HistoricalFS!L13,0) -> 0.33987372 | N11: =IFERROR(AVERAGE(C11:L11),0) -> 0.33445021 | O11: =IFERROR(MEDIAN(C11:L11),0) -> 0.33726318
B12: EBITDA Margin | C12: =IFERROR(HistoricalFS!C19,0) -> 0.19876258 | D12: =IFERROR(HistoricalFS!D19,0) -> 0.19043659 | E12: =IFERROR(HistoricalFS!E19,0) -> 0.19568163 | F12: =IFERROR(HistoricalFS!F19,0) -> 0.20591354 | G12: =IFERROR(HistoricalFS!G19,0) -> 0.22362856 | H12: =IFERROR(HistoricalFS!H19,0) -> 0.16506525 | I12: =IFERROR(HistoricalFS!I19,0) -> 0.18150467 | J12: =IFERROR(HistoricalFS!J19,0) -> 0.21369313 | ... L12: =IFERROR(HistoricalFS!L19,0) -> 0.18828172 | N12: =IFERROR(AVERAGE(C12:L12),0) -> 0.19401126 | O12: =IFERROR(MEDIAN(C12:L12),0) -> 0.19305911
B13: EBIT Margin | C13: =IFERROR(SUM(HistoricalFS!C27,HistoricalFS!C21)/HistoricalFS!C6,0) -> 0.17653511 | D13: =IFERROR(SUM(HistoricalFS!D27,HistoricalFS!D21)/HistoricalFS!D6,0) -> 0.16901136 | E13: =IFERROR(SUM(HistoricalFS!E27,HistoricalFS!E21)/HistoricalFS!E6,0) -> 0.16334609 | F13: =IFERROR(SUM(HistoricalFS!F27,HistoricalFS!F21)/HistoricalFS!F6,0) -> 0.16729643 | G13: =IFERROR(SUM(HistoricalFS!G27,HistoricalFS!G21)/HistoricalFS!G6,0) -> 0.18718599 | H13: =IFERROR(SUM(HistoricalFS!H27,HistoricalFS!H21)/HistoricalFS!H6,0) -> 0.13701287 | I13: =IFERROR(SUM(HistoricalFS!I27,HistoricalFS!I21)/HistoricalFS!I6,0) -> 0.15662629 | J13: =IFERROR(SUM(HistoricalFS!J27,HistoricalFS!J21)/HistoricalFS!J6,0) -> 0.18966139 | ... L13: =IFERROR(SUM(HistoricalFS!L27,HistoricalFS!L21)/HistoricalFS!L6,0) -> 0.15374749 | N13: =IFERROR(AVERAGE(C13:L13),0) -> 0.16472975 | O13: =IFERROR(MEDIAN(C13:L13),0) -> 0.16532126
B14: EBT Margin | C14: =IFERROR(HistoricalFS!C28,0) -> 0.17405668 | D14: =IFERROR(HistoricalFS!D28,0) -> 0.1665465 | E14: =IFERROR(HistoricalFS!E28,0) -> 0.15760444 | F14: =IFERROR(HistoricalFS!F28,0) -> 0.16223341 | G14: =IFERROR(HistoricalFS!G28,0) -> 0.18296589 | H14: =IFERROR(HistoricalFS!H28,0) -> 0.13373432 | I14: =IFERROR(HistoricalFS!I28,0) -> 0.15243795 | J14: =IFERROR(HistoricalFS!J28,0) -> 0.1838811 | ... L14: =IFERROR(HistoricalFS!L28,0) -> 0.14825591 | N14: =IFERROR(AVERAGE(C14:L14),0) -> 0.1601895 | O14: =IFERROR(MEDIAN(C14:L14),0) -> 0.15991893
B15: Net Profit Margin | C15: =IFERROR(HistoricalFS!C34,0) -> 0.1114295 | D15: =IFERROR(HistoricalFS!D34,0) -> 0.10467501 | E15: =IFERROR(HistoricalFS!E34,0) -> 0.1005331 | F15: =IFERROR(HistoricalFS!F34,0) -> 0.11993766 | G15: =IFERROR(HistoricalFS!G34,0) -> 0.13241504 | H15: =IFERROR(HistoricalFS!H34,0) -> 0.095835303 | I15: =IFERROR(HistoricalFS!I34,0) -> 0.10913377 | J15: =IFERROR(HistoricalFS!J34,0) -> 0.13344882 | ... L15: =IFERROR(HistoricalFS!L34,0) -> 0.1030454 | N15: =IFERROR(AVERAGE(C15:L15),0) -> 0.11095372 | O15: =IFERROR(MEDIAN(C15:L15),0) -> 0.10690439
B17: Sales Expense % Sales | C17: =IFERROR(HistoricalFS!C16,0) -> 0.15506384 | D17: =IFERROR(HistoricalFS!D16,0) -> 0.14421604 | E17: =IFERROR(HistoricalFS!E16,0) -> 0.13354276 | F17: =IFERROR(HistoricalFS!F16,0) -> 0.14306191 | G17: =IFERROR(HistoricalFS!G16,0) -> 0.12997501 | H17: =IFERROR(HistoricalFS!H16,0) -> 0.12738615 | I17: =IFERROR(HistoricalFS!I16,0) -> 0.12937757 | J17: =IFERROR(HistoricalFS!J16,0) -> 0.1380419 | ... L17: =IFERROR(HistoricalFS!L16,0) -> 0.151592 | N17: =IFERROR(AVERAGE(C17:L17),0) -> 0.14043895 | O17: =IFERROR(MEDIAN(C17:L17),0) -> 0.1405519
B18: Depreciation % Gross Block | C18: =IFERROR(HistoricalFS!C25,0) -> 0.085536536 | D18: =IFERROR(HistoricalFS!D25,0) -> 0.07661424 | E18: =IFERROR(HistoricalFS!E25,0) -> 0.076420587 | F18: =IFERROR(HistoricalFS!F25,0) -> 0.094240522 | G18: =IFERROR(HistoricalFS!G25,0) -> 0.094288608 | H18: =IFERROR(HistoricalFS!H25,0) -> 0.095614898 | I18: =IFERROR(HistoricalFS!I25,0) -> 0.088675072 | J18: =IFERROR(HistoricalFS!J25,0) -> 0.073395285 | ... L18: =IFERROR(HistoricalFS!L25,0) -> 0.08023309 | N18: =IFERROR(AVERAGE(C18:L18),0) -> 0.083781407 | O18: =IFERROR(MEDIAN(C18:L18),0) -> 0.082884813
B19: Operating Income % Sales | C19: =IFERROR(SUM(HistoricalFS!C27,HistoricalFS!C21)/HistoricalFS!C6,0) -> 0.17653511 | D19: =IFERROR(SUM(HistoricalFS!D27,HistoricalFS!D21)/HistoricalFS!D6,0) -> 0.16901136 | E19: =IFERROR(SUM(HistoricalFS!E27,HistoricalFS!E21)/HistoricalFS!E6,0) -> 0.16334609 | F19: =IFERROR(SUM(HistoricalFS!F27,HistoricalFS!F21)/HistoricalFS!F6,0) -> 0.16729643 | G19: =IFERROR(SUM(HistoricalFS!G27,HistoricalFS!G21)/HistoricalFS!G6,0) -> 0.18718599 | H19: =IFERROR(SUM(HistoricalFS!H27,HistoricalFS!H21)/HistoricalFS!H6,0) -> 0.13701287 | I19: =IFERROR(SUM(HistoricalFS!I27,HistoricalFS!I21)/HistoricalFS!I6,0) -> 0.15662629 | J19: =IFERROR(SUM(HistoricalFS!J27,HistoricalFS!J21)/HistoricalFS!J6,0) -> 0.18966139 | ... L19: =IFERROR(SUM(HistoricalFS!L27,HistoricalFS!L21)/HistoricalFS!L6,0) -> 0.15374749 | N19: =IFERROR(AVERAGE(C19:L19),0) -> 0.16472975 | O19: =IFERROR(MEDIAN(C19:L19),0) -> 0.16532126
B21: Return on Capital Employed | C21: =IFERROR((HistoricalFS!C18-HistoricalFS!C24)/SUM(HistoricalFS!C47:C49),0) -> 0.32568534 | D21: =IFERROR((HistoricalFS!D18-HistoricalFS!D24)/SUM(HistoricalFS!D47:D49),0) -> 0.31793919 | E21: =IFERROR((HistoricalFS!E18-HistoricalFS!E24)/SUM(HistoricalFS!E47:E49),0) -> 0.29126565 | F21: =IFERROR((HistoricalFS!F18-HistoricalFS!F24)/SUM(HistoricalFS!F47:F49),0) -> 0.30059314 | G21: =IFERROR((HistoricalFS!G18-HistoricalFS!G24)/SUM(HistoricalFS!G47:G49),0) -> 0.29241025 | H21: =IFERROR((HistoricalFS!H18-HistoricalFS!H24)/SUM(HistoricalFS!H47:H49),0) -> 0.25893857 | I21: =IFERROR((HistoricalFS!I18-HistoricalFS!I24)/SUM(HistoricalFS!I47:I49),0) -> 0.30135929 | J21: =IFERROR((HistoricalFS!J18-HistoricalFS!J24)/SUM(HistoricalFS!J47:J49),0) -> 0.31750609 | ... L21: =IFERROR((HistoricalFS!L18-HistoricalFS!L24)/SUM(HistoricalFS!L47:L49),0) -> 0.21623587 | N21: =IFERROR(AVERAGE(C21:L21),0) -> 0.28515252 | O21: =IFERROR(MEDIAN(C21:L21),0) -> 0.2965017
B22: Retained Earnings % | C22: =IFERROR(HistoricalFS!C44,0) -> 0.41133852 | D22: =IFERROR(HistoricalFS!D44,0) -> 0.52615112 | E22: =IFERROR(HistoricalFS!E44,0) -> 0.47930744 | F22: =IFERROR(HistoricalFS!F44,0) -> 0.52516614 | G22: =IFERROR(HistoricalFS!G44,0) -> 0.40448332 | H22: =IFERROR(HistoricalFS!H44,0) -> 0.34137106 | I22: =IFERROR(HistoricalFS!I44,0) -> 0.34632439 | J22: =IFERROR(HistoricalFS!J44,0) -> 0.3256656 | ... L22: =IFERROR(HistoricalFS!L44,0) -> 0.28061046 | N22: =IFERROR(AVERAGE(C22:L22),0) -> 0.39323284 | O22: =IFERROR(MEDIAN(C22:L22),0) -> 0.37540386
B23: Return on Equity % | C23: =IFERROR(HistoricalFS!C33/SUM(HistoricalFS!C47:C48),0) -> 0.22072255 | D23: =IFERROR(HistoricalFS!D33/SUM(HistoricalFS!D47:D48),0) -> 0.20940093 | E23: =IFERROR(HistoricalFS!E33/SUM(HistoricalFS!E47:E48),0) -> 0.20424051 | F23: =IFERROR(HistoricalFS!F33/SUM(HistoricalFS!F47:F48),0) -> 0.23929434 | G23: =IFERROR(HistoricalFS!G33/SUM(HistoricalFS!G47:G48),0) -> 0.22450686 | H23: =IFERROR(HistoricalFS!H33/SUM(HistoricalFS!H47:H48),0) -> 0.20192723 | I23: =IFERROR(HistoricalFS!I33/SUM(HistoricalFS!I47:I48),0) -> 0.23535617 | J23: =IFERROR(HistoricalFS!J33/SUM(HistoricalFS!J47:J48),0) -> 0.25291831 | ... L23: =IFERROR(HistoricalFS!L33/SUM(HistoricalFS!L47:L48),0) -> 0.17156983 | N23: =IFERROR(AVERAGE(C23:L23),0) -> 0.2133108 | O23: =IFERROR(MEDIAN(C23:L23),0) -> 0.21506174
B24: Self Sustained Growth Rate | C24: =IFERROR(C22*C23,0) -> 0.090791687 | D24: =IFERROR(D22*D23,0) -> 0.11017654 | E24: =IFERROR(E22*E23,0) -> 0.097893998 | F24: =IFERROR(F22*F23,0) -> 0.12566929 | G24: =IFERROR(G22*G23,0) -> 0.090809282 | H24: =IFERROR(H22*H23,0) -> 0.068932112 | I24: =IFERROR(I22*I23,0) -> 0.081509583 | J24: =IFERROR(J22*J23,0) -> 0.082366793 | ... L24: =IFERROR(L22*L23,0) -> 0.048144289 | N24: =IFERROR(AVERAGE(C24:L24),0) -> 0.084684406 | O24: =IFERROR(MEDIAN(C24:L24),0) -> 0.08657924
B25: Interest Coverage Ratio | C25: =IFERROR(SUM(HistoricalFS!C27,HistoricalFS!C21)/HistoricalFS!C21,0) -> 71.22877 | D25: =IFERROR(SUM(HistoricalFS!D27,HistoricalFS!D21)/HistoricalFS!D21,0) -> 68.568604 | E25: =IFERROR(SUM(HistoricalFS!E27,HistoricalFS!E21)/HistoricalFS!E21,0) -> 28.449353 | F25: =IFERROR(SUM(HistoricalFS!F27,HistoricalFS!F21)/HistoricalFS!F21,0) -> 33.042803 | G25: =IFERROR(SUM(HistoricalFS!G27,HistoricalFS!G21)/HistoricalFS!G21,0) -> 44.355888 | H25: =IFERROR(SUM(HistoricalFS!H27,HistoricalFS!H21)/HistoricalFS!H21,0) -> 41.790693 | I25: =IFERROR(SUM(HistoricalFS!I27,HistoricalFS!I21)/HistoricalFS!I21,0) -> 37.395777 | J25: =IFERROR(SUM(HistoricalFS!J27,HistoricalFS!J21)/HistoricalFS!J21,0) -> 32.811717 | ... L25: =IFERROR(SUM(HistoricalFS!L27,HistoricalFS!L21)/HistoricalFS!L21,0) -> 27.99693 | N25: =IFERROR(AVERAGE(C25:L25),0) -> 40.757635 | O25: =IFERROR(MEDIAN(C25:L25),0) -> 35.21929
B27: Debtor Turnover Ratio | D27: =IFERROR(HistoricalFS!D6/AVERAGE('Raw FS'!E32:F32),0) -> 10.588137 | E27: =IFERROR(HistoricalFS!E6/AVERAGE('Raw FS'!F32:G32),0) -> 10.577312 | F27: =IFERROR(HistoricalFS!F6/AVERAGE('Raw FS'!G32:H32),0) -> 10.919098 | G27: =IFERROR(HistoricalFS!G6/AVERAGE('Raw FS'!H32:I32),0) -> 9.8761838 | H27: =IFERROR(HistoricalFS!H6/AVERAGE('Raw FS'!I32:J32),0) -> 8.9915897 | I27: =IFERROR(HistoricalFS!I6/AVERAGE('Raw FS'!J32:K32),0) -> 8.1073319 | J27: =IFERROR(HistoricalFS!J6/AVERAGE('Raw FS'!K32:L32),0) -> 7.4521793 | K27: =IFERROR(HistoricalFS!K6/AVERAGE('Raw FS'!L32:M32),0) -> 7.3683842 | L27: =IFERROR(HistoricalFS!L6/AVERAGE('Raw FS'!M32:N32),0) -> 8.1092844 | N27: =IFERROR(AVERAGE(D27:L27),0) -> 9.1099444 | O27: =IFERROR(MEDIAN(D27:L27),0) -> 8.9915897
B28: Creditor Turnover ratio | D28: =IFERROR(HistoricalFS!D9/AVERAGE('Raw FS'!E13:F13),0) -> 5.4833064 | E28: =IFERROR(HistoricalFS!E9/AVERAGE('Raw FS'!F13:G13),0) -> 5.6679007 | F28: =IFERROR(HistoricalFS!F9/AVERAGE('Raw FS'!G13:H13),0) -> 5.8079982 | G28: =IFERROR(HistoricalFS!G9/AVERAGE('Raw FS'!H13:I13),0) -> 5.0888579 | H28: =IFERROR(HistoricalFS!H9/AVERAGE('Raw FS'!I13:J13),0) -> 5.4595174 | I28: =IFERROR(HistoricalFS!I9/AVERAGE('Raw FS'!J13:K13),0) -> 6.094807 | J28: =IFERROR(HistoricalFS!J9/AVERAGE('Raw FS'!K13:L13),0) -> 6.1639405 | K28: =IFERROR(HistoricalFS!K9/AVERAGE('Raw FS'!L13:M13),0) -> 5.922977 | L28: =IFERROR(HistoricalFS!L9/AVERAGE('Raw FS'!M13:N13),0) -> 6.092499 | N28: =IFERROR(AVERAGE(D28:L28),0) -> 5.7535338 | O28: =IFERROR(MEDIAN(D28:L28),0) -> 5.8079982
B29: Inventory Turnover Ratio | D29: =IFERROR(HistoricalFS!D9/AVERAGE(HistoricalFS!C60:D60),0) -> 4.236004 | E29: =IFERROR(HistoricalFS!E9/AVERAGE(HistoricalFS!D60:E60),0) -> 4.4440194 | F29: =IFERROR(HistoricalFS!F9/AVERAGE(HistoricalFS!E60:F60),0) -> 4.0240624 | G29: =IFERROR(HistoricalFS!G9/AVERAGE(HistoricalFS!F60:G60),0) -> 3.9049164 | H29: =IFERROR(HistoricalFS!H9/AVERAGE(HistoricalFS!G60:H60),0) -> 4.1381509 | I29: =IFERROR(HistoricalFS!I9/AVERAGE(HistoricalFS!H60:I60),0) -> 3.8446183 | J29: =IFERROR(HistoricalFS!J9/AVERAGE(HistoricalFS!I60:J60),0) -> 3.7926315 | K29: =IFERROR(HistoricalFS!K9/AVERAGE(HistoricalFS!J60:K60),0) -> 3.5975394 | L29: =IFERROR(HistoricalFS!L9/AVERAGE(HistoricalFS!K60:L60),0) -> 3.7695106 | N29: =IFERROR(AVERAGE(D29:L29),0) -> 3.9723837 | O29: =IFERROR(MEDIAN(D29:L29),0) -> 3.9049164
B30: Fixed Asset Turnover ratio | D30: =IFERROR(HistoricalFS!D6/AVERAGE(HistoricalFS!C53:D53),0) -> 4.7824326 | E30: =IFERROR(HistoricalFS!E6/AVERAGE(HistoricalFS!D53:E53),0) -> 3.7619525 | F30: =IFERROR(HistoricalFS!F6/AVERAGE(HistoricalFS!E53:F53),0) -> 3.1657069 | G30: =IFERROR(HistoricalFS!G6/AVERAGE(HistoricalFS!F53:G53),0) -> 3.5797699 | H30: =IFERROR(HistoricalFS!H6/AVERAGE(HistoricalFS!G53:H53),0) -> 5.1155483 | I30: =IFERROR(HistoricalFS!I6/AVERAGE(HistoricalFS!H53:I53),0) -> 6.1098417 | J30: =IFERROR(HistoricalFS!J6/AVERAGE(HistoricalFS!I53:J53),0) -> 5.4957823 | K30: =IFERROR(HistoricalFS!K6/AVERAGE(HistoricalFS!J53:K53),0) -> 4.1432395 | L30: =IFERROR(HistoricalFS!L6/AVERAGE(HistoricalFS!K53:L53),0) -> 3.7733641 | N30: =IFERROR(AVERAGE(D30:L30),0) -> 4.4364042 | O30: =IFERROR(MEDIAN(D30:L30),0) -> 4.1432395
B31: Capital Turonver Ratio | D31: =IFERROR(HistoricalFS!D6/AVERAGE(SUM(HistoricalFS!D47:D48),SUM(HistoricalFS!C47:C48)),0) -> 2.1012144 | E31: =IFERROR(HistoricalFS!E6/AVERAGE(SUM(HistoricalFS!E47:E48),SUM(HistoricalFS!D47:D48)),0) -> 2.1520459 | F31: =IFERROR(HistoricalFS!F6/AVERAGE(SUM(HistoricalFS!F47:F48),SUM(HistoricalFS!E47:E48)),0) -> 2.0622977 | G31: =IFERROR(HistoricalFS!G6/AVERAGE(SUM(HistoricalFS!G47:G48),SUM(HistoricalFS!F47:F48)),0) -> 1.8933 | H31: =IFERROR(HistoricalFS!H6/AVERAGE(SUM(HistoricalFS!H47:H48),SUM(HistoricalFS!G47:G48)),0) -> 2.1865988 | I31: =IFERROR(HistoricalFS!I6/AVERAGE(SUM(HistoricalFS!I47:I48),SUM(HistoricalFS!H47:H48)),0) -> 2.3143761 | J31: =IFERROR(HistoricalFS!J6/AVERAGE(SUM(HistoricalFS!J47:J48),SUM(HistoricalFS!I47:I48)),0) -> 2.0445961 | K31: =IFERROR(HistoricalFS!K6/AVERAGE(SUM(HistoricalFS!K47:K48),SUM(HistoricalFS!J47:J48)),0) -> 1.7785104 | L31: =IFERROR(HistoricalFS!L6/AVERAGE(SUM(HistoricalFS!L47:L48),SUM(HistoricalFS!K47:K48)),0) -> 1.7455147 | N31: =IFERROR(AVERAGE(D31:L31),0) -> 2.0309394 | O31: =IFERROR(MEDIAN(D31:L31),0) -> 2.0622977
B33: Days taken | C33: 365
B34: Debtor Days | D34: =IFERROR($C$33/D27,0) -> 34.472542 | E34: =IFERROR($C$33/E27,0) -> 34.507823 | F34: =IFERROR($C$33/F27,0) -> 33.42767 | G34: =IFERROR($C$33/G27,0) -> 36.957595 | H34: =IFERROR($C$33/H27,0) -> 40.593489 | I34: =IFERROR($C$33/I27,0) -> 45.020977 | J34: =IFERROR($C$33/J27,0) -> 48.978961 | K34: =IFERROR($C$33/K27,0) -> 49.535962 | L34: =IFERROR($C$33/L27,0) -> 45.010137 | N34: =IFERROR(AVERAGE(D34:L34),0) -> 40.945017 | O34: =IFERROR(MEDIAN(D34:L34),0) -> 40.593489
B35: Payable Days | D35: =IFERROR($C$33/D28,0) -> 66.565677 | E35: =IFERROR($C$33/E28,0) -> 64.39774 | F35: =IFERROR($C$33/F28,0) -> 62.844372 | G35: =IFERROR($C$33/G28,0) -> 71.725328 | H35: =IFERROR($C$33/H28,0) -> 66.855726 | I35: =IFERROR($C$33/I28,0) -> 59.887048 | J35: =IFERROR($C$33/J28,0) -> 59.215367 | K35: =IFERROR($C$33/K28,0) -> 61.624417 | L35: =IFERROR($C$33/L28,0) -> 59.909735 | N35: =IFERROR(AVERAGE(D35:L35),0) -> 63.66949 | O35: =IFERROR(MEDIAN(D35:L35),0) -> 62.844372
B36: Inventory Days | D36: =IFERROR($C$33/D29,0) -> 86.166114 | E36: =IFERROR($C$33/E29,0) -> 82.132855 | F36: =IFERROR($C$33/F29,0) -> 90.704359 | G36: =IFERROR($C$33/G29,0) -> 93.471912 | H36: =IFERROR($C$33/H29,0) -> 88.203646 | I36: =IFERROR($C$33/I29,0) -> 94.937903 | J36: =IFERROR($C$33/J29,0) -> 96.239248 | K36: =IFERROR($C$33/K29,0) -> 101.45823 | L36: =IFERROR($C$33/L29,0) -> 96.829546 | N36: =IFERROR(AVERAGE(D36:L36),0) -> 92.238202 | O36: =IFERROR(MEDIAN(D36:L36),0) -> 93.471912
B37: Cash Conversion Cycle | D37: =IFERROR(ABS(D34+D36-D35),0) -> 54.072979 | E37: =IFERROR(ABS(E34+E36-E35),0) -> 52.242938 | F37: =IFERROR(ABS(F34+F36-F35),0) -> 61.287658 | G37: =IFERROR(ABS(G34+G36-G35),0) -> 58.704179 | H37: =IFERROR(ABS(H34+H36-H35),0) -> 61.94141 | I37: =IFERROR(ABS(I34+I36-I35),0) -> 80.071831 | J37: =IFERROR(ABS(J34+J36-J35),0) -> 86.002842 | K37: =IFERROR(ABS(K34+K36-K35),0) -> 89.369779 | L37: =IFERROR(ABS(L34+L36-L35),0) -> 81.929948 | N37: =IFERROR(AVERAGE(D37:L37),0) -> 69.513729 | O37: =IFERROR(MEDIAN(D37:L37),0) -> 61.94141
B39: CFO/Sales | D39: =IFERROR(HistoricalFS!D77/HistoricalFS!D6,0) -> 0.12559028 | E39: =IFERROR(HistoricalFS!E77/HistoricalFS!E6,0) -> 0.12832554 | F39: =IFERROR(HistoricalFS!F77/HistoricalFS!F6,0) -> 0.15031233 | G39: =IFERROR(HistoricalFS!G77/HistoricalFS!G6,0) -> 0.16966958 | H39: =IFERROR(HistoricalFS!H77/HistoricalFS!H6,0) -> 0.033881671 | I39: =IFERROR(HistoricalFS!I77/HistoricalFS!I6,0) -> 0.12160544 | J39: =IFERROR(HistoricalFS!J77/HistoricalFS!J6,0) -> 0.17196919 | K39: =IFERROR(HistoricalFS!K77/HistoricalFS!K6,0) -> 0.13047984 | L39: =IFERROR(HistoricalFS!L77/HistoricalFS!L6,0) -> 0.19919322 | N39: =IFERROR(AVERAGE(C39:L39),0) -> 0.13678079 | O39: =IFERROR(MEDIAN(C39:L39),0) -> 0.13047984
B40: CFO/Total Assets | C40: =IFERROR(HistoricalFS!C77/HistoricalFS!C64,0) -> 0.12317425 | D40: =IFERROR(HistoricalFS!D77/HistoricalFS!D64,0) -> 0.15352222 | E40: =IFERROR(HistoricalFS!E77/HistoricalFS!E64,0) -> 0.15194931 | F40: =IFERROR(HistoricalFS!F77/HistoricalFS!F64,0) -> 0.18825168 | G40: =IFERROR(HistoricalFS!G77/HistoricalFS!G64,0) -> 0.18098445 | H40: =IFERROR(HistoricalFS!H77/HistoricalFS!H64,0) -> 0.042947188 | I40: =IFERROR(HistoricalFS!I77/HistoricalFS!I64,0) -> 0.16268848 | J40: =IFERROR(HistoricalFS!J77/HistoricalFS!J64,0) -> 0.2041419 | ... L40: =IFERROR(HistoricalFS!L77/HistoricalFS!L64,0) -> 0.20533768 | N40: =IFERROR(AVERAGE(C40:L40),0) -> 0.1558738 | O40: =IFERROR(MEDIAN(C40:L40),0) -> 0.15810535
B41: CFO/Total Debt | C41: =IFERROR(HistoricalFS!C77/HistoricalFS!C49,0) -> 2.7269158 | D41: =IFERROR(HistoricalFS!D77/HistoricalFS!D49,0) -> 3.961157 | E41: =IFERROR(HistoricalFS!E77/HistoricalFS!E49,0) -> 1.8710215 | F41: =IFERROR(HistoricalFS!F77/HistoricalFS!F49,0) -> 2.7161377 | G41: =IFERROR(HistoricalFS!G77/HistoricalFS!G49,0) -> 3.3701698 | H41: =IFERROR(HistoricalFS!H77/HistoricalFS!H49,0) -> 0.62134503 | I41: =IFERROR(HistoricalFS!I77/HistoricalFS!I49,0) -> 2.170111 | J41: =IFERROR(HistoricalFS!J77/HistoricalFS!J49,0) -> 2.4668806 | ... L41: =IFERROR(HistoricalFS!L77/HistoricalFS!L49,0) -> 1.8040535 | N41: =IFERROR(AVERAGE(C41:L41),0) -> 2.3639425 | O41: =IFERROR(MEDIAN(C41:L41),0) -> 2.3184958

Sheet Forecast(Explicit)
B2: ="Forecast"&" - "&Datasheet!$B$1 -> Forecast - ASIAN PAINTS LTD
B4: Section 1: Revenue
B5: Revenue Growth | C5: 0.06 | D5: 0.06 | E5: 0.07 | F5: 0.07 | G5: 0.07
B6: Revenue | C6: =HistoricalFS!$L$6*(1+'Forecast(Explicit)'!C5) -> 37718.552 | D6: =C6*(1+D5) -> 39981.666 | E6: =D6*(1+E5) -> 42780.382 | F6: =E6*(1+F5) -> 45775.009 | G6: =F6*(1+G5) -> 48979.26
B9: Section 2: Gross Margin & COGS
B10: Years | C10: 2027 | D10: =C10+1 -> 2028 | E10: =D10+1 -> 2029 | F10: =E10+1 -> 2030 | G10: =F10+1 -> 2031
B11: Gross Margin | C11: 0.35 | D11: 0.35 | E11: 0.36 | F11: 0.36 | G11: 0.36
B12: Gross Profit | C12: =C6*C11 -> 13201.493 | D12: =D6*D11 -> 13993.583 | E12: =E6*E11 -> 15400.938 | F12: =F6*F11 -> 16479.003 | G12: =G6*G11 -> 17632.533
B14: COGS | C14: =C6-C12 -> 24517.059 | D14: =D6-D12 -> 25988.083 | E14: =E6-E12 -> 27379.445 | F14: =F6-F12 -> 29296.006 | G14: =G6-G12 -> 31346.726
B17: Section 3 : Operating Expenses
B18: Years | C18: 2027 | D18: =C18+1 -> 2028 | E18: =D18+1 -> 2029 | F18: =E18+1 -> 2030 | G18: =F18+1 -> 2031
B19: Other operating Expense | C19: =C6*$H$19 -> 5657.7829 | D19: =D6*$H$19 -> 5997.2498 | E19: =E6*$H$19 -> 6417.0573 | F19: =F6*$H$19 -> 6866.2513 | G19: =G6*$H$19 -> 7346.8889 | H19: 0.15
B20: Total Forecast of Op Exp as % Sales | C20: =SUM(C19) -> 5657.7829 | D20: =SUM(D19) -> 5997.2498 | E20: =SUM(E19) -> 6417.0573 | F20: =SUM(F19) -> 6866.2513 | G20: =SUM(G19) -> 7346.8889
B23: Section 4 : EBITDA
B24: Years | C24: 2027 | D24: =C24+1 -> 2028 | E24: =D24+1 -> 2029 | F24: =E24+1 -> 2030 | G24: =F24+1 -> 2031
B25: EBIDTA Margin | C25: =C26/C6 -> 0.2 | D25: =D26/D6 -> 0.2 | E25: =E26/E6 -> 0.21 | F25: =F26/F6 -> 0.21 | G25: =G26/G6 -> 0.21
B26: EBITDA Amount | C26: =C6-C14-C20 -> 7543.7105 | D26: =D6-D14-D20 -> 7996.3331 | E26: =E6-E14-E20 -> 8983.8802 | F26: =F6-F14-F20 -> 9612.7519 | G26: =G6-G14-G20 -> 10285.644
B28: Section 5 : Depreciation
B29: Years | C29: 2027 | D29: =C29+1 -> 2028 | E29: =D29+1 -> 2029 | F29: =E29+1 -> 2030 | G29: =F29+1 -> 2031
B30: Depreciation | C30: 0.08 | D30: 0.08 | E30: 0.08 | F30: 0.08 | G30: 0.08
B31: Depreciation Amount | C31: ='PPE Schedule'!H10 -> 1346.0595 | D31: ='PPE Schedule'!I10 -> 1435.9657 | E31: ='PPE Schedule'!J10 -> 1592.6433 | F31: ='PPE Schedule'!K10 -> 1760.9217 | G31: ='PPE Schedule'!L10 -> 1916.0314
B33: Section 6 : Interest
B34: Years | C34: 2027 | D34: =C34+1 -> 2028 | E34: =D34+1 -> 2029 | F34: =E34+1 -> 2030 | G34: =F34+1 -> 2031
B35: Interest | C35: 195.41 | D35: 195.41 | E35: 195.41 | F35: 195.41 | G35: 195.41
B37: Section 7: Capital Expenditure
B38: Years | C38: 2027 | D38: =C38+1 -> 2028 | E38: =D38+1 -> 2029 | F38: =E38+1 -> 2030 | G38: =F38+1 -> 2031
B39: Capex | C39: =$H$39*C6 -> 1659.6163 | D39: =$H$39*D6 -> 1759.1933 | E39: =$H$39*E6 -> 1882.3368 | F39: =$H$39*F6 -> 2014.1004 | G39: =$H$39*G6 -> 2155.0874 | H39: 0.044
B40: Capex | C40: ='PPE Schedule'!C16 -> 600 | D40: ='PPE Schedule'!D16 -> 1000 | E40: ='PPE Schedule'!E16 -> 900 | F40: ='PPE Schedule'!F16 -> 400 | G40: ='PPE Schedule'!G16 -> 0 | H40: Bottom Up
B42: Section 8: Operating Working Capital
B43: Years | C43: 2027 | D43: =C43+1 -> 2028 | E43: =D43+1 -> 2029 | F43: =E43+1 -> 2030 | G43: =F43+1 -> 2031
B44: Other Current Liabilities | C44: =$H$44*C6 -> 4149.0408 | D44: =$H$44*D6 -> 4397.9832 | E44: =$H$44*E6 -> 4705.842 | F44: =$H$44*F6 -> 5035.251 | G44: =$H$44*G6 -> 5387.7185 | H44: 0.11
B45: Trade Payable | C45: =('Ratio Analysis'!$O$35/365)*C14 -> 4221.258 | D45: =('Ratio Analysis'!$O$35/365)*D14 -> 4474.5335 | E45: =('Ratio Analysis'!$O$35/365)*E14 -> 4714.0931 | F45: =('Ratio Analysis'!$O$35/365)*F14 -> 5044.0796 | G45: =('Ratio Analysis'!$O$35/365)*G14 -> 5397.1652 | H45: Based on days
B46: Inventory | C46: =(93/365)*C14 -> 6246.8123 | D46: =(93/365)*D14 -> 6621.621 | E46: =(93/365)*E14 -> 6976.1325 | F46: =(93/365)*F14 -> 7464.4617 | G46: =(93/365)*G14 -> 7986.974 | H46: Based on days
B47: Other Current Assets | C47: =$H$47*C6 -> 5092.0046 | D47: =$H$47*D6 -> 5397.5248 | E47: =$H$47*E6 -> 5775.3516 | F47: =$H$47*F6 -> 6179.6262 | G47: =$H$47*G6 -> 6612.2 | H47: 0.135
B48: Trade Recievable | C48: =(45/365)*'Forecast(Explicit)'!C6 -> 4650.2325 | D48: =(45/365)*'Forecast(Explicit)'!D6 -> 4929.2464 | E48: =(45/365)*'Forecast(Explicit)'!E6 -> 5274.2937 | F48: =(45/365)*'Forecast(Explicit)'!F6 -> 5643.4942 | G48: =(45/365)*'Forecast(Explicit)'!G6 -> 6038.5388 | H48: Based on days
B49: Working Capital | C49: =SUM(C46:C48)-SUM(C44:C45) -> 7618.7506 | D49: =SUM(D46:D48)-SUM(D44:D45) -> 8075.8756 | E49: =SUM(E46:E48)-SUM(E44:E45) -> 8605.8426 | F49: =SUM(F46:F48)-SUM(F44:F45) -> 9208.2515 | G49: =SUM(G46:G48)-SUM(G44:G45) -> 9852.8292
B51: Section 9: Fixed Asset
B52: Years | C52: 2027 | D52: =C52+1 -> 2028 | E52: =D52+1 -> 2029 | F52: =E52+1 -> 2030 | G52: =F52+1 -> 2031
B53: Opening PPE | C53: ='Raw FS'!N26 -> 15316 | D53: =C54 -> 16975.616 | E53: =D54 -> 18734.81 | F53: =E54 -> 20617.146 | G53: =F54 -> 22631.247
B54: Closing Gross PPE | C54: =C53+C39 -> 16975.616 | D54: =D53+D39 -> 18734.81 | E54: =E53+E39 -> 20617.146 | F54: =F53+F39 -> 22631.247 | G54: =G53+G39 -> 24786.334
B56: Section 10: Dividend payout
B57: Years | C57: 2027 | D57: =C57+1 -> 2028 | E57: =D57+1 -> 2029 | F57: =E57+1 -> 2030 | G57: =F57+1 -> 2031
B58: Dividend Payout % | C58: 0.6 | D58: 0.6 | E58: 0.6 | F58: 0.6 | G58: 0.6
B60: Section 11: EBIT
B61: Years | C61: 2027 | D61: =C61+1 -> 2028 | E61: =D61+1 -> 2029 | F61: =E61+1 -> 2030 | G61: =F61+1 -> 2031
B62: EBIT | C62: =C26-C31 -> 6197.6509 | D62: =D26-D31 -> 6560.3674 | E62: =E26-E31 -> 7391.237 | F62: =F26-F31 -> 7851.8301 | G62: =G26-G31 -> 8369.6131

Sheet WACC
B2: ="Weighted Average Cost of Capital "&" - "&Datasheet!$B$1 -> Weighted Average Cost of Capital - ASIAN PAINTS LTD
B3: All Figures in INR unless stated otherwise
B5: Peer Comps
H6: Debt/ | I6: Debt/ | J6: Levered | K6: Unlevered
B7: Name of the Comp | D7: Country | E7: Total Debt | F7: Total Equity | G7: Tax Rate1 | H7: Equity | I7: Capital | J7: Beta2 | K7: Beta3
B9: Berger Paints | D9: India | E9: 635.13 | F9: 57863.35 | G9: 0.25 | H9: =E9/F9 -> 0.010976378 | I9: =IFERROR(E9/SUM(E9,F9),0) -> 0.010857205 | J9: =Beta!L33 -> 0.9394496 | K9: =J9/(1+(1-G9)*H9) -> 0.93177894
B10: kansai Nerolac | D10: India | E10: 302.73 | F10: 16046.48 | G10: 0.25 | H10: =E10/F10 -> 0.01886582 | I10: =IFERROR(E10/SUM(E10,F10),0) -> 0.018516491 | J10: =Beta!L23 -> 0.89048014 | K10: =J10/(1+(1-G10)*H10) -> 0.8780562
B11: JSW Dulux | D11: India | E11: 79.1 | F11: 13906.24 | G11: 0.25 | H11: =E11/F11 -> 0.005688094 | I11: =IFERROR(E11/SUM(E11,F11),0) -> 0.0056559226 | J11: =Beta!L43 -> 0.57054979 | K11: =J11/(1+(1-G11)*H11) -> 0.56812613
B12: Indigo Paints | D12: India | E12: 18.37 | F12: 5075.56 | G12: 0.25 | H12: =E12/F12 -> 0.0036193051 | I12: =IFERROR(E12/SUM(E12,F12),0) -> 0.0036062529 | J12: =Beta!L53 -> 0.87909785 | K12: =J12/(1+(1-G12)*H12) -> 0.87671802
B13: Sirca Paints | D13: India | E13: 32.32 | F13: 2236.2 | G13: 0.25 | H13: =E13/F13 -> 0.01445309 | I13: =IFERROR(E13/SUM(E13,F13),0) -> 0.014247174 | J13: =Beta!L63 -> 1.0607296 | K13: =J13/(1+(1-G13)*H13) -> 1.0493548
B15: Cost Of Debt | G15: Average | H15: =AVERAGE(H9:H13) -> 0.010720537 | I15: =AVERAGE(I9:I13) -> 0.010576609 | J15: =AVERAGE(J9:J13) -> 0.8680614 | K15: =AVERAGE(K9:K13) -> 0.86080681
G16: Median | H16: =MEDIAN(H9:H13) -> 0.010976378 | I16: =MEDIAN(I9:I13) -> 0.010857205 | J16: =MEDIAN(J9:J13) -> 0.89048014 | K16: =MEDIAN(K9:K13) -> 0.8780562
B17: Pre Tax Cost of Debt | E17: =K22+0.4% -> 0.0724
B18: Tax Rate | E18: 0.25
B19: Post Tax Cost of Debt | E19: =E17*(1-E18) -> 0.0543
G20: Cost Of Equity
G22: Risk Free Rate | K22: 0.0684
B23: Capital Structure | G23: Equity Risk Premium | K23: ='Market Return'!G5-WACC!K22 -> 0.045045455
G24: Levered Beta4 | K24: =K40 -> 0.8808003
D25: Current | E25: Target | G25: Cost of Equity | K25: =K22+K23*K24 -> 0.10807605
B26: Total Debt | C26: 3928.93 | D26: =IFERROR(C26/$C$28,0) -> 0.014981593 | E26: =I16 -> 0.010857205
B27: Market Capitalization | C27: 258321.56 | D27: =IFERROR(C27/$C$28,0) -> 0.98501841 | E27: =1-E26 -> 0.98914279
B28: Total Capital | C28: =SUM(C26:C27) -> 262250.49 | D28: =SUM(D26:D27) -> 1 | E28: =SUM(E26:E27) -> 1 | G28: Weighted Average Cost of Capital
B30: Debt/ Equity | D30: =D26/D27 -> 0.015209454 | E30: =E26/E27 -> 0.010976378 | J30: Total Cost | K30: Total Weight
G31: Debt | J31: =E19 -> 0.0543 | K31: =E26 -> 0.010857205
B32: Notes: | G32: Equity | J32: =K25 -> 0.10807605 | K32: =1-K31 -> 0.98914279
B33: 1.Tax rate is considered as marginal tax rate for the countries | G33: WACC | K33: =SUMPRODUCT(J31:J32,K31:K32) -> 0.10749219
B34: 2. Levered Beta is based on 5 year Weekly data
B35: 3. Unlevered Beta = Levered Beta/(1+(1-Tax Rate)*Debt/Equity | G35: Levered Beta (Comps)
B36: 4. Levered Beta = Unlevered Beta*(1+(1-Tax Rate)*Debt/Equity
G37: Comps Median Unlevered Beta | K37: =K16 -> 0.8780562
G38: Target Debt/Equity | K38: =E30 -> 0.010976378
G39: Tax Rate | K39: 0.25
G40: Levered Beta | K40: =K37+K38*K39 -> 0.8808003

Sheet Common Size Statement
B2: ="Common Size Income Statement"&" - "&Datasheet!$B$1 -> Common Size Income Statement - ASIAN PAINTS LTD
B3: Years | C3: 42825 | D3: 43190 | E3: 43555 | F3: 43921 | G3: 44286 | H3: 44651 | I3: 45016 | J3: 45382 | K3: 45747 | L3: 46112
B5: =Datasheet!A17 -> Sales | C5: =Datasheet!B17/Datasheet!B$17 -> 1 | D5: =Datasheet!C17/Datasheet!C$17 -> 1 | E5: =Datasheet!D17/Datasheet!D$17 -> 1 | F5: =Datasheet!E17/Datasheet!E$17 -> 1 | G5: =Datasheet!F17/Datasheet!F$17 -> 1 | H5: =Datasheet!G17/Datasheet!G$17 -> 1 | I5: =Datasheet!H17/Datasheet!H$17 -> 1 | J5: =Datasheet!I17/Datasheet!I$17 -> 1 | ... L5: =Datasheet!K17/Datasheet!K$17 -> 1
B6: =Datasheet!A18 -> Raw Material Cost | C6: =Datasheet!B18/Datasheet!B$17 -> 0.49479518 | D6: =Datasheet!C18/Datasheet!C$17 -> 0.48311366 | E6: =Datasheet!D18/Datasheet!D$17 -> 0.51841646 | F6: =Datasheet!E18/Datasheet!E$17 -> 0.49388286 | G6: =Datasheet!F18/Datasheet!F$17 -> 0.48015709 | H6: =Datasheet!G18/Datasheet!G$17 -> 0.58840195 | I6: =Datasheet!H18/Datasheet!H$17 -> 0.55048728 | J6: =Datasheet!I18/Datasheet!I$17 -> 0.49051902 | ... L6: =Datasheet!K18/Datasheet!K$17 -> 0.48173987
B7: =Datasheet!A19 -> Change in Inventory | C7: =Datasheet!B19/Datasheet!B$17 -> 0.035094964 | D7: =Datasheet!C19/Datasheet!C$17 -> -0.0084477742 | E7: =Datasheet!D19/Datasheet!D$17 -> 0.015242101 | F7: =Datasheet!E19/Datasheet!E$17 -> 0.011832519 | G7: =Datasheet!F19/Datasheet!F$17 -> 0.0042578591 | H7: =Datasheet!G19/Datasheet!G$17 -> 0.045529612 | I7: =Datasheet!H19/Datasheet!H$17 -> 0.0089806513 | J7: =Datasheet!I19/Datasheet!I$17 -> -0.010249409 | ... L7: =Datasheet!K19/Datasheet!K$17 -> -0.016965147
B8: =Datasheet!A20 -> Power and Fuel | C8: =Datasheet!B20/Datasheet!B$17 -> 0.0070389105 | D8: =Datasheet!C20/Datasheet!C$17 -> 0.006555896 | E8: =Datasheet!D20/Datasheet!D$17 -> 0.0062177335 | F8: =Datasheet!E20/Datasheet!E$17 -> 0.0048383945 | G8: =Datasheet!F20/Datasheet!F$17 -> 0.0039631019 | H8: =Datasheet!G20/Datasheet!G$17 -> 0.0040283451 | I8: =Datasheet!H20/Datasheet!H$17 -> 0.0040097319 | J8: =Datasheet!I20/Datasheet!I$17 -> 0.0037540784 | ... L8: =Datasheet!K20/Datasheet!K$17 -> 0.0046959915
B9: =Datasheet!A21 -> Other Mfr. Exp | C9: =Datasheet!B21/Datasheet!B$17 -> 0.11039378 | D9: =Datasheet!C21/Datasheet!C$17 -> 0.10054831 | E9: =Datasheet!D21/Datasheet!D$17 -> 0.096795084 | F9: =Datasheet!E21/Datasheet!E$17 -> 0.096288948 | G9: =Datasheet!F21/Datasheet!F$17 -> 0.09525768 | H9: =Datasheet!G21/Datasheet!G$17 -> 0.098980182 | I9: =Datasheet!H21/Datasheet!H$17 -> 0.084555501 | J9: =Datasheet!I21/Datasheet!I$17 -> 0.077960306 | ... L9: =Datasheet!K21/Datasheet!K$17 -> 0.077763764
B10: =Datasheet!A22 -> Employee Cost | C10: =Datasheet!B22/Datasheet!B$17 -> 0.069040678 | D10: =Datasheet!C22/Datasheet!C$17 -> 0.066681724 | E10: =Datasheet!D22/Datasheet!D$17 -> 0.064588441 | F10: =Datasheet!E22/Datasheet!E$17 -> 0.067846867 | G10: =Datasheet!F22/Datasheet!F$17 -> 0.071276423 | H10: =Datasheet!G22/Datasheet!G$17 -> 0.061667734 | I10: =Datasheet!H22/Datasheet!H$17 -> 0.059045905 | J10: =Datasheet!I22/Datasheet!I$17 -> 0.06578216 | ... L10: =Datasheet!K22/Datasheet!K$17 -> 0.078961509
B11: Other Operating Expense | C11: =HistoricalFS!C15/HistoricalFS!C6 -> 0.15506384 | D11: =HistoricalFS!D15/HistoricalFS!D6 -> 0.14421604 | E11: =HistoricalFS!E15/HistoricalFS!E6 -> 0.13354276 | F11: =HistoricalFS!F15/HistoricalFS!F6 -> 0.14306191 | G11: =HistoricalFS!G15/HistoricalFS!G6 -> 0.12997501 | H11: =HistoricalFS!H15/HistoricalFS!H6 -> 0.12738615 | I11: =HistoricalFS!I15/HistoricalFS!I6 -> 0.12937757 | J11: =HistoricalFS!J15/HistoricalFS!J6 -> 0.1380419 | ... L11: =HistoricalFS!L15/HistoricalFS!L6 -> 0.151592
B12: =Datasheet!A25 -> Other Income | C12: =Datasheet!B25/Datasheet!B$17 -> 0.022433955 | D12: =Datasheet!C25/Datasheet!C$17 -> 0.019995186 | E12: =Datasheet!D25/Datasheet!D$17 -> 0.014229114 | F12: =Datasheet!E25/Datasheet!E$17 -> 0.017322036 | G12: =Datasheet!F25/Datasheet!F$17 -> 0.015274407 | H12: =Datasheet!G25/Datasheet!G$17 -> 0.01016725 | I12: =Datasheet!H25/Datasheet!H$17 -> 0.012510224 | J12: =Datasheet!I25/Datasheet!I$17 -> 0.023129067 | ... L12: =Datasheet!K25/Datasheet!K$17 -> 0.020458054
B13: =Datasheet!A26 -> Depreciation | C13: =Datasheet!B26/Datasheet!B$17 -> 0.022227475 | D13: =Datasheet!C26/Datasheet!C$17 -> 0.021425239 | E13: =Datasheet!D26/Datasheet!D$17 -> 0.03233554 | F13: =Datasheet!E26/Datasheet!E$17 -> 0.038617107 | G13: =Datasheet!F26/Datasheet!F$17 -> 0.036442576 | H13: =Datasheet!G26/Datasheet!G$17 -> 0.028052374 | I13: =Datasheet!H26/Datasheet!H$17 -> 0.024878373 | J13: =Datasheet!I26/Datasheet!I$17 -> 0.024031737 | ... L13: =Datasheet!K26/Datasheet!K$17 -> 0.034534226
B14: =Datasheet!A27 -> Interest | C14: =Datasheet!B27/Datasheet!B$17 -> 0.0024784242 | D14: =Datasheet!C27/Datasheet!C$17 -> 0.0024648505 | E14: =Datasheet!D27/Datasheet!D$17 -> 0.0057416452 | F14: =Datasheet!E27/Datasheet!E$17 -> 0.0050630218 | G14: =Datasheet!F27/Datasheet!F$17 -> 0.0042200933 | H14: =Datasheet!G27/Datasheet!G$17 -> 0.0032785499 | I14: =Datasheet!H27/Datasheet!H$17 -> 0.0041883417 | J14: =Datasheet!I27/Datasheet!I$17 -> 0.0057802947 | ... L14: =Datasheet!K27/Datasheet!K$17 -> 0.005491584
B15: =Datasheet!A28 -> Profit before tax | C15: =Datasheet!B28/Datasheet!B$17 -> 0.19649064 | D15: =Datasheet!C28/Datasheet!C$17 -> 0.18654169 | E15: =Datasheet!D28/Datasheet!D$17 -> 0.17183356 | F15: =Datasheet!E28/Datasheet!E$17 -> 0.17955545 | G15: =Datasheet!F28/Datasheet!F$17 -> 0.1982403 | H15: =Datasheet!G28/Datasheet!G$17 -> 0.14390157 | I15: =Datasheet!H28/Datasheet!H$17 -> 0.16494818 | J15: =Datasheet!I28/Datasheet!I$17 -> 0.20701017 | ... L15: =Datasheet!K28/Datasheet!K$17 -> 0.16871396
B16: =Datasheet!A29 -> Tax | C16: =Datasheet!B29/Datasheet!B$17 -> 0.062627183 | D16: =Datasheet!C29/Datasheet!C$17 -> 0.061871491 | E16: =Datasheet!D29/Datasheet!D$17 -> 0.05707134 | F16: =Datasheet!E29/Datasheet!E$17 -> 0.042295751 | G16: =Datasheet!F29/Datasheet!F$17 -> 0.05055085 | H16: =Datasheet!G29/Datasheet!G$17 -> 0.03789902 | I16: =Datasheet!H29/Datasheet!H$17 -> 0.043304177 | J16: =Datasheet!I29/Datasheet!I$17 -> 0.050432275 | ... L16: =Datasheet!K29/Datasheet!K$17 -> 0.04521051
B17: =Datasheet!A30 -> Net profit | C17: =Datasheet!B30/Datasheet!B$17 -> 0.1287632 | D17: =Datasheet!C30/Datasheet!C$17 -> 0.12118779 | E17: =Datasheet!D30/Datasheet!D$17 -> 0.1120533 | F17: =Datasheet!E30/Datasheet!E$17 -> 0.13384476 | G17: =Datasheet!F30/Datasheet!F$17 -> 0.14458252 | H17: =Datasheet!G30/Datasheet!G$17 -> 0.10413872 | I17: =Datasheet!H30/Datasheet!H$17 -> 0.11906691 | J17: =Datasheet!I30/Datasheet!I$17 -> 0.15383213 | ... L17: =Datasheet!K30/Datasheet!K$17 -> 0.1215548
B18: =Datasheet!A31 -> Dividend Amount | C18: =Datasheet!B31/Datasheet!B$17 -> 0.065594254 | D18: =Datasheet!C31/Datasheet!C$17 -> 0.049600138 | E18: =Datasheet!D31/Datasheet!D$17 -> 0.05234684 | F18: =Datasheet!E31/Datasheet!E$17 -> 0.056950461 | G18: =Datasheet!F31/Datasheet!F$17 -> 0.078855366 | H18: =Datasheet!G31/Datasheet!G$17 -> 0.063119904 | I18: =Datasheet!H31/Datasheet!H$17 -> 0.071338086 | J18: =Datasheet!I31/Datasheet!I$17 -> 0.089989134 | ... L18: =Datasheet!K31/Datasheet!K$17 -> 0.07412978
B19: EBITDA | C19: =C5-SUM(C6,C7,C8,C9,C10,C11) -> 0.12857265 | D19: =D5-SUM(D6,D7,D8,D9,D10,D11) -> 0.20733214 | E19: =E5-SUM(E6,E7,E8,E9,E10,E11) -> 0.16519743 | F19: =F5-SUM(F6,F7,F8,F9,F10,F11) -> 0.1822485 | G19: =G5-SUM(G6,G7,G8,G9,G10,G11) -> 0.21511284 | H19: =H5-SUM(H6,H7,H8,H9,H10,H11) -> 0.074006023 | I19: =I5-SUM(I6,I7,I8,I9,I10,I11) -> 0.16354336 | J19: =J5-SUM(J6,J7,J8,J9,J10,J11) -> 0.23419195 | ... L19: =L5-SUM(L6,L7,L8,L9,L10,L11) -> 0.22221201
B21: ="Common Size Balance Sheet"&" - "&Datasheet!$B$1 -> Common Size Balance Sheet - ASIAN PAINTS LTD
B22: Years | C22: 42825 | D22: 43190 | E22: 43555 | F22: 43921 | G22: 44286 | H22: 44651 | I22: 45016 | J22: 45382 | K22: 45747 | L22: 46112
B24: Total Liabilities | C24: =Datasheet!B61/Datasheet!B$61 -> 1 | D24: =Datasheet!C61/Datasheet!C$61 -> 1 | E24: =Datasheet!D61/Datasheet!D$61 -> 1 | F24: =Datasheet!E61/Datasheet!E$61 -> 1 | G24: =Datasheet!F61/Datasheet!F$61 -> 1 | H24: =Datasheet!G61/Datasheet!G$61 -> 1 | I24: =Datasheet!H61/Datasheet!H$61 -> 1 | J24: =Datasheet!I61/Datasheet!I$61 -> 1 | ... L24: =Datasheet!K61/Datasheet!K$61 -> 1
B25: Equity Share Capital | C25: =Datasheet!B57/Datasheet!B$61 -> 0.0077322476 | D25: =Datasheet!C57/Datasheet!C$61 -> 0.0069691677 | E25: =Datasheet!D57/Datasheet!D$61 -> 0.0059031906 | F25: =Datasheet!E57/Datasheet!E$61 -> 0.0059437463 | G25: =Datasheet!F57/Datasheet!F$61 -> 0.004712277 | H25: =Datasheet!G57/Datasheet!G$61 -> 0.004177986 | I25: =Datasheet!H57/Datasheet!H$61 -> 0.0037208104 | J25: =Datasheet!I57/Datasheet!I$61 -> 0.0032079441 | ... L25: =Datasheet!K57/Datasheet!K$61 -> 0.0027787796
B26: Reserves | C26: =Datasheet!B58/Datasheet!B$61 -> 0.60522813 | D26: =Datasheet!C58/Datasheet!C$61 -> 0.60408487 | E26: =Datasheet!D58/Datasheet!D$61 -> 0.57694149 | F26: =Datasheet!E58/Datasheet!E$61 -> 0.62177833 | G26: =Datasheet!F58/Datasheet!F$61 -> 0.62442435 | H26: =Datasheet!G58/Datasheet!G$61 -> 0.59741193 | I26: =Datasheet!H58/Datasheet!H$61 -> 0.61663007 | J26: =Datasheet!I58/Datasheet!I$61 -> 0.62314047 | ... L26: =Datasheet!K58/Datasheet!K$61 -> 0.61635111
B27: Borrowings | C27: =Datasheet!B59/Datasheet!B$61 -> 0.045169804 | D27: =Datasheet!C59/Datasheet!C$61 -> 0.038756913 | E27: =Datasheet!D59/Datasheet!D$61 -> 0.081211951 | F27: =Datasheet!E59/Datasheet!E$61 -> 0.069308593 | G27: =Datasheet!F59/Datasheet!F$61 -> 0.053701879 | H27: =Datasheet!G59/Datasheet!G$61 -> 0.069119709 | I27: =Datasheet!H59/Datasheet!H$61 -> 0.074967813 | J27: =Datasheet!I59/Datasheet!I$61 -> 0.082753053 | ... L27: =Datasheet!K59/Datasheet!K$61 -> 0.11382017
B28: Other Liabilities | C28: =Datasheet!B60/Datasheet!B$61 -> 0.34186981 | D28: =Datasheet!C60/Datasheet!C$61 -> 0.35018905 | E28: =Datasheet!D60/Datasheet!D$61 -> 0.33594337 | F28: =Datasheet!E60/Datasheet!E$61 -> 0.30296933 | G28: =Datasheet!F60/Datasheet!F$61 -> 0.31716149 | H28: =Datasheet!G60/Datasheet!G$61 -> 0.32929037 | I28: =Datasheet!H60/Datasheet!H$61 -> 0.30468131 | J28: =Datasheet!I60/Datasheet!I$61 -> 0.29089853 | ... L28: =Datasheet!K60/Datasheet!K$61 -> 0.26704994
B30: Total Assets | C30: =Datasheet!B66/Datasheet!B66 -> 1 | D30: =Datasheet!C66/Datasheet!C66 -> 1 | E30: =Datasheet!D66/Datasheet!D66 -> 1 | F30: =Datasheet!E66/Datasheet!E66 -> 1 | G30: =Datasheet!F66/Datasheet!F66 -> 1 | H30: =Datasheet!G66/Datasheet!G66 -> 1 | I30: =Datasheet!H66/Datasheet!H66 -> 1 | J30: =Datasheet!I66/Datasheet!I66 -> 1 | ... L30: =Datasheet!K66/Datasheet!K66 -> 1
B31: Fixed Asset Net Block | C31: =Datasheet!B62/Datasheet!$B$66 -> 0.26631918 | D31: =Datasheet!C62/Datasheet!$B$66 -> 0.30086117 | E31: =Datasheet!D62/Datasheet!$B$66 -> 0.52369694 | F31: =Datasheet!E62/Datasheet!$B$66 -> 0.50561983 | G31: =Datasheet!F62/Datasheet!$B$66 -> 0.47226363 | H31: =Datasheet!G62/Datasheet!$B$66 -> 0.44489927 | I31: =Datasheet!H62/Datasheet!$B$66 -> 0.46516498 | J31: =Datasheet!I62/Datasheet!$B$66 -> 0.5760992 | ... L31: =Datasheet!K62/Datasheet!$B$66 -> 0.77711667
B32: Capital Work in Progress | C32: =Datasheet!B63/Datasheet!$B$66 -> 0.020760665 | D32: =Datasheet!C63/Datasheet!$B$66 -> 0.11326791 | E32: =Datasheet!D63/Datasheet!$B$66 -> 0.016901797 | F32: =Datasheet!E63/Datasheet!$B$66 -> 0.011304946 | G32: =Datasheet!F63/Datasheet!$B$66 -> 0.014750278 | H32: =Datasheet!G63/Datasheet!$B$66 -> 0.034375128 | I32: =Datasheet!H63/Datasheet!$B$66 -> 0.082190599 | J32: =Datasheet!I63/Datasheet!$B$66 -> 0.21751944 | ... L32: =Datasheet!K63/Datasheet!$B$66 -> 0.14902392
B33: Investments | C33: =Datasheet!B64/Datasheet!$B$66 -> 0.21378068 | D33: =Datasheet!C64/Datasheet!$B$66 -> 0.17256487 | E33: =Datasheet!D64/Datasheet!$B$66 -> 0.20705689 | F33: =Datasheet!E64/Datasheet!$B$66 -> 0.16274237 | G33: =Datasheet!F64/Datasheet!$B$66 -> 0.38184018 | H33: =Datasheet!G64/Datasheet!$B$66 -> 0.26178801 | I33: =Datasheet!H64/Datasheet!$B$66 -> 0.3435425 | J33: =Datasheet!I64/Datasheet!$B$66 -> 0.36983875 | ... L33: =Datasheet!K64/Datasheet!$B$66 -> 0.5692569
B34: Other Assets | C34: =Datasheet!B65/Datasheet!$B$66 -> 0.49913947 | D34: =Datasheet!C65/Datasheet!$B$66 -> 0.52279973 | E34: =Datasheet!D65/Datasheet!$B$66 -> 0.56218647 | F34: =Datasheet!E65/Datasheet!$B$66 -> 0.62123756 | G34: =Datasheet!F65/Datasheet!$B$66 -> 0.77201881 | H34: =Datasheet!G65/Datasheet!$B$66 -> 1.1096493 | I34: =Datasheet!H65/Datasheet!$B$66 -> 1.1872104 | J34: =Datasheet!I65/Datasheet!$B$66 -> 1.2468862 | ... L34: =Datasheet!K65/Datasheet!$B$66 -> 1.287208
B35: Receivables | C35: =Datasheet!B67/Datasheet!$B$66 -> 0.11661248 | D35: =Datasheet!C67/Datasheet!$B$66 -> 0.13950854 | E35: =Datasheet!D67/Datasheet!$B$66 -> 0.15375258 | F35: =Datasheet!E67/Datasheet!$B$66 -> 0.14471524 | G35: =Datasheet!F67/Datasheet!$B$66 -> 0.20976462 | H35: =Datasheet!G67/Datasheet!$B$66 -> 0.31208228 | I35: =Datasheet!H67/Datasheet!$B$66 -> 0.37379032 | J35: =Datasheet!I67/Datasheet!$B$66 -> 0.39411327 | ... L35: =Datasheet!K67/Datasheet!$B$66 -> 0.35967204
B36: Inventory | C36: =Datasheet!B68/Datasheet!$B$66 -> 0.21176137 | D36: =Datasheet!C68/Datasheet!$B$66 -> 0.21429015 | E36: =Datasheet!D68/Datasheet!$B$66 -> 0.25391469 | F36: =Datasheet!E68/Datasheet!$B$66 -> 0.2732574 | G36: =Datasheet!F68/Datasheet!$B$66 -> 0.30621055 | H36: =Datasheet!G68/Datasheet!$B$66 -> 0.49600046 | I36: =Datasheet!H68/Datasheet!$B$66 -> 0.50064852 | J36: =Datasheet!I68/Datasheet!$B$66 -> 0.4774945 | ... L36: =Datasheet!K68/Datasheet!$B$66 -> 0.46300702
B37: Cash & Bank | C37: =Datasheet!B69/Datasheet!$B$66 -> 0.064586677 | D37: =Datasheet!C69/Datasheet!$B$66 -> 0.032619412 | E37: =Datasheet!D69/Datasheet!$B$66 -> 0.035862409 | F37: =Datasheet!E69/Datasheet!$B$66 -> 0.063105039 | G37: =Datasheet!F69/Datasheet!$B$66 -> 0.049233426 | H37: =Datasheet!G69/Datasheet!$B$66 -> 0.06967487 | I37: =Datasheet!H69/Datasheet!$B$66 -> 0.06802153 | J37: =Datasheet!I69/Datasheet!$B$66 -> 0.087383587 | ... L37: =Datasheet!K69/Datasheet!$B$66 -> 0.086550871

Sheet Intrisinic Growth
B1: ="Intrisinic Growth"&" - "&Datasheet!$B$1 -> Intrisinic Growth - ASIAN PAINTS LTD
B2: Calculation of ROC | G2: 2022 | H2: =G2+1 -> 2023 | I2: =H2+1 -> 2024 | J2: =I2+1 -> 2025 | K2: =J2+1 -> 2026
B4: Current Assets
B5: Inventories | G5: ='Raw FS'!J31 -> 6153 | H5: ='Raw FS'!K31 -> 6211 | I5: ='Raw FS'!L31 -> 5923 | J5: ='Raw FS'!M31 -> 6719 | K5: ='Raw FS'!N31 -> 5744
B6: Trade receivables | G6: ='Raw FS'!J32 -> 3871 | H6: ='Raw FS'!K32 -> 4637 | I6: ='Raw FS'!L32 -> 4889 | J6: ='Raw FS'!M32 -> 4314 | K6: ='Raw FS'!N32 -> 4462
B7: Loans & Advances | G7: ='Raw FS'!J34 -> 8 | H7: ='Raw FS'!K34 -> 12 | I7: ='Raw FS'!L34 -> 17 | J7: ='Raw FS'!M34 -> 22 | K7: ='Raw FS'!N34 -> 27
B8: Other Asset Item | G8: ='Raw FS'!J35 -> 2869 | H8: ='Raw FS'!K35 -> 3024 | I8: ='Raw FS'!L35 -> 3555 | J8: ='Raw FS'!M35 -> 3319 | K8: ='Raw FS'!N35 -> 4662
B9: Total Current Assets | G9: =SUM(G5:G8) -> 12901 | H9: =SUM(H5:H8) -> 13884 | I9: =SUM(I5:I8) -> 14384 | J9: =SUM(J5:J8) -> 14374 | K9: =SUM(K5:K8) -> 14895
B11: Current Liabilities
B12: Trade Payable | G12: ='Raw FS'!J13 -> 4164 | H12: ='Raw FS'!K13 -> 3635 | I12: ='Raw FS'!L13 -> 3831 | J12: ='Raw FS'!M13 -> 3848 | K12: ='Raw FS'!N13 -> 3863
B13: Advances from Customers | G13: ='Raw FS'!J14 -> 76 | H13: ='Raw FS'!K14 -> 108 | I13: ='Raw FS'!L14 -> 154 | J13: ='Raw FS'!M14 -> 174 | K13: ='Raw FS'!N14 -> 107
B14: Other Current liabilities | G14: ='Raw FS'!J15 -> 2932 | H14: ='Raw FS'!K15 -> 3657 | I14: ='Raw FS'!L15 -> 4017 | J14: ='Raw FS'!M15 -> 3984 | K14: ='Raw FS'!N15 -> 4604
B15: Total Current liabilities | G15: =SUM(G12:G14) -> 7172 | H15: =SUM(H12:H14) -> 7400 | I15: =SUM(I12:I14) -> 8002 | J15: =SUM(J12:J14) -> 8006 | K15: =SUM(K12:K14) -> 8574
A17: # | B17: Net Working Capital | G17: =G9-G15 -> 5729 | H17: =H9-H15 -> 6484 | I17: =I9-I15 -> 6382 | J17: =J9-J15 -> 6368 | K17: =K9-K15 -> 6321
B19: Non Current Assets
B20: Land | G20: ='Raw FS'!J18 -> 644 | H20: ='Raw FS'!K18 -> 804 | I20: ='Raw FS'!L18 -> 1126 | J20: ='Raw FS'!M18 -> 1035 | K20: ='Raw FS'!N18 -> 1204
B21: Building | G21: ='Raw FS'!J19 -> 2325 | H21: ='Raw FS'!K19 -> 2883 | I21: ='Raw FS'!L19 -> 3390 | J21: ='Raw FS'!M19 -> 3771 | K21: ='Raw FS'!N19 -> 4124
B22: Plant Machinery | G22: ='Raw FS'!J20 -> 4531 | H22: ='Raw FS'!K20 -> 4825 | I22: ='Raw FS'!L20 -> 5422 | J22: ='Raw FS'!M20 -> 7576 | K22: ='Raw FS'!N20 -> 8210
B23: Equipments | G23: ='Raw FS'!J21 -> 253 | H23: ='Raw FS'!K21 -> 270 | I23: ='Raw FS'!L21 -> 298 | J23: ='Raw FS'!M21 -> 325 | K23: ='Raw FS'!N21 -> 351
B24: Furniture n fittings | G24: ='Raw FS'!J22 -> 113 | H24: ='Raw FS'!K22 -> 146 | I24: ='Raw FS'!L22 -> 175 | J24: ='Raw FS'!M22 -> 203 | K24: ='Raw FS'!N22 -> 216
B25: Vehicles | G25: ='Raw FS'!J23 -> 32 | H25: ='Raw FS'!K23 -> 36 | I25: ='Raw FS'!L23 -> 40 | J25: ='Raw FS'!M23 -> 34 | K25: ='Raw FS'!N23 -> 45
B26: Intangible Assets | G26: ='Raw FS'!J24 -> 345 | H26: ='Raw FS'!K24 -> 422 | I26: ='Raw FS'!L24 -> 850 | J26: ='Raw FS'!M24 -> 827 | K26: ='Raw FS'!N24 -> 833
B27: Other fixed assets | G27: ='Raw FS'!J25 -> 294 | H27: ='Raw FS'!K25 -> 289 | I27: ='Raw FS'!L25 -> 321 | J27: ='Raw FS'!M25 -> 328 | K27: ='Raw FS'!N25 -> 335
B28: Gross Block | G28: =SUM(G20:G27) -> 8537 | H28: =SUM(H20:H27) -> 9675 | I28: =SUM(I20:I27) -> 11622 | J28: =SUM(J20:J27) -> 14099 | K28: =SUM(K20:K27) -> 15318
B29: Accumulated Depreciation | G29: =-'Raw FS'!J27 -> -3019 | H29: =-'Raw FS'!K27 -> -3905 | I29: =-'Raw FS'!L27 -> -4475 | J29: =-'Raw FS'!M27 -> -4879 | K29: =-'Raw FS'!N27 -> -5676
B30: Net Non Current Assets | G30: =G28+G29 -> 5518 | H30: =H28+H29 -> 5770 | I30: =I28+I29 -> 7147 | J30: =J28+J29 -> 9220 | K30: =K28+K29 -> 9642
A34: # | B34: Invested Capital | G34: =G30+ABS(G17) -> 11247 | H34: =H30+ABS(H17) -> 12254 | I34: =I30+ABS(I17) -> 13529 | J34: =J30+ABS(J17) -> 15588 | K34: =K30+ABS(K17) -> 15963
B35: EBIT | G35: =HistoricalFS!H18-HistoricalFS!H24 -> 3987.25 | H35: =HistoricalFS!I18-HistoricalFS!I24 -> 5401.82 | I35: =HistoricalFS!J18-HistoricalFS!J24 -> 6731.98 | J35: =HistoricalFS!K18-HistoricalFS!K24 -> 4979.87 | K35: =HistoricalFS!L18-HistoricalFS!L24 -> 5470.88
A37: # | B37: ROIC | G37: =G35/G34 -> 0.35451676 | H37: =H35/H34 -> 0.44082096 | I37: =I35/I34 -> 0.49759627 | J37: =J35/J34 -> 0.31946818 | K37: =K35/K34 -> 0.34272255
B39: Calculation of Reinvestment Rate | G39: 2022 | H39: =G39+1 -> 2023 | I39: =H39+1 -> 2024 | J39: =I39+1 -> 2025 | K39: =J39+1 -> 2026
B41: Net Capex | G41: =-SUM('Raw FS'!J53:J54) -> 511 | H41: =-SUM('Raw FS'!K53:K54) -> 1420 | I41: =-SUM('Raw FS'!L53:L54) -> 2491 | J41: =-SUM('Raw FS'!M53:M54) -> 1820 | K41: =-SUM('Raw FS'!N53:N54) -> 1484
B42: Change in WC | H42: =H17-G17 -> 755 | I42: =I17-H17 -> -102 | J42: =J17-I17 -> -14 | K42: =K17-J17 -> -47
B44: EBIT | G44: =G35 -> 3987.25 | H44: =H35 -> 5401.82 | I44: =I35 -> 6731.98 | J44: =J35 -> 4979.87 | K44: =K35 -> 5470.88
B45: Marginal Tax Rate | G45: 0.25 | H45: 0.25 | I45: 0.25 | J45: 0.25 | K45: 0.25
B46: EBIT(1-Tax rate) | G46: =G44*(1-G45) -> 2990.4375 | H46: =H44*(1-H45) -> 4051.365 | I46: =I44*(1-I45) -> 5048.985 | J46: =J44*(1-J45) -> 3734.9025 | K46: =K44*(1-K45) -> 4103.16
B48: Reinvestment | H48: =H41+H42 -> 2175 | I48: =I41+I42 -> 2389 | J48: =J41+J42 -> 1806 | K48: =K41+K42 -> 1437
B49: Reinvestment Rate | H49: =H48/H46 -> 0.5368561 | I49: =I48/I46 -> 0.47316441 | J49: =J48/J46 -> 0.48354676 | K49: =K48/K46 -> 0.35021788
J51: 4 Year Average | K51: =AVERAGE(H49:K49) -> 0.46094629
J52: 4 Year Median | K52: =MEDIAN(H49:K49) -> 0.47835558
B54: Calculation of Growth Rate | G54: 2022 | H54: =G54+1 -> 2023 | I54: =H54+1 -> 2024 | J54: =I54+1 -> 2025 | K54: =J54+1 -> 2026
B56: Reinvestment Rate | H56: =H49 -> 0.5368561 | I56: =I49 -> 0.47316441 | J56: =J49 -> 0.48354676 | K56: =K49 -> 0.35021788
B57: ROIC | H57: =H37 -> 0.44082096 | I57: =I37 -> 0.49759627 | J57: =J37 -> 0.31946818 | K57: =K37 -> 0.34272255
A59: # | B59: Intrinsic growth | H59: =H56*H57 -> 0.23665742 | I59: =I56*I57 -> 0.23544485 | J59: =J56*J57 -> 0.1544778 | K59: =K56*K57 -> 0.12002756
J61: 4 Year Average | K61: =AVERAGE(H59:K59) -> 0.18665191
J62: 4 Year Median | K62: =MEDIAN(H59:K59) -> 0.19496133

Sheet DCF
B2: ="Intrisinic Growth"&" - "&Datasheet!$B$1 -> Intrisinic Growth - ASIAN PAINTS LTD
B3: Calculation PV of FCFF | H3: 2026 | I3: =H3+1 -> 2027 | J3: =I3+1 -> 2028 | K3: =J3+1 -> 2029 | L3: =K3+1 -> 2030 | M3: =L3+1 -> 2031
B5: EBIT | H5: =HistoricalFS!L18-HistoricalFS!L24 -> 5470.88 | I5: ='Forecast(Explicit)'!C62 -> 6197.6509 | J5: ='Forecast(Explicit)'!D62 -> 6560.3674 | K5: ='Forecast(Explicit)'!E62 -> 7391.237 | L5: ='Forecast(Explicit)'!F62 -> 7851.8301 | M5: ='Forecast(Explicit)'!G62 -> 8369.6131
B6: Tax Rate | H6: 0.25 | I6: 0.25 | J6: 0.25 | K6: 0.25 | L6: 0.25 | M6: 0.25
B7: EBIT*(1-tax) | H7: =H5*(1-H6) -> 4103.16 | I7: =I5*(1-I6) -> 4648.2382 | J7: =J5*(1-J6) -> 4920.2756 | K7: =K5*(1-K6) -> 5543.4277 | L7: =L5*(1-L6) -> 5888.8726 | M7: =M5*(1-M6) -> 6277.2098
B8: Add: Depreciation and Amortization | H8: =HistoricalFS!L24 -> 1228.85 | I8: ='Forecast(Explicit)'!C31 -> 1346.0595 | J8: ='Forecast(Explicit)'!D31 -> 1435.9657 | K8: ='Forecast(Explicit)'!E31 -> 1592.6433 | L8: ='Forecast(Explicit)'!F31 -> 1760.9217 | M8: ='Forecast(Explicit)'!G31 -> 1916.0314
B9: Less: Capital Expenditure | H9: =ABS('Raw FS'!N53) -> 1487 | I9: ='Forecast(Explicit)'!C40 -> 600 | J9: ='Forecast(Explicit)'!D40 -> 1000 | K9: ='Forecast(Explicit)'!E40 -> 900 | L9: ='Forecast(Explicit)'!F40 -> 400 | M9: ='Forecast(Explicit)'!G40 -> 0
B10: Less: Change in Operating Working Capital | I10: ='Forecast(Explicit)'!C49-6646 -> 972.7506 | J10: ='Forecast(Explicit)'!D49-'Forecast(Explicit)'!C49 -> 457.12504 | K10: ='Forecast(Explicit)'!E49-'Forecast(Explicit)'!D49 -> 529.96693 | L10: ='Forecast(Explicit)'!F49-'Forecast(Explicit)'!E49 -> 602.40898 | M10: ='Forecast(Explicit)'!G49-'Forecast(Explicit)'!F49 -> 644.57761
B11: Free cash Flow to Firm (FCFF) | I11: =I7+I8-I9-I10 -> 4421.5471 | J11: =J7+J8-J9-J10 -> 4899.1162 | K11: =K7+K8-K9-K10 -> 5706.1041 | L11: =L7+L8-L9-L10 -> 6647.3854 | M11: =M7+M8-M9-M10 -> 7548.6636
B12: Mid Year Convention | I12: 0.5 | J12: 1.5 | K12: 2.5 | L12: 3.5 | M12: 4.5
B13: Discounting Factor | I13: =1/(1+$C$18)^I12 -> 0.95023203 | J13: =1/(1+$C$18)^J12 -> 0.85800336 | K13: =1/(1+$C$18)^K12 -> 0.77472633 | L13: =1/(1+$C$18)^L12 -> 0.69953209 | M13: =1/(1+$C$18)^M12 -> 0.63163614
B15: PV of FCFF | I15: =I11*I13 -> 4201.4957 | J15: =J11*J13 -> 4203.4582 | K15: =K11*K13 -> 4420.6691 | L15: =L11*L13 -> 4650.0594 | M15: =M11*M13 -> 4768.0087
B17: Terminal Growth | C17: 0.065
B18: WACC | C18: =WACC!K33 -> 0.10749219 | G18: Sensitivity Analysis
H19: WACC
B20: Calculation of Terminal Value | F20: TERMINAL GROWTH % | G20: =D39 -> 1447.9888 | H20: 0.1 | I20: 0.129931 | J20: 0.16 | K20: 0.19 | L20: 0.21 | M20: 0.23
G21: 0.03 | H21: 960.33195 | I21: 658.69194 | J21: 496.27649 | K21: 395.60536 | L21: 347.36906 | M21: 308.93302
B22: FCFF(N+1) | D22: =M11*(1+D24) -> 8039.3267 | G22: 0.04 | H22: 1094.5581 | I22: 715.79633 | J22: 526.28423 | K22: 413.44291 | L22: 360.56653 | M22: 318.96784
B23: WACC | D23: =C18 -> 0.10749219 | G23: 0.05 | H23: 1282.4748 | I23: 787.18915 | J23: 561.74793 | K23: 433.82869 | L23: 375.41369 | M23: 330.11763
B24: Terminal Growth Rate | D24: =C17 -> 0.065 | G24: 0.065 | H24: 1765.689 | I24: 935.5103 | J24: 628.9423 | K24: 470.52308 | L24: 401.5242 | M24: 349.37637
G25: 0.08 | H25: 2973.7246 | I25: 1172.9471 | J25: 721.33457 | K25: 517.22504 | L25: 433.66021 | M25: 372.48686
B26: Terminal Value | D26: =D22/(D23-D24) -> 189195.39 | G26: 0.09 | H26: 5792.4742 | I26: 1430.3413 | J26: 804.92757 | K26: 556.14334 | L26: 459.54756 | M26: 390.6451
B28: Calculation of Equity Value
B30: PV of FCFF | D30: =SUM(I15:M15) -> 22243.691
B31: PV of Terminal Value | D31: =D26/(1+C18)^M12 -> 119502.64
B32: Value of Operating Asset | D32: =SUM(D30:D31) -> 141746.34
B34: Add: Cash | D34: =Datasheet!K69 -> 1073.68
B35: Less: Debt | D35: =SUM(Datasheet!K59) -> 3928.93
B36: Enterprise Value | D36: =D32+D34-D35 -> 138891.09
B37: No. of Shares | D37: =Datasheet!K93 -> 95.92
B39: Equity Value per share | D39: =D36/D37 -> 1447.9888
B41: Share Price | D41: 2761
B42: Premium/Discount | D42: =D41/D39-1 -> 0.90678271
B43: As of 29th July 2026

Sheet Relative Valuation
B2: ="Relative Valuation"&" - "&Datasheet!$B$1 -> Relative Valuation - ASIAN PAINTS LTD
B3: Amount in crores
B4: Comparable Companies Valuation
D6: Market Data | K6: Market Data | O6: Valuation
B7: Company | C7: Ticker | D7: Share Price | E7: Shares Outstanding | F7: Equity Value | G7: Net Debt | H7: Enterprise Value | K7: Revenue | L7: EBITDA | M7: Net Income | O7: EV/Revenue | P7: EV/EBITDA | Q7: P/E
B9: ='Data for Rel Val'!C2 -> Asian Paints | D9: ='Data for Rel Val'!D2 -> 2747.3 | E9: ='Data for Rel Val'!E2 -> 95.92 | F9: =D9*E9 -> 263521.02 | G9: ='Data for Rel Val'!H2 -> 2855.25 | H9: =F9+G9 -> 266376.27 | K9: ='Data for Rel Val'!K2 -> 37186.93 | L9: ='Data for Rel Val'!L2 -> 8471.1827 | M9: ='Data for Rel Val'!M2 -> 4837.09 | O9: =$H9/K9 -> 7.163169 | P9: =$H9/L9 -> 31.444991 | Q9: =F9/M9 -> 54.479246
B10: ='Data for Rel Val'!C3 -> Berger Paints | D10: ='Data for Rel Val'!D3 -> 520.45 | E10: ='Data for Rel Val'!E3 -> 116.6 | F10: =D10*E10 -> 60684.47 | G10: ='Data for Rel Val'!H3 -> 329.82 | H10: =F10+G10 -> 61014.29 | K10: ='Data for Rel Val'!K3 -> 11880.25 | L10: ='Data for Rel Val'!L3 -> 2225.1708 | M10: ='Data for Rel Val'!M3 -> 1128.02 | O10: =$H10/K10 -> 5.1357749 | P10: =$H10/L10 -> 27.420048 | Q10: =F10/M10 -> 53.797335
B11: ='Data for Rel Val'!C4 -> Kansai Nerolac | D11: ='Data for Rel Val'!D4 -> 196.74 | E11: ='Data for Rel Val'!E4 -> 80.87 | F11: =D11*E11 -> 15910.364 | G11: ='Data for Rel Val'!H4 -> 76.95 | H11: =F11+G11 -> 15987.314 | K11: ='Data for Rel Val'!K4 -> 8051.91 | L11: ='Data for Rel Val'!L4 -> 1202.9554 | M11: ='Data for Rel Val'!M4 -> 575.84 | O11: =$H11/K11 -> 1.9855306 | P11: =$H11/L11 -> 13.290031 | Q11: =F11/M11 -> 27.629834
B12: ='Data for Rel Val'!C5 -> JSW Dulux | D12: ='Data for Rel Val'!D5 -> 2938.8 | E12: ='Data for Rel Val'!E5 -> 4.55 | F12: =D12*E12 -> 13371.54 | G12: ='Data for Rel Val'!H5 -> -244.6 | H12: =F12+G12 -> 13126.94 | K12: ='Data for Rel Val'!K5 -> 3599.2 | L12: ='Data for Rel Val'!L5 -> 584.51008 | M12: ='Data for Rel Val'!M5 -> 1973.8 | O12: =$H12/K12 -> 3.6471827 | P12: =$H12/L12 -> 22.458022 | Q12: =F12/M12 -> 6.7745162
B13: ='Data for Rel Val'!C6 -> Indigo Paints | D13: ='Data for Rel Val'!D6 -> 1111.8 | E13: ='Data for Rel Val'!E6 -> 4.77 | F13: =D13*E13 -> 5303.286 | G13: ='Data for Rel Val'!H6 -> -10.18 | H13: =F13+G13 -> 5293.106 | K13: ='Data for Rel Val'!K6 -> 1330.12 | L13: ='Data for Rel Val'!L6 -> 302.20326 | M13: ='Data for Rel Val'!M6 -> 145.39 | O13: =$H13/K13 -> 3.9794199 | P13: =$H13/L13 -> 17.515052 | Q13: =F13/M13 -> 36.476278
B14: ='Data for Rel Val'!C7 -> Sirca Paints | D14: ='Data for Rel Val'!D7 -> 420.45 | E14: ='Data for Rel Val'!E7 -> 5.68 | F14: =D14*E14 -> 2388.156 | G14: ='Data for Rel Val'!H7 -> -25.66 | H14: =F14+G14 -> 2362.496 | K14: ='Data for Rel Val'!K7 -> 508.26 | L14: ='Data for Rel Val'!L7 -> 111.30894 | M14: ='Data for Rel Val'!M7 -> 67.05 | O14: =$H14/K14 -> 4.6482037 | P14: =$H14/L14 -> 21.224674 | Q14: =F14/M14 -> 35.617539
B15: ='Data for Rel Val'!C8 -> Shalimar Paints | D15: ='Data for Rel Val'!D8 -> 66.68 | E15: ='Data for Rel Val'!E8 -> 8.37 | F15: =D15*E15 -> 558.1116 | G15: ='Data for Rel Val'!H8 -> 117.67 | H15: =F15+G15 -> 675.7816 | K15: ='Data for Rel Val'!K8 -> 575.63 | L15: ='Data for Rel Val'!L8 -> -28.20587 | M15: ='Data for Rel Val'!M8 -> -64.95 | O15: =$H15/K15 -> 1.1739861 | P15: =$H15/L15 -> -23.958899 | Q15: =F15/M15 -> -8.5929423
B17: High | O17: =MAX(O9:O15) -> 7.163169 | P17: =MAX(P9:P15) -> 31.444991 | Q17: =MAX(Q9:Q15) -> 54.479246
B18: 75th Percentile | O18: =QUARTILE(O9:O15,3) -> 4.8919893 | P18: =QUARTILE(P9:P15,3) -> 24.939035 | Q18: =QUARTILE(Q9:Q15,3) -> 45.136806
B19: Average | O19: =AVERAGE(O9:O15) -> 3.9618953 | P19: =AVERAGE(P9:P15) -> 15.627703 | Q19: =AVERAGE(Q9:Q15) -> 29.454544
B20: Median | O20: =MEDIAN(O9:O15) -> 3.9794199 | P20: =MEDIAN(P9:P15) -> 21.224674 | Q20: =MEDIAN(Q9:Q15) -> 35.617539
B21: 25th Percentile | O21: =QUARTILE(O9:O15,1) -> 2.8163567 | P21: =QUARTILE(P9:P15,1) -> 15.402542 | Q21: =QUARTILE(Q9:Q15,1) -> 17.202175
B22: Low | O22: =MIN(O9:O15) -> 1.1739861 | P22: =MIN(P9:P15) -> -23.958899 | Q22: =MIN(Q9:Q15) -> -8.5929423
B24: Asian Paints Comparable Valuation | O24: EV/Revenue | P24: EV/EBITDA | Q24: P/E
B26: Implied Enterprise Value | O26: =O20*K9 -> 147982.41 | P26: =P20*L9 -> 179798.09 | Q26: =Q28+Q27 -> 175140.49
B27: Net Debt | O27: =$G$9 -> 2855.25 | P27: =$G$9 -> 2855.25 | Q27: =$G$9 -> 2855.25
B28: Implied Market Value | O28: =O26-O27 -> 145127.16 | P28: =P26-P27 -> 176942.84 | Q28: =Q20*M9 -> 172285.24
B29: Share Outstanding | O29: =$E$9 -> 95.92 | P29: =$E$9 -> 95.92 | Q29: =$E$9 -> 95.92
B31: Implied Value Per Share | O31: =O28/O29 -> 1513.0021 | P31: =P28/P29 -> 1844.6919 | Q31: =Q28/Q29 -> 1796.1347
B33: Source: Screener.in | O33: =IF(O31>$D$9,"Undervalued","Overvalued") -> Overvalued | P33: =IF(P31>$D$9,"Undervalued","Overvalued") -> Overvalued | Q33: =IF(Q31>$D$9,"Undervalued","Overvalued") -> Overvalued

Sheet Data>

Sheet Datasheet
A1: COMPANY NAME | B1: ASIAN PAINTS LTD | E1: =IF(B2<>B3, "A NEW VERSION OF THE WORKSHEET IS AVAILABLE", "")
A2: LATEST VERSION | B2: 2.1 | E2: PLEASE DO NOT MAKE ANY CHANGES TO THIS SHEET
A3: CURRENT VERSION | B3: 2.1
A5: META
A6: Number of shares | B6: =IF(B9>0, B9/B8, 0) -> 95.930465
A7: Face Value | B7: 1
A8: Current Price | B8: 2693.05
A9: Market Capitalization | B9: 258345.54
A15: PROFIT & LOSS
A16: Report Date | B16: 42825 | C16: 43190 | D16: 43555 | E16: 43921 | F16: 44286 | G16: 44651 | H16: 45016 | I16: 45382 | J16: 45747 | K16: 46112 | R16: -684 | S16: -1426 | T16: -1151 | U16: -414 | V16: -289 | W16: -551 | X16: -1446 | Y16: -2496 | Z16: -1830 | AA16: -1487
A17: Sales | B17: 15061.99 | C17: 16824.55 | D17: 19240.13 | E17: 20211.25 | F17: 21712.79 | G17: 29101.28 | H17: 34488.59 | I17: 35494.73 | J17: 33905.62 | K17: 35583.54 | R17: 15061.99 | S17: 16824.55 | T17: 19240.13 | U17: 20211.25 | V17: 21712.79 | W17: 29101.28 | X17: 34488.59 | Y17: 35494.73 | Z17: 33905.62 | AA17: 35583.54
A18: Raw Material Cost | B18: 7452.6 | C18: 8128.17 | D18: 9974.4 | E18: 9981.99 | F18: 10425.55 | G18: 17123.25 | H18: 18985.53 | I18: 17410.84 | J18: 17504.51 | K18: 17142.01 | R18: =R16/R17 -> -0.045412326 | S18: =S16/S17 -> -0.084757096 | T18: =T16/T17 -> -0.059822881 | U18: =U16/U17 -> -0.020483642 | V18: =V16/V17 -> -0.013310127 | W18: =W16/W17 -> -0.018933875 | X18: =X16/X17 -> -0.04192691 | Y18: =Y16/Y17 -> -0.070320298 | ... AA18: =AA16/AA17 -> -0.041788984
A19: Change in Inventory | B19: 528.6 | C19: -142.13 | D19: 293.26 | E19: 239.15 | F19: 92.45 | G19: 1324.97 | H19: 309.73 | I19: -363.8 | J19: 205 | K19: -603.68
A20: Power and Fuel | B20: 106.02 | C20: 110.3 | D20: 119.63 | E20: 97.79 | F20: 86.05 | G20: 117.23 | H20: 138.29 | I20: 133.25 | J20: 148.58 | K20: 167.1 | L20: =SUM(B18:B21) -> 9749.97 | M20: =SUM(C18:C21) -> 9788.02 | N20: =SUM(D18:D21) -> 12249.64 | O20: =SUM(E18:E21) -> 12265.05 | W20: =MEDIAN(R18:AA18) -> -0.043669618
A21: Other Mfr. Exp | B21: 1662.75 | C21: 1691.68 | D21: 1862.35 | E21: 1946.12 | F21: 2068.31 | G21: 2880.45 | H21: 2916.2 | I21: 2767.18 | J21: 2687.4 | K21: 2767.11
A22: Employee Cost | B22: 1039.89 | C22: 1121.89 | D22: 1242.69 | E22: 1371.27 | F22: 1547.61 | G22: 1794.61 | H22: 2036.41 | I22: 2334.92 | J22: 2605.78 | K22: 2809.73
A23: Selling and admin | B23: 4364.04 | C23: 2254.92 | D23: 2366.87 | E23: 2311.51 | F23: 2245.69 | G23: 2941.98 | H23: 3500.84 | I23: 3811.86 | J23: 3874.94 | K23: 4112.07
A24: Other Expenses | B24: -2028.47 | C24: 171.45 | D24: 202.51 | E24: 579.95 | F24: 576.43 | G24: 765.12 | H24: 961.21 | I24: 1087.9 | J24: 1283.2 | K24: 1282.11
A25: Other Income | B25: 337.9 | C25: 336.41 | D25: 273.77 | E25: 350.1 | F25: 331.65 | G25: 295.88 | H25: 431.46 | I25: 820.96 | J25: 350.22 | K25: 727.97
A26: Depreciation | B26: 334.79 | C26: 360.47 | D26: 622.14 | E26: 780.5 | F26: 791.27 | G26: 816.36 | H26: 858.02 | I26: 853 | J26: 1026.34 | K26: 1228.85 | N26: 16824.55 | Q26: 334.79 | R26: 360.47 | S26: 622.14 | T26: 780.5 | U26: 791.27 | V26: 816.36 | W26: 858.02 | X26: 853 | Y26: 1026.34 | Z26: 1228.85
A27: Interest | B27: 37.33 | C27: 41.47 | D27: 110.47 | E27: 102.33 | F27: 91.63 | G27: 95.41 | H27: 144.45 | I27: 205.17 | J27: 227.02 | K27: 195.41 | N27: 8128.17
A28: Profit before tax | B28: 2959.54 | C28: 3138.48 | D28: 3306.1 | E28: 3629.04 | F28: 4304.35 | G28: 4187.72 | H28: 5688.83 | I28: 7347.77 | J28: 5103.07 | K28: 6003.44 | N28: -142.13
A29: Tax | B29: 943.29 | C29: 1040.96 | D29: 1098.06 | E29: 854.85 | F29: 1097.6 | G29: 1102.91 | H29: 1493.5 | I29: 1790.08 | J29: 1393.36 | K29: 1608.75 | N29: 110.3
A30: Net profit | B30: 1939.43 | C30: 2038.93 | D30: 2155.92 | E30: 2705.17 | F30: 3139.29 | G30: 3030.57 | H30: 4106.45 | I30: 5460.23 | J30: 3667.23 | K30: 4325.35 | N30: 1691.68
A31: Dividend Amount | B31: 987.98 | C31: 834.5 | D31: 1007.16 | E31: 1151.04 | F31: 1712.17 | G31: 1836.87 | H31: 2460.35 | I31: 3194.14 | J31: 2378.82 | K31: 2637.8 | N31: 1121.89
N32: 2254.92
N33: 171.45
C34: =C24/C17 -> 0.010190466 | D34: =D24/D17 -> 0.010525397 | E34: =E24/E17 -> 0.028694415 | F34: =F24/F17 -> 0.026547947 | G34: =G24/G17 -> 0.026291627 | H34: =H24/H17 -> 0.027870377 | I34: =I24/I17 -> 0.03064962 | J34: =J24/J17 -> 0.037846233 | K34: =K24/K17 -> 0.036030985 | N34: 360.47
N35: 41.47
N36: =N26-SUM(N27:N35) -> 3086.33
N37: =N36-C29 -> 2045.37
A40: Quarters
A41: Report Date | B41: 45291 | C41: 45382 | D41: 45473 | E41: 45565 | F41: 45657 | G41: 45747 | H41: 45838 | I41: 45930 | J41: 46022 | K41: 46112
A42: Sales | B42: 9103.09 | C42: 8730.76 | D42: 8969.73 | E42: 8027.54 | F42: 8549.44 | G42: 8358.91 | H42: 8938.55 | I42: 8531.27 | J42: 8867.02 | K42: 9246.7
A43: Expenses | B43: 7047 | C43: 7039.39 | D43: 7275.96 | E43: 6788.03 | F43: 6912.71 | G43: 6922.71 | H43: 7313.58 | I43: 7027.89 | J43: 7086.06 | K43: 7460.09
A44: Other Income | B44: 186.46 | C44: 212.43 | D44: 192.93 | E44: 24.53 | F44: 192.82 | G44: -60.06 | H44: 229.11 | I44: 236.94 | J44: 69.14 | K44: 196.59
A45: Depreciation | B45: 220.35 | C45: 225.61 | D45: 227.7 | E45: 241.99 | F45: 255.55 | G45: 301.1 | H45: 300.87 | I45: 304.93 | J45: 313.07 | K45: 309.98
A46: Interest | B46: 54.42 | C46: 54.1 | D46: 55.38 | E46: 63.01 | F46: 55.84 | G46: 52.79 | H46: 44.5 | I46: 43.87 | J46: 47.94 | K46: 59.1
A47: Profit before tax | B47: 1967.78 | C47: 1624.09 | D47: 1603.62 | E47: 959.04 | F47: 1518.16 | G47: 1022.25 | H47: 1508.71 | I47: 1391.52 | J47: 1489.09 | K47: 1614.12
A48: Tax | B48: 492.62 | C48: 348.79 | D48: 416.83 | E48: 265.38 | F48: 389.73 | G48: 321.42 | H48: 391.66 | I48: 373.29 | J48: 415.17 | K48: 428.63
A49: Net profit | B49: 1447.72 | C49: 1256.72 | D49: 1169.98 | E49: 694.64 | F49: 1110.48 | G49: 692.13 | H49: 1099.77 | I49: 993.59 | J49: 1059.87 | K49: 1172.12
A50: Operating Profit | B50: 2056.09 | C50: 1691.37 | D50: 1693.77 | E50: 1239.51 | F50: 1636.73 | G50: 1436.2 | H50: 1624.97 | I50: 1503.38 | J50: 1780.96 | K50: 1786.61
A55: BALANCE SHEET
A56: Report Date | B56: 42825 | C56: 43190 | D56: 43555 | E56: 43921 | F56: 44286 | G56: 44651 | H56: 45016 | I56: 45382 | J56: 45747 | K56: 46112
A57: Equity Share Capital | B57: 95.92 | C57: 95.92 | D57: 95.92 | E57: 95.92 | F57: 95.92 | G57: 95.92 | H57: 95.92 | I57: 95.92 | J57: 95.92 | K57: 95.92
A58: Reserves | B58: 7507.97 | C58: 8314.31 | D58: 9374.63 | E58: 10034.24 | F58: 12710.37 | G58: 13715.64 | H58: 15896.31 | I58: 18632.38 | J58: 19303.89 | K58: 21275.67
A59: Borrowings | B59: 560.34 | C59: 533.43 | D59: 1319.6 | E59: 1118.5 | F59: 1093.12 | G59: 1586.88 | H59: 1932.62 | I59: 2474.38 | J59: 2290.29 | K59: 3928.93
A60: Other Liabilities | B60: 4240.96 | C60: 4819.82 | D60: 5458.69 | E60: 4889.31 | F60: 6455.93 | G60: 7559.99 | H60: 7854.48 | I60: 8698.09 | J60: 8665.15 | K60: 9218.23
A61: Total | B61: 12405.19 | C61: 13763.48 | D61: 16248.84 | E61: 16137.97 | F61: 20355.34 | G61: 22958.43 | H61: 25779.33 | I61: 29900.77 | J61: 30355.25 | K61: 34518.75
A62: Net Block | B62: 3303.74 | C62: 3732.24 | D62: 6496.56 | E62: 6272.31 | F62: 5858.52 | G62: 5519.06 | H62: 5770.46 | I62: 7146.62 | J62: 9220.1 | K62: 9640.28
A63: Capital Work in Progress | B63: 257.54 | C63: 1405.11 | D63: 209.67 | E63: 140.24 | F63: 182.98 | G63: 426.43 | H63: 1019.59 | I63: 2698.37 | J63: 1254.49 | K63: 1848.67
A64: Investments | B64: 2651.99 | C64: 2140.7 | D64: 2568.58 | E64: 2018.85 | F64: 4736.8 | G64: 3247.53 | H64: 4261.71 | I64: 4587.92 | J64: 4724.75 | K64: 7061.74
A65: Other Assets | B65: 6191.92 | C65: 6485.43 | D65: 6974.03 | E65: 7706.57 | F65: 9577.04 | G65: 13765.41 | H65: 14727.57 | I65: 15467.86 | J65: 15155.91 | K65: 15968.06
A66: Total | B66: 12405.19 | C66: 13763.48 | D66: 16248.84 | E66: 16137.97 | F66: 20355.34 | G66: 22958.43 | H66: 25779.33 | I66: 29900.77 | J66: 30355.25 | K66: 34518.75
A67: Receivables | B67: 1446.6 | C67: 1730.63 | D67: 1907.33 | E67: 1795.22 | F67: 2602.17 | G67: 3871.44 | H67: 4636.94 | I67: 4889.05 | J67: 4313.65 | K67: 4461.8
... A70: No. of Equity Shares | B70: 959197790 | C70: 959197790 | D70: 959197790 | E70: 959197790 | F70: 959197790 | G70: 959197790 | H70: 959197790 | I70: 959197790 | J70: 959197790 | K70: 959197790
A71: New Bonus Shares
A72: Face value | B72: 1 | C72: 1 | D72: 1 | E72: 1 | F72: 1 | G72: 1 | H72: 1 | I72: 1 | J72: 1 | K72: 1
B74: 1937 | C74: 1750 | D74: 1925 | E74: 2316 | F74: 2690 | G74: 2320 | H74: 2613 | I74: 2932 | J74: 3657 | K74: 4017
B75: 15061.99 | C75: 16824.55 | D75: 19240.13 | E75: 20211.25 | F75: 21712.79 | G75: 29101.28 | H75: 34488.59 | I75: 35494.73 | J75: 33905.62 | K75: 35583.54
B76: =B74/B75 -> 0.12860186 | C76: =C74/C75 -> 0.10401467 | D76: =D74/D75 -> 0.1000513 | E76: =E74/E75 -> 0.11458965 | F76: =F74/F75 -> 0.12389011 | G76: =G74/G75 -> 0.079721579 | H76: =H74/H75 -> 0.075764188 | I76: =I74/I75 -> 0.082603812 | ... K76: =K74/K75 -> 0.11288927
A80: CASH FLOW:
A81: Report Date | B81: 42825 | C81: 43190 | D81: 43555 | E81: 43921 | F81: 44286 | G81: 44651 | H81: 45016 | I81: 45382 | J81: 45747 | K81: 46112
A82: Cash from Operating Activity | B82: 1527.33 | C82: 2113.44 | D82: 2469.54 | E82: 3038.15 | F82: 3683.35 | G82: 986.49 | H82: 4193.43 | I82: 6103.6 | J82: 4423.96 | K82: 7088.18
A83: Cash from Investing Activity | B83: -681.11 | C83: -1556.14 | D83: -917.79 | E83: -517.91 | F83: -540.54 | G83: -316.75 | H83: -1282.34 | I83: -2548.48 | J83: -940.91 | K83: -1328.23
A84: Cash from Financing Activity | B84: -756.43 | C84: -1379.14 | D84: -1117.46 | E84: -2871.46 | F84: -650.4 | G84: -1807.61 | H84: -2140.05 | I84: -2982.5 | J84: -3752.58 | K84: -2376.51
A85: Net Cash Flow | B85: 89.79 | C85: -821.84 | D85: 434.29 | E85: -351.22 | F85: 2492.41 | G85: -1137.87 | H85: 771.04 | I85: 572.62 | J85: -269.53 | K85: 3383.44
A90: PRICE: | B90: 1073.5 | C90: 1120.4 | D90: 1492.7 | E90: 1666.5 | F90: 2537.4 | G90: 3079.95 | H90: 2761.65 | I90: 2846.75 | J90: 2340.65 | K90: 2165.2
A92: DERIVED:
A93: Adjusted Equity Shares in Cr | B93: 95.92 | C93: 95.92 | D93: 95.92 | E93: 95.92 | F93: 95.92 | G93: 95.92 | H93: 95.92 | I93: 95.92 | J93: 95.92 | K93: 95.92

Sheet Beta
B3: Regression Beta
B5: #VALUE! | F5: #VALUE! | J5: Beta Drifting - AP | N5: #VALUE! | R5: #VALUE! | V5: #VALUE! | Z5: #VALUE! | AD5: #VALUE!
B7: {=_xlfn.STOCKHISTORY(B5,"2021-07-22","2026-07-22",1,1,0,1)} -> Date | C7: Close | D7: Weekly Returns | F7: {=_xlfn.STOCKHISTORY(F5,"2021-07-22","2026-07-22",1,1,0,1)} -> Date | G7: Close | H7: Weekly Return | J7: Raw Beta | L7: =_xlfn.COVARIANCE.S(D9:D269,H9:H269)/_xlfn.VAR.S(H9:H269) -> 0.92190928 | N7: {=_xlfn.STOCKHISTORY(N5,"2021-07-22","2026-07-22",1,1,0,1)} -> Date | O7: Close | P7: Weekly Returns | R7: {=_xlfn.STOCKHISTORY(R5,"2021-07-22","2026-07-22",1,1,0,1)} -> Date | S7: Close | T7: Weekly Returns | V7: {=_xlfn.STOCKHISTORY(V5,"2021-07-22","2026-07-22",1,1,0,1)} -> Date | W7: Close | X7: Weekly Returns | Z7: {=_xlfn.STOCKHISTORY(Z5,"2021-07-22","2026-07-22",1,1,0,1)} -> Date | AA7: Close | AB7: Weekly Returns | AD7: {=_xlfn.STOCKHISTORY(AD5,"2021-07-22","2026-07-22",1,1,0,1)} -> Date | AE7: Close | AF7: Weekly Returns
B8: 44396 | C8: 3083.75 | F8: 44396 | G8: 15856.05 | J8: Levered Raw Beta | L8: =L7 -> 0.92190928 | N8: 44396 | O8: 413.8679 | R8: 44396 | S8: 711.8722 | V8: 44396 | W8: 2190.8872 | Z8: 44396 | AA8: 2599.6 | AD8: 44396 | AE8: 173.875
B9: 44403 | C9: 2958.45 | D9: =C9/C8-1 -> -0.040632347 | F9: 44403 | G9: 15763.05 | H9: =G9/G8-1 -> -0.0058652691 | J9: Beta Weight | L9: 0.75 | N9: 44403 | O9: 415.1279 | P9: =O9/O8-1 -> 0.0030444497 | R9: 44403 | S9: 702.9555 | T9: =S9/S8-1 -> -0.012525703 | V9: 44403 | W9: 2174.5191 | X9: =W9/W8-1 -> -0.0074709917 | Z9: 44403 | AA9: 2605.1 | AB9: =AA9/AA8-1 -> 0.0021157101 | AD9: 44403 | AE9: 169.5 | AF9: =AE9/AE8-1 -> -0.025161754
B10: 44410 | C10: 2966.45 | D10: =C10/C9-1 -> 0.0027041187 | F10: 44410 | G10: 16238.2 | H10: =G10/G9-1 -> 0.030143278 | J10: Market Beta | L10: 1 | N10: 44410 | O10: 422.1247 | P10: =O10/O9-1 -> 0.016854565 | R10: 44410 | S10: 689.8306 | T10: =S10/S9-1 -> -0.018671025 | V10: 44410 | W10: 2130.2965 | X10: =W10/W9-1 -> -0.020336726 | Z10: 44410 | AA10: 2624.4 | AB10: =AA10/AA9-1 -> 0.0074085448 | AD10: 44410 | AE10: 174.875 | AF10: =AE10/AE9-1 -> 0.031710914
B11: 44417 | C11: 2988.7 | D11: =C11/C10-1 -> 0.0075005478 | F11: 44417 | G11: 16529.1 | H11: =G11/G10-1 -> 0.017914547 | J11: Market Beta Weight | L11: 0.25 | N11: 44417 | O11: 416.5538 | P11: =O11/O10-1 -> -0.013197285 | R11: 44417 | S11: 675.9556 | T11: =S11/S10-1 -> -0.020113634 | V11: 44417 | W11: 2123.9311 | X11: =W11/W10-1 -> -0.0029880348 | Z11: 44417 | AA11: 2422.15 | AB11: =AA11/AA10-1 -> -0.077065234 | AD11: 44417 | AE11: 170.675 | AF11: =AE11/AE10-1 -> -0.024017155
B12: 44424 | C12: 3112.95 | D12: =C12/C11-1 -> 0.041573259 | F12: 44424 | G12: 16450.5 | H12: =G12/G11-1 -> -0.0047552498 | N12: 44424 | O12: 414.8295 | P12: =O12/O11-1 -> -0.0041394413 | R12: 44424 | S12: 682.7056 | T12: =S12/S11-1 -> 0.009985863 | V12: 44424 | W12: 2119.6237 | X12: =W12/W11-1 -> -0.0020280319 | Z12: 44424 | AA12: 2433 | AB12: =AA12/AA11-1 -> 0.0044794914 | AD12: 44424 | AE12: 162.85 | AF12: =AE12/AE11-1 -> -0.045847371
B13: 44431 | C13: 3036.8 | D13: =C13/C12-1 -> -0.024462327 | F13: 44432 | G13: 16705.2 | H13: =G13/G12-1 -> 0.015482812 | J13: Adjusted Beta | L13: =(L8*L9)+L10*L11 -> 0.94143196 | N13: 44431 | O13: 412.6078 | P13: =O13/O12-1 -> -0.0053556943 | R13: 44431 | S13: 654.8724 | T13: =S13/S12-1 -> -0.040768964 | V13: 44431 | W13: 2106.9886 | X13: =W13/W12-1 -> -0.0059610109 | Z13: 44431 | AA13: 2590.6 | AB13: =AA13/AA12-1 -> 0.064775997 | AD13: 44431 | AE13: 173.225 | AF13: =AE13/AE12-1 -> 0.063708935
B14: 44438 | C14: 3338.8 | D14: =C14/C13-1 -> 0.099446786 | F14: 44438 | G14: 17323.6 | H14: =G14/G13-1 -> 0.037018413 | N14: 44438 | O14: 410.8835 | P14: =O14/O13-1 -> -0.0041790291 | R14: 44438 | S14: 692.7889 | T14: =S14/S13-1 -> 0.057899066 | V14: 44438 | W14: 2158.1031 | X14: =W14/W13-1 -> 0.024259505 | Z14: 44438 | AA14: 2626.05 | AB14: =AA14/AA13-1 -> 0.013684089 | AD14: 44438 | AE14: 168.925 | AF14: =AE14/AE13-1 -> -0.024823207
B15: 44445 | C15: 3346.35 | D15: =C15/C14-1 -> 0.0022612915 | F15: 44445 | G15: 17369.25 | H15: =G15/G14-1 -> 0.0026351336 | J15: Beta Drifting - KN | N15: 44445 | O15: 405.3458 | P15: =O15/O14-1 -> -0.013477543 | R15: 44445 | S15: 697.1222 | T15: =S15/S14-1 -> 0.0062548635 | V15: 44445 | W15: 2101.8676 | X15: =W15/W14-1 -> -0.026057838 | Z15: 44445 | AA15: 2590.15 | AB15: =AA15/AA14-1 -> -0.013670722 | AD15: 44445 | AE15: 165.2 | AF15: =AE15/AE14-1 -> -0.022051206
B16: 44452 | C16: 3303.05 | D16: =C16/C15-1 -> -0.012939471 | F16: 44452 | G16: 17585.15 | H16: =G16/G15-1 -> 0.012430013 | N16: 44452 | O16: 407.1696 | P16: =O16/O15-1 -> 0.0044993682 | R16: 44452 | S16: 682.2889 | T16: =S16/S15-1 -> -0.021277905 | V16: 44452 | W16: 2116.5128 | X16: =W16/W15-1 -> 0.0069677081 | Z16: 44452 | AA16: 2605.35 | AB16: =AA16/AA15-1 -> 0.005868386 | AD16: 44452 | AE16: 169.275 | AF16: =AE16/AE15-1 -> 0.02466707
B17: 44459 | C17: 3448.6 | D17: =C17/C16-1 -> 0.044065334 | F17: 44459 | G17: 17853.2 | H17: =G17/G16-1 -> 0.015242975 | J17: Raw Beta | L17: =_xlfn.COVARIANCE.S(P9:P269,$H$9:$H$269)/_xlfn.VAR.S($H$9:$H$269) -> 0.85397352 | N17: 44459 | O17: 416.9186 | P17: =O17/O16-1 -> 0.02394334 | R17: 44459 | S17: 700.0805 | T17: =S17/S16-1 -> 0.026076344 | V17: 44459 | W17: 2112.5883 | X17: =W17/W16-1 -> -0.0018542293 | Z17: 44459 | AA17: 2587.85 | AB17: =AA17/AA16-1 -> -0.0067169478 | AD17: 44459 | AE17: 172.025 | AF17: =AE17/AE16-1 -> 0.016245754
B18: 44466 | C18: 3177.85 | D18: =C18/C17-1 -> -0.07851012 | F18: 44466 | G18: 17532.05 | H18: =G18/G17-1 -> -0.017988372 | J18: Levered Raw Beta | L18: =L17 -> 0.85397352 | N18: 44466 | O18: 422.5557 | P18: =O18/O17-1 -> 0.013520865 | R18: 44466 | S18: 675.3306 | T18: =S18/S17-1 -> -0.035352934 | V18: 44466 | W18: 2153.365 | X18: =W18/W17-1 -> 0.019301773 | Z18: 44466 | AA18: 2526.3 | AB18: =AA18/AA17-1 -> -0.023784222 | AD18: 44466 | AE18: 178.025 | AF18: =AE18/AE17-1 -> 0.034878651
B19: 44473 | C19: 3306.9 | D19: =C19/C18-1 -> 0.040609217 | F19: 44473 | G19: 17895.2 | H19: =G19/G18-1 -> 0.020713493 | J19: Beta Weight | L19: 0.75 | N19: 44473 | O19: 418.9413 | P19: =O19/O18-1 -> -0.0085536652 | R19: 44473 | S19: 691.9556 | T19: =S19/S18-1 -> 0.024617572 | V19: 44473 | W19: 2143.2187 | X19: =W19/W18-1 -> -0.0047118347 | Z19: 44473 | AA19: 2533.3 | AB19: =AA19/AA18-1 -> 0.0027708507 | AD19: 44473 | AE19: 204.475 | AF19: =AE19/AE18-1 -> 0.14857464
B20: 44480 | C20: 3297.8 | D20: =C20/C19-1 -> -0.0027518219 | F20: 44480 | G20: 18338.55 | H20: =G20/G19-1 -> 0.0247748 | J20: Market Beta | L20: 1 | N20: 44480 | O20: 402.693 | P20: =O20/O19-1 -> -0.038784192 | R20: 44480 | S20: 698.7055 | T20: =S20/S19-1 -> 0.0097548166 | V20: 44480 | W20: 2126.0848 | X20: =W20/W19-1 -> -0.0079944711 | Z20: 44480 | AA20: 2508 | AB20: =AA20/AA19-1 -> -0.0099869735 | AD20: 44480 | AE20: 208.925 | AF20: =AE20/AE19-1 -> 0.021763052
B21: 44487 | C21: 2982.4 | D21: =C21/C20-1 -> -0.095639517 | F21: 44487 | G21: 18114.9 | H21: =G21/G20-1 -> -0.012195621 | J21: Market Beta Weight | L21: 0.25 | N21: 44487 | O21: 364.6587 | P21: =O21/O20-1 -> -0.094449866 | R21: 44487 | S21: 613.7059 | T21: =S21/S20-1 -> -0.12165297 | V21: 44487 | W21: 2068.7485 | X21: =W21/W20-1 -> -0.026968021 | Z21: 44487 | AA21: 2420.8 | AB21: =AA21/AA20-1 -> -0.03476874 | AD21: 44487 | AE21: 198.95 | AF21: =AE21/AE20-1 -> -0.047744406
B22: 44494 | C22: 3100.1 | D22: =C22/C21-1 -> 0.039464861 | F22: 44494 | G22: 17671.65 | H22: =G22/G21-1 -> -0.024468807 | N22: 44494 | O22: 361.4753 | P22: =O22/O21-1 -> -0.0087298068 | R22: 44494 | S22: 617.9142 | T22: =S22/S21-1 -> 0.0068571933 | V22: 44494 | W22: 2010.9815 | X22: =W22/W21-1 -> -0.027923646 | Z22: 44494 | AA22: 2390.35 | AB22: =AA22/AA21-1 -> -0.012578486 | AD22: 44494 | AE22: 181.325 | AF22: =AE22/AE21-1 -> -0.088590098
B23: 44501 | C23: 3159.25 | D23: =C23/C22-1 -> 0.01908003 | F23: 44501 | G23: 17916.8 | H23: =G23/G22-1 -> 0.013872502 | J23: Adjusted Beta | L23: =(L18*L19)+L20*L21 -> 0.89048014 | N23: 44501 | O23: 381.2386 | P23: =O23/O22-1 -> 0.054673998 | R23: 44501 | S23: 635.8308 | T23: =S23/S22-1 -> 0.028995288 | V23: 44501 | W23: 2034.8158 | X23: =W23/W22-1 -> 0.011852073 | Z23: 44501 | AA23: 2349.85 | AB23: =AA23/AA22-1 -> -0.016943125 | AD23: 44501 | AE23: 197.85 | AF23: =AE23/AE22-1 -> 0.091134703
B24: 44508 | C24: 3122.9 | D24: =C24/C23-1 -> -0.011505895 | F24: 44508 | G24: 18102.75 | H24: =G24/G23-1 -> 0.010378527 | N24: 44508 | O24: 395.63 | P24: =O24/O23-1 -> 0.037749063 | R24: 44508 | S24: 662.0807 | T24: =S24/S23-1 -> 0.041284411 | V24: 44508 | W24: 2025.4352 | X24: =W24/W23-1 -> -0.0046100487 | Z24: 44508 | AA24: 2298.7 | AB24: =AA24/AA23-1 -> -0.021767347 | AD24: 44508 | AE24: 210.95 | AF24: =AE24/AE23-1 -> 0.066211777
B25: 44515 | C25: 3226.85 | D25: =C25/C24-1 -> 0.033286368 | F25: 44515 | G25: 17764.8 | H25: =G25/G24-1 -> -0.018668434 | J25: Beta Drifting - BP | N25: 44515 | O25: 391.8829 | P25: =O25/O24-1 -> -0.0094712231 | R25: 44515 | S25: 656.789 | T25: =S25/S24-1 -> -0.0079925302 | V25: 44515 | W25: 2109.1902 | X25: =W25/W24-1 -> 0.041351607 | Z25: 44515 | AA25: 2300.7 | AB25: =AA25/AA24-1 -> 0.00087005699 | AD25: 44515 | AE25: 233.475 | AF25: =AE25/AE24-1 -> 0.10677886
B26: 44522 | C26: 3143.1 | D26: =C26/C25-1 -> -0.025954104 | F26: 44522 | G26: 17026.45 | H26: =G26/G25-1 -> -0.041562528 | N26: 44522 | O26: 384.5877 | P26: =O26/O25-1 -> -0.018615765 | R26: 44522 | S26: 635.0808 | T26: =S26/S25-1 -> -0.033052015 | V26: 44522 | W26: 2001.5531 | X26: =W26/W25-1 -> -0.051032429 | Z26: 44522 | AA26: 2234.1 | AB26: =AA26/AA25-1 -> -0.028947712 | AD26: 44522 | AE26: 240.075 | AF26: =AE26/AE25-1 -> 0.028268551
B27: 44529 | C27: 3110.45 | D27: =C27/C26-1 -> -0.010387834 | F27: 44529 | G27: 17196.7 | H27: =G27/G26-1 -> 0.0099991484 | J27: Raw Beta | L27: =_xlfn.COVARIANCE.S(T9:T269,$H$9:$H$269)/_xlfn.VAR.S($H$9:$H$269) -> 0.91926614 | N27: 44529 | O27: 394.5025 | P27: =O27/O26-1 -> 0.025780336 | R27: 44529 | S27: 608.2892 | T27: =S27/S26-1 -> -0.042186128 | V27: 44529 | W27: 1971.0184 | X27: =W27/W26-1 -> -0.015255503 | Z27: 44529 | AA27: 2208.7 | AB27: =AA27/AA26-1 -> -0.011369231 | AD27: 44529 | AE27: 278.225 | AF27: =AE27/AE26-1 -> 0.15890867
B28: 44536 | C28: 3283.15 | D28: =C28/C27-1 -> 0.055522513 | F28: 44536 | G28: 17511.3 | H28: =G28/G27-1 -> 0.018294208 | J28: Levered Raw Beta | L28: =L27 -> 0.91926614 | N28: 44536 | O28: 395.9616 | P28: =O28/O27-1 -> 0.0036985824 | R28: 44536 | S28: 635.4141 | T28: =S28/S27-1 -> 0.044592112 | V28: 44536 | W28: 1971.5448 | X28: =W28/W27-1 -> 0.00026707006 | Z28: 44536 | AA28: 2071.75 | AB28: =AA28/AA27-1 -> -0.062004799 | AD28: 44536 | AE28: 287.325 | AF28: =AE28/AE27-1 -> 0.032707341
B29: 44543 | C29: 3243.7 | D29: =C29/C28-1 -> -0.012015899 | F29: 44543 | G29: 16985.2 | H29: =G29/G28-1 -> -0.030043458 | J29: Beta Weight | L29: 0.75 | N29: 44543 | O29: 391.1865 | P29: =O29/O28-1 -> -0.012059503 | R29: 44543 | S29: 627.7058 | T29: =S29/S28-1 -> -0.012131144 | V29: 44543 | W29: 1905.6895 | X29: =W29/W28-1 -> -0.033402893 | Z29: 44543 | AA29: 2036.8 | AB29: =AA29/AA28-1 -> -0.016869796 | AD29: 44543 | AE29: 256.8 | AF29: =AE29/AE28-1 -> -0.10623858
B30: 44550 | C30: 3284.8 | D30: =C30/C29-1 -> 0.012670716 | F30: 44550 | G30: 17003.75 | H30: =G30/G29-1 -> 0.0010921273 | J30: Market Beta | L30: 1 | N30: 44550 | O30: 381.8686 | P30: =O30/O29-1 -> -0.023819585 | R30: 44550 | S30: 617.4142 | T30: =S30/S29-1 -> -0.016395579 | V30: 44550 | W30: 1889.6085 | X30: =W30/W29-1 -> -0.0084384156 | Z30: 44550 | AA30: 1914.15 | AB30: =AA30/AA29-1 -> -0.060217007 | AD30: 44550 | AE30: 253.175 | AF30: =AE30/AE29-1 -> -0.014116044
B31: 44557 | C31: 3382.95 | D31: =C31/C30-1 -> 0.029880054 | F31: 44557 | G31: 17354.05 | H31: =G31/G30-1 -> 0.020601338 | J31: Market Beta Weight | L31: 0.25 | N31: 44557 | O31: 392.0819 | P31: =O31/O30-1 -> 0.026745587 | R31: 44557 | S31: 643.1224 | T31: =S31/S30-1 -> 0.041638498 | V31: 44557 | W31: 1957.9047 | X31: =W31/W30-1 -> 0.036143042 | Z31: 44557 | AA31: 2130.75 | AB31: =AA31/AA30-1 -> 0.11315728 | AD31: 44557 | AE31: 267.875 | AF31: =AE31/AE30-1 -> 0.058062605
B32: 44564 | C32: 3576.3 | D32: =C32/C31-1 -> 0.057154259 | F32: 44564 | G32: 17812.7 | H32: =G32/G31-1 -> 0.026428989 | N32: 44564 | O32: 396.5253 | P32: =O32/O31-1 -> 0.011332836 | R32: 44564 | S32: 658.9557 | T32: =S32/S31-1 -> 0.024619419 | V32: 44564 | W32: 1914.1607 | X32: =W32/W31-1 -> -0.022342252 | Z32: 44564 | AA32: 2062.55 | AB32: =AA32/AA31-1 -> -0.032007509 | AD32: 44564 | AE32: 259.225 | AF32: =AE32/AE31-1 -> -0.032291181
B33: 44571 | C33: 3364.4 | D33: =C33/C32-1 -> -0.059251181 | F33: 44571 | G33: 18255.75 | H33: =G33/G32-1 -> 0.024872703 | J33: Adjusted Beta | L33: =(L28*L29)+L30*L31 -> 0.9394496 | N33: 44571 | O33: 404.8152 | P33: =O33/O32-1 -> 0.020906358 | R33: 44571 | S33: 642.7891 | T33: =S33/S32-1 -> -0.024533667 | V33: 44571 | W33: 1895.0167 | X33: =W33/W32-1 -> -0.01000125 | Z33: 44571 | AA33: 2072.1 | AB33: =AA33/AA32-1 -> 0.0046301908 | AD33: 44571 | AE33: 288.4 | AF33: =AE33/AE32-1 -> 0.11254702
B34: 44578 | C34: 3274.85 | D34: =C34/C33-1 -> -0.02661693 | F34: 44578 | G34: 17617.15 | H34: =G34/G33-1 -> -0.034980759 | N34: 44578 | O34: 381.8023 | P34: =O34/O33-1 -> -0.056847915 | R34: 44578 | S34: 620.6225 | T34: =S34/S33-1 -> -0.034485028 | V34: 44578 | W34: 1885.9712 | X34: =W34/W33-1 -> -0.0047733089 | Z34: 44578 | AA34: 2014.15 | AB34: =AA34/AA33-1 -> -0.027966797 | AD34: 44578 | AE34: 277.15 | AF34: =AE34/AE33-1 -> -0.039008322
B35: 44585 | C35: 3110.85 | D35: =C35/C34-1 -> -0.05007863 | F35: 44585 | G35: 17101.95 | H35: =G35/G34-1 -> -0.029244231 | J35: Beta Drifting - JSWD | N35: 44585 | O35: 378.2874 | P35: =O35/O34-1 -> -0.0092060734 | R35: 44585 | S35: 605.3309 | T35: =S35/S34-1 -> -0.024639132 | V35: 44585 | W35: 1851.4641 | X35: =W35/W34-1 -> -0.018296727 | Z35: 44585 | AA35: 1959.35 | AB35: =AA35/AA34-1 -> -0.027207507 | AD35: 44585 | AE35: 260.125 | AF35: =AE35/AE34-1 -> -0.061428829
B36: 44592 | C36: 3236.65 | D36: =C36/C35-1 -> 0.040439108 | F36: 44592 | G36: 17516.3 | H36: =G36/G35-1 -> 0.024228231 | N36: 44592 | O36: 358.5904 | P36: =O36/O35-1 -> -0.052068877 | R36: 44592 | S36: 612.6642 | T36: =S36/S35-1 -> 0.012114531 | V36: 44592 | W36: 1821.0251 | X36: =W36/W35-1 -> -0.016440502 | Z36: 44592 | AA36: 1977.55 | AB36: =AA36/AA35-1 -> 0.0092887948 | AD36: 44592 | AE36: 255.25 | AF36: =AE36/AE35-1 -> -0.01874099
B37: 44599 | C37: 3216.3 | D37: =C37/C36-1 -> -0.006287365 | F37: 44599 | G37: 17374.75 | H37: =G37/G36-1 -> -0.0080810445 | J37: Raw Beta | L37: =_xlfn.COVARIANCE.S(X9:X269,$H$9:$H$269)/_xlfn.VAR.S($H$9:$H$269) -> 0.42739972 | N37: 44599 | O37: 329.9403 | P37: =O37/O36-1 -> -0.07989645 | R37: 44599 | S37: 598.2893 | T37: =S37/S36-1 -> -0.023462935 | V37: 44599 | W37: 1809.5387 | X37: =W37/W36-1 -> -0.0063076561 | Z37: 44599 | AA37: 1933.65 | AB37: =AA37/AA36-1 -> -0.022199186 | AD37: 44599 | AE37: 241.55 | AF37: =AE37/AE36-1 -> -0.05367287
B38: 44606 | C38: 3258.45 | D38: =C38/C37-1 -> 0.013105121 | F38: 44606 | G38: 17276.3 | H38: =G38/G37-1 -> -0.0056662686 | J38: Levered Raw Beta | L38: =L37 -> 0.42739972 | N38: 44606 | O38: 328.0502 | P38: =O38/O37-1 -> -0.0057286121 | R38: 44606 | S38: 614.8309 | T38: =S38/S37-1 -> 0.027648163 | V38: 44606 | W38: 1855.9151 | X38: =W38/W37-1 -> 0.025628852 | Z38: 44606 | AA38: 1760.2 | AB38: =AA38/AA37-1 -> -0.089700825 | AD38: 44606 | AE38: 235.7 | AF38: =AE38/AE37-1 -> -0.024218588
B39: 44613 | C39: 3119.2 | D39: =C39/C38-1 -> -0.042735043 | F39: 44613 | G39: 16658.4 | H39: =G39/G38-1 -> -0.03576576 | J39: Beta Weight | L39: 0.75 | N39: 44613 | O39: 299.0022 | P39: =O39/O38-1 -> -0.088547424 | R39: 44613 | S39: 571.4144 | T39: =S39/S38-1 -> -0.070615351 | V39: 44613 | W39: 1790.5383 | X39: =W39/W38-1 -> -0.03522618 | Z39: 44613 | AA39: 1747.5 | AB39: =AA39/AA38-1 -> -0.0072150892 | AD39: 44613 | AE39: 211.275 | AF39: =AE39/AE38-1 -> -0.10362749
B40: 44620 | C40: 2738.15 | D40: =C40/C39-1 -> -0.12216273 | F40: 44620 | G40: 16245.35 | H40: =G40/G39-1 -> -0.024795298 | J40: Market Beta | L40: 1 | N40: 44620 | O40: 295.1225 | P40: =O40/O39-1 -> -0.01297549 | R40: 44620 | S40: 544.2062 | T40: =S40/S39-1 -> -0.047615531 | V40: 44620 | W40: 1758.1371 | X40: =W40/W39-1 -> -0.018095787 | Z40: 44620 | AA40: 1648.1 | AB40: =AA40/AA39-1 -> -0.056881259 | AD40: 44620 | AE40: 204.075 | AF40: =AE40/AE39-1 -> -0.034078807
B41: 44627 | C41: 2932 | D41: =C41/C40-1 -> 0.070795975 | F41: 44627 | G41: 16630.45 | H41: =G41/G40-1 -> 0.023705245 | J41: Market Beta Weight | L41: 0.25 | N41: 44627 | O41: 298.5048 | P41: =O41/O40-1 -> 0.011460665 | R41: 44627 | S41: 566.0394 | T41: =S41/S40-1 -> 0.040119352 | V41: 44627 | W41: 1868.598 | X41: =W41/W40-1 -> 0.062828377 | Z41: 44627 | AA41: 1640.7 | AB41: =AA41/AA40-1 -> -0.0044900188 | AD41: 44627 | AE41: 226.35 | AF41: =AE41/AE40-1 -> 0.10915105
B42: 44634 | C42: 3136.6 | D42: =C42/C41-1 -> 0.069781719 | F42: 44634 | G42: 17287.05 | H42: =G42/G41-1 -> 0.039481794 | N42: 44634 | O42: 315.5821 | P42: =O42/O41-1 -> 0.057209465 | R42: 44634 | S42: 598.2893 | T42: =S42/S41-1 -> 0.056974656 | V42: 44634 | W42: 1857.8773 | X42: =W42/W41-1 -> -0.0057372961 | Z42: 44634 | AA42: 1636.7 | AB42: =AA42/AA41-1 -> -0.0024379838 | AD42: 44634 | AE42: 232.35 | AF42: =AE42/AE41-1 -> 0.026507621
B43: 44641 | C43: 3046.95 | D43: =C43/C42-1 -> -0.028581904 | F43: 44641 | G43: 17153 | H43: =G43/G42-1 -> -0.0077543595 | J43: Adjusted Beta | L43: =(L38*L39)+L40*L41 -> 0.57054979 | N43: 44641 | O43: 301.2571 | P43: =O43/O42-1 -> -0.045392308 | R43: 44641 | S43: 573.831 | T43: =S43/S42-1 -> -0.04088039 | V43: 44641 | W43: 1861.6583 | X43: =W43/W42-1 -> 0.0020351183 | Z43: 44641 | AA43: 1531.4 | AB43: =AA43/AA42-1 -> -0.064336775 | AD43: 44641 | AE43: 232.825 | AF43: =AE43/AE42-1 -> 0.0020443297
B44: 44648 | C44: 3114.15 | D44: =C44/C43-1 -> 0.022054842 | F44: 44648 | G44: 17670.45 | H44: =G44/G43-1 -> 0.030166735 | N44: 44648 | O44: 311.5698 | P44: =O44/O43-1 -> 0.034232222 | R44: 44648 | S44: 592.9976 | T44: =S44/S43-1 -> 0.033401123 | V44: 44648 | W44: 1840.4084 | X44: =W44/W43-1 -> -0.011414501 | Z44: 44648 | AA44: 1616.8 | AB44: =AA44/AA43-1 -> 0.055765966 | AD44: 44648 | AE44: 242.375 | AF44: =AE44/AE43-1 -> 0.041017932
B45: 44655 | C45: 3206.25 | D45: =C45/C44-1 -> 0.029574683 | F45: 44655 | G45: 17784.35 | H45: =G45/G44-1 -> 0.0064457894 | J45: Beta Drifting - IP | N45: 44655 | O45: 307.8559 | P45: =O45/O44-1 -> -0.011919961 | R45: 44655 | S45: 612.1642 | T45: =S45/S44-1 -> 0.032321547 | V45: 44655 | W45: 1832.8466 | X45: =W45/W44-1 -> -0.0041087619 | Z45: 44655 | AA45: 1673.65 | AB45: =AA45/AA44-1 -> 0.035162048 | AD45: 44655 | AE45: 256.625 | AF45: =AE45/AE44-1 -> 0.058793192
B46: 44662 | C46: 3080.65 | D46: =C46/C45-1 -> -0.039173489 | F46: 44662 | G46: 17475.65 | H46: =G46/G45-1 -> -0.017357958 | N46: 44662 | O46: 308.4196 | P46: =O46/O45-1 -> 0.0018310515 | R46: 44662 | S46: 603.4559 | T46: =S46/S45-1 -> -0.014225432 | V46: 44662 | W46: 1814.1812 | X46: =W46/W45-1 -> -0.010183831 | Z46: 44662 | AA46: 1621.8 | AB46: =AA46/AA45-1 -> -0.030980193 | AD46: 44662 | AE46: 252.825 | AF46: =AE46/AE45-1 -> -0.014807599
B47: 44669 | C47: 3164.4 | D47: =C47/C46-1 -> 0.027185821 | F47: 44669 | G47: 17171.95 | H47: =G47/G46-1 -> -0.017378467 | J47: Raw Beta | L47: =_xlfn.COVARIANCE.S(AB9:AB269,$H$9:$H$269)/_xlfn.VAR.S($H$9:$H$269) -> 0.83879714 | N47: 44669 | O47: 311.5698 | P47: =O47/O46-1 -> 0.010214007 | R47: 44669 | S47: 597.2059 | T47: =S47/S46-1 -> -0.010357012 | V47: 44669 | W47: 1807.6722 | X47: =W47/W46-1 -> -0.0035878445 | Z47: 44669 | AA47: 1556.9 | AB47: =AA47/AA46-1 -> -0.040017265 | AD47: 44669 | AE47: 269.85 | AF47: =AE47/AE46-1 -> 0.067339069
B48: 44676 | C48: 3237.2 | D48: =C48/C47-1 -> 0.023005941 | F48: 44676 | G48: 17102.55 | H48: =G48/G47-1 -> -0.0040414746 | J48: Levered Raw Beta | L48: =L47 -> 0.83879714 | N48: 44676 | O48: 311.404 | P48: =O48/O47-1 -> -0.000532144 | R48: 44676 | S48: 598.2893 | T48: =S48/S47-1 -> 0.0018141147 | V48: 44676 | W48: 1798.0523 | X48: =W48/W47-1 -> -0.005321706 | Z48: 44676 | AA48: 1556 | AB48: =AA48/AA47-1 -> -0.00057807181 | AD48: 44676 | AE48: 249.175 | AF48: =AE48/AE47-1 -> -0.076616639
B49: 44683 | C49: 3016.25 | D49: =C49/C48-1 -> -0.068253429 | F49: 44683 | G49: 16411.25 | H49: =G49/G48-1 -> -0.040420873 | J49: Beta Weight | L49: 0.75 | N49: 44683 | O49: 299.3006 | P49: =O49/O48-1 -> -0.038867195 | R49: 44683 | S49: 555.5811 | T49: =S49/S48-1 -> -0.071383861 | V49: 44683 | W49: 1752.346 | X49: =W49/W48-1 -> -0.025419895 | Z49: 44683 | AA49: 1490.95 | AB49: =AA49/AA48-1 -> -0.041805913 | AD49: 44683 | AE49: 238.075 | AF49: =AE49/AE48-1 -> -0.044547005
B50: 44690 | C50: 3064 | D50: =C50/C49-1 -> 0.015830916 | F50: 44690 | G50: 15782.15 | H50: =G50/G49-1 -> -0.03833346 | J50: Market Beta | L50: 1 | N50: 44690 | O50: 264.0186 | P50: =O50/O49-1 -> -0.11788149 | R50: 44690 | S50: 547.0811 | T50: =S50/S49-1 -> -0.015299297 | V50: 44690 | W50: 1688.9794 | X50: =W50/W49-1 -> -0.036161009 | Z50: 44690 | AA50: 1443.85 | AB50: =AA50/AA49-1 -> -0.031590597 | AD50: 44690 | AE50: 216.5 | AF50: =AE50/AE49-1 -> -0.090622703
B51: 44697 | C51: 3109.95 | D51: =C51/C50-1 -> 0.014996736 | F51: 44697 | G51: 16266.15 | H51: =G51/G50-1 -> 0.030667558 | J51: Market Beta Weight | L51: 0.25 | N51: 44697 | O51: 264.4165 | P51: =O51/O50-1 -> 0.0015070908 | R51: 44697 | S51: 525.2896 | T51: =S51/S50-1 -> -0.039832303 | V51: 44697 | W51: 1708.4584 | X51: =W51/W50-1 -> 0.011533 | Z51: 44697 | AA51: 1620.05 | AB51: =AA51/AA50-1 -> 0.12203484 | AD51: 44697 | AE51: 219.9 | AF51: =AE51/AE50-1 -> 0.015704388
B52: 44704 | C52: 2834.85 | D52: =C52/C51-1 -> -0.088458014 | F52: 44704 | G52: 16352.45 | H52: =G52/G51-1 -> 0.0053054964 | N52: 44704 | O52: 268.4952 | P52: =O52/O51-1 -> 0.015425285 | R52: 44704 | S52: 479.3731 | T52: =S52/S51-1 -> -0.087411782 | V52: 44704 | W52: 1663.805 | X52: =W52/W51-1 -> -0.026136662 | Z52: 44704 | AA52: 1577.45 | AB52: =AA52/AA51-1 -> -0.026295485 | AD52: 44704 | AE52: 224.125 | AF52: =AE52/AE51-1 -> 0.019213279
B53: 44711 | C53: 2886.9 | D53: =C53/C52-1 -> 0.01836076 | F53: 44711 | G53: 16584.3 | H53: =G53/G52-1 -> 0.014178304 | J53: Adjusted Beta | L53: =(L48*L49)+L50*L51 -> 0.87909785 | N53: 44711 | O53: 273.8007 | P53: =O53/O52-1 -> 0.01976013 | R53: 44711 | S53: 507.4146 | T53: =S53/S52-1 -> 0.05849619 | V53: 44711 | W53: 1718.844 | X53: =W53/W52-1 -> 0.033080199 | Z53: 44711 | AA53: 1571.5 | AB53: =AA53/AA52-1 -> -0.0037719104 | AD53: 44711 | AE53: 225.65 | AF53: =AE53/AE52-1 -> 0.0068042387
B54: 44718 | C54: 2708.75 | D54: =C54/C53-1 -> -0.061709793 | F54: 44718 | G54: 16201.8 | H54: =G54/G53-1 -> -0.023063982 | N54: 44718 | O54: 264.6818 | P54: =O54/O53-1 -> -0.033304882 | R54: 44718 | S54: 483.9564 | T54: =S54/S53-1 -> -0.046230834 | V54: 44718 | W54: 1709.3678 | X54: =W54/W53-1 -> -0.0055131239 | Z54: 44718 | AA54: 1549.9 | AB54: =AA54/AA53-1 -> -0.01374483 | AD54: 44718 | AE54: 224.225 | AF54: =AE54/AE53-1 -> -0.0063150897
B55: 44725 | C55: 2580.2 | D55: =C55/C54-1 -> -0.047457314 | F55: 44725 | G55: 15293.5 | H55: =G55/G54-1 -> -0.056061672 | J55: Beta Drifting - SP | N55: 44725 | O55: 245.9465 | P55: =O55/O54-1 -> -0.07078424 | R55: 44725 | S55: 467.2898 | T55: =S55/S54-1 -> -0.034438226 | V55: 44725 | W55: 1628.7715 | X55: =W55/W54-1 -> -0.047149771 | Z55: 44725 | AA55: 1430.4 | AB55: =AA55/AA54-1 -> -0.077101748 | AD55: 44725 | AE55: 211.1 | AF55: =AE55/AE54-1 -> -0.058534954
B56: 44732 | C56: 2760.9 | D56: =C56/C55-1 -> 0.070033331 | F56: 44732 | G56: 15699.25 | H56: =G56/G55-1 -> 0.026530879 | N56: 44732 | O56: 247.505 | P56: =O56/O55-1 -> 0.006336744 | R56: 44732 | S56: 495.0814 | T56: =S56/S55-1 -> 0.059474014 | V56: 44732 | W56: 1704.6775 | X56: =W56/W55-1 -> 0.046603222 | Z56: 44732 | AA56: 1426.35 | AB56: =AA56/AA55-1 -> -0.0028313758 | AD56: 44732 | AE56: 219.575 | AF56: =AE56/AE55-1 -> 0.04014685
B57: 44739 | C57: 2773.15 | D57: =C57/C56-1 -> 0.004436959 | F57: 44739 | G57: 15752.05 | H57: =G57/G56-1 -> 0.003363218 | J57: Raw Beta | L57: =_xlfn.COVARIANCE.S(AF9:AF269,$H$9:$H$269)/_xlfn.VAR.S($H$9:$H$269) -> 1.0809728 | N57: 44739 | O57: 247.0076 | P57: =O57/O56-1 -> -0.0020096564 | R57: 44739 | S57: 485.2064 | T57: =S57/S56-1 -> -0.019946215 | V57: 44739 | W57: 1796.9516 | X57: =W57/W56-1 -> 0.054129945 | Z57: 44739 | AA57: 1384.15 | AB57: =AA57/AA56-1 -> -0.029586006 | AD57: 44739 | AE57: 213.55 | AF57: =AE57/AE56-1 -> -0.027439372
B58: 44746 | C58: 2879.8 | D58: =C58/C57-1 -> 0.038458071 | F58: 44746 | G58: 16220.6 | H58: =G58/G57-1 -> 0.029745335 | J58: Levered Raw Beta | L58: =L57 -> 1.0809728 | N58: 44746 | O58: 259.2104 | P58: =O58/O57-1 -> 0.049402529 | R58: 44746 | S58: 487.7064 | T58: =S58/S57-1 -> 0.0051524465 | V58: 44746 | W58: 1815.1384 | X58: =W58/W57-1 -> 0.010120918 | Z58: 44746 | AA58: 1434.6 | AB58: =AA58/AA57-1 -> 0.036448362 | AD58: 44746 | AE58: 240.05 | AF58: =AE58/AE57-1 -> 0.12409272
B59: 44753 | C59: 2978.15 | D59: =C59/C58-1 -> 0.034151677 | F59: 44753 | G59: 16049.2 | H59: =G59/G58-1 -> -0.01056681 | J59: Beta Weight | L59: 0.75 | N59: 44753 | O59: 259.6415 | P59: =O59/O58-1 -> 0.0016631277 | R59: 44753 | S59: 478.0398 | T59: =S59/S58-1 -> -0.019820531 | V59: 44753 | W59: 1837.9676 | X59: =W59/W58-1 -> 0.012577113 | Z59: 44753 | AA59: 1409.1 | AB59: =AA59/AA58-1 -> -0.01777499 | AD59: 44753 | AE59: 242.7 | AF59: =AE59/AE58-1 -> 0.011039367
B60: 44760 | C60: 3067.4 | D60: =C60/C59-1 -> 0.029968269 | F60: 44760 | G60: 16719.45 | H60: =G60/G59-1 -> 0.041762206 | J60: Market Beta | L60: 1 | N60: 44760 | O60: 266.7045 | P60: =O60/O59-1 -> 0.027202893 | R60: 44760 | S60: 491.1647 | T60: =S60/S59-1 -> 0.027455664 | V60: 44760 | W60: 1842.3707 | X60: =W60/W59-1 -> 0.0023956353 | Z60: 44760 | AA60: 1393.3 | AB60: =AA60/AA59-1 -> -0.011212831 | AD60: 44760 | AE60: 254.5 | AF60: =AE60/AE59-1 -> 0.048619695
B61: 44767 | C61: 3333.75 | D61: =C61/C60-1 -> 0.086832497 | F61: 44767 | G61: 17158.25 | H61: =G61/G60-1 -> 0.026244882 | J61: Market Beta Weight | L61: 0.25 | N61: 44767 | O61: 265.2787 | P61: =O61/O60-1 -> -0.0053459915 | R61: 44767 | S61: 520.5813 | T61: =S61/S60-1 -> 0.059891519 | V61: 44767 | W61: 1861.754 | X61: =W61/W60-1 -> 0.010520847 | Z61: 44767 | AA61: 1391.7 | AB61: =AA61/AA60-1 -> -0.0011483528 | AD61: 44767 | AE61: 255.25 | AF61: =AE61/AE60-1 -> 0.0029469548
B62: 44774 | C62: 3473.9 | D62: =C62/C61-1 -> 0.042039745 | F62: 44774 | G62: 17397.5 | H62: =G62/G61-1 -> 0.01394373 | N62: 44774 | O62: 332.56 | P62: =O62/O61-1 -> 0.25362496 | R62: 44774 | S62: 561.4561 | T62: =S62/S61-1 -> 0.078517611 | V62: 44774 | W62: 1825.189 | X62: =W62/W61-1 -> -0.019640081 | Z62: 44774 | AA62: 1564.7 | AB62: =AA62/AA61-1 -> 0.1243084 | AD62: 44774 | AE62: 272.025 | AF62: =AE62/AE61-1 -> 0.065719882
B63: 44781 | C63: 3427.85 | D63: =C63/C62-1 -> -0.013255995 | F63: 44781 | G63: 17698.15 | H63: =G63/G62-1 -> 0.017281219 | J63: Adjusted Beta | L63: =(L58*L59)+L60*L61 -> 1.0607296 | N63: 44781 | O63: 327.7849 | P63: =O63/O62-1 -> -0.014358612 | R63: 44781 | S63: 563.6644 | T63: =S63/S62-1 -> 0.0039331659 | V63: 44781 | W63: 1835.4789 | X63: =W63/W62-1 -> 0.0056377175 | Z63: 44781 | AA63: 1504.8 | AB63: =AA63/AA62-1 -> -0.038282099 | AD63: 44781 | AE63: 270.2 | AF63: =AE63/AE62-1 -> -0.0067089422
B64: 44789 | C64: 3482.55 | D64: =C64/C63-1 -> 0.015957524 | F64: 44789 | G64: 17758.45 | H64: =G64/G63-1 -> 0.0034071358 | N64: 44789 | O64: 335.3785 | P64: =O64/O63-1 -> 0.023166412 | R64: 44789 | S64: 580.9143 | T64: =S64/S63-1 -> 0.030603139 | V64: 44789 | W64: 1816.8613 | X64: =W64/W63-1 -> -0.010143184 | Z64: 44789 | AA64: 1511.25 | AB64: =AA64/AA63-1 -> 0.0042862839 | AD64: 44789 | AE64: 267.675 | AF64: =AE64/AE63-1 -> -0.0093449297
B65: 44795 | C65: 3323.55 | D65: =C65/C64-1 -> -0.0456562 | F65: 44795 | G65: 17558.9 | H65: =G65/G64-1 -> -0.011236904 | N65: 44795 | O65: 326.8896 | P65: =O65/O64-1 -> -0.025311402 | R65: 44795 | S65: 550.1228 | T65: =S65/S64-1 -> -0.053005237 | V65: 44795 | W65: 1856.0108 | X65: =W65/W64-1 -> 0.021547875 | Z65: 44795 | AA65: 1670.4 | AB65: =AA65/AA64-1 -> 0.10531017 | AD65: 44795 | AE65: 260.65 | AF65: =AE65/AE64-1 -> -0.026244513
B66: 44802 | C66: 3431.05 | D66: =C66/C65-1 -> 0.032344932 | F66: 44802 | G66: 17539.45 | H66: =G66/G65-1 -> -0.0011077004 | N66: 44802 | O66: 331.3994 | P66: =O66/O65-1 -> 0.013796095 | R66: 44802 | S66: 556.7894 | T66: =S66/S65-1 -> 0.012118385 | V66: 44802 | W66: 1857.303 | X66: =W66/W65-1 -> 0.0006962244 | Z66: 44802 | AA66: 1589.6 | AB66: =AA66/AA65-1 -> -0.048371648 | AD66: 44802 | AE66: 270.525 | AF66: =AE66/AE65-1 -> 0.037886054
B67: 44809 | C67: 3441.85 | D67: =C67/C66-1 -> 0.0031477245 | F67: 44809 | G67: 17833.35 | H67: =G67/G66-1 -> 0.016756512 | N67: 44809 | O67: 340.4852 | P67: =O67/O66-1 -> 0.027416465 | R67: 44809 | S67: 553.3311 | T67: =S67/S66-1 -> -0.0062111455 | V67: 44809 | W67: 1932.9218 | X67: =W67/W66-1 -> 0.040714305 | Z67: 44809 | AA67: 1554 | AB67: =AA67/AA66-1 -> -0.022395571 | AD67: 44809 | AE67: 306.85 | AF67: =AE67/AE66-1 -> 0.13427594
B68: 44816 | C68: 3322.55 | D68: =C68/C67-1 -> -0.034661592 | F68: 44816 | G68: 17530.85 | H68: =G68/G67-1 -> -0.016962601 | N68: 44816 | O68: 318.2681 | P68: =O68/O67-1 -> -0.065251294 | R68: 44816 | S68: 532.4979 | T68: =S68/S67-1 -> -0.037650513 | V68: 44816 | W68: 2041.229 | X68: =W68/W67-1 -> 0.056032893 | Z68: 44816 | AA68: 1601.35 | AB68: =AA68/AA67-1 -> 0.030469755 | AD68: 44816 | AE68: 299.15 | AF68: =AE68/AE67-1 -> -0.025093694
B69: 44823 | C69: 3395.25 | D69: =C69/C68-1 -> 0.021880784 | F69: 44823 | G69: 17327.35 | H69: =G69/G68-1 -> -0.011608108 | N69: 44823 | O69: 317.7375 | P69: =O69/O68-1 -> -0.0016671479 | R69: 44823 | S69: 528.0812 | T69: =S69/S68-1 -> -0.008294305 | V69: 44823 | W69: 2064.3454 | X69: =W69/W68-1 -> 0.011324746 | Z69: 44823 | AA69: 1523.6 | AB69: =AA69/AA68-1 -> -0.048552784 | AD69: 44823 | AE69: 298.925 | AF69: =AE69/AE68-1 -> -0.00075213104
B70: 44830 | C70: 3342.45 | D70: =C70/C69-1 -> -0.015551138 | F70: 44830 | G70: 17094.35 | H70: =G70/G69-1 -> -0.013446949 | N70: 44830 | O70: 324.7342 | P70: =O70/O69-1 -> 0.022020378 | R70: 44830 | S70: 514.1646 | T70: =S70/S69-1 -> -0.026353144 | V70: 44830 | W70: 2111.2482 | X70: =W70/W69-1 -> 0.022720423 | Z70: 44830 | AA70: 1499.4 | AB70: =AA70/AA69-1 -> -0.015883434 | AD70: 44830 | AE70: 297.7 | AF70: =AE70/AE69-1 -> -0.0040980179
B71: 44837 | C71: 3343.7 | D71: =C71/C70-1 -> 0.00037397717 | F71: 44837 | G71: 17331.8 | H71: =G71/G70-1 -> 0.013890554 | N71: 44837 | O71: 315.4163 | P71: =O71/O70-1 -> -0.028693929 | R71: 44837 | S71: 521.5812 | T71: =S71/S70-1 -> 0.014424564 | V71: 44837 | W71: 2129.1478 | X71: =W71/W70-1 -> 0.0084782073 | Z71: 44837 | AA71: 1493.55 | AB71: =AA71/AA70-1 -> -0.0039015606 | AD71: 44837 | AE71: 305.575 | AF71: =AE71/AE70-1 -> 0.026452805
B72: 44844 | C72: 3185.5 | D72: =C72/C71-1 -> -0.047312857 | F72: 44844 | G72: 17185.7 | H72: =G72/G71-1 -> -0.0084295918 | N72: 44844 | O72: 319.2297 | P72: =O72/O71-1 -> 0.012090054 | R72: 44844 | S72: 510.3313 | T72: =S72/S71-1 -> -0.021568837 | V72: 44844 | W72: 1958.5269 | X72: =W72/W71-1 -> -0.080135771 | Z72: 44844 | AA72: 1482.65 | AB72: =AA72/AA71-1 -> -0.0072980483 | AD72: 44844 | AE72: 299.05 | AF72: =AE72/AE71-1 -> -0.021353187
B73: 44851 | C73: 3092.4 | D73: =C73/C72-1 -> -0.029226181 | F73: 44851 | G73: 17576.3 | H73: =G73/G72-1 -> 0.022728198 | N73: 44851 | O73: 317.8038 | P73: =O73/O72-1 -> -0.0044666897 | R73: 44851 | S73: 487.7897 | T73: =S73/S72-1 -> -0.044170522 | V73: 44851 | W73: 2046.9243 | X73: =W73/W72-1 -> 0.045134637 | Z73: 44851 | AA73: 1418.85 | AB73: =AA73/AA72-1 -> -0.043031059 | AD73: 44851 | AE73: 306.6 | AF73: =AE73/AE72-1 -> 0.025246614
B74: 44858 | C74: 3053.4 | D74: =C74/C73-1 -> -0.012611564 | F74: 44858 | G74: 17786.8 | H74: =G74/G73-1 -> 0.011976355 | N74: 44858 | O74: 315.8142 | P74: =O74/O73-1 -> -0.0062604664 | R74: 44858 | S74: 479.0398 | T74: =S74/S73-1 -> -0.017937853 | V74: 44858 | W74: 2039.6018 | X74: =W74/W73-1 -> -0.0035773184 | Z74: 44858 | AA74: 1430.05 | AB74: =AA74/AA73-1 -> 0.0078937167 | AD74: 44858 | AE74: 292.75 | AF74: =AE74/AE73-1 -> -0.045172864
B75: 44865 | C75: 3181.35 | D75: =C75/C74-1 -> 0.041904107 | F75: 44865 | G75: 18117.15 | H75: =G75/G74-1 -> 0.018572762 | N75: 44865 | O75: 297.1121 | P75: =O75/O74-1 -> -0.05921868 | R75: 44865 | S75: 503.5397 | T75: =S75/S74-1 -> 0.051143767 | V75: 44865 | W75: 2015.0974 | X75: =W75/W74-1 -> -0.012014306 | Z75: 44865 | AA75: 1542.65 | AB75: =AA75/AA74-1 -> 0.078738506 | AD75: 44865 | AE75: 325.225 | AF75: =AE75/AE74-1 -> 0.11093083
... B269: 46223 | C269: 2637.9 | D269: =C269/C268-1 -> -0.019003347 | F269: 46223 | G269: 23767.45 | H269: =G269/G268-1 -> -0.02329428 | N269: 46223 | O269: 193.19 | P269: =O269/O268-1 -> -0.040192766 | R269: 46223 | S269: 497.95 | T269: =S269/S268-1 -> 0.0086084667 | V269: 46223 | W269: 2943.9 | X269: =W269/W268-1 -> -0.02972875 | Z269: 46223 | AA269: 1048.9 | AB269: =AA269/AA268-1 -> -0.015209839 | AD269: 46223 | AE269: 393.45 | AF269: =AE269/AE268-1 -> 0.0062659847

Sheet Market Return
B2: Market Returns
B3: Year | C3: Annual
B4: 2015 | C4: -0.0406
B5: 2016 | C5: 0.0301 | E5: Average Return | G5: =AVERAGE(C4:C18) -> 0.11344545
B6: 2017 | C6: 0.2865 | E6: Dividend Yield | G6: 1.2%1
B7: 2018 | C7: 0.0315 | E7: Total Market Return | G7: =SUM(G5:G6) -> 0.11344545
B8: 2019 | C8: 0.1202
B9: 2020 | C9: 0.149
B10: 2021 | C10: 0.2412
B11: 2022 | C11: 0.0432
B12: 2023 | C12: 0.1942
B13: 2024 | C13: 0.0875
B14: 2025 | C14: 0.1051

Sheet Data for Rel Val
B1: Sr.No | C1: Name | D1: CMP Rs. | E1: No. Eq. shares Cr | F1: Market Cap | G1: Debt Rs. Cr | H1: Net Debt | I1: Cash End rs. Cr. | J1: EV | K1: Sales Rs. Cr | L1: EBITDA | M1: NP 12M Rs. Cr.
B2: 1 | C2: Asian Paints | D2: 2747.3 | E2: 95.92 | F2: =D2*E2 -> 263521.02 | G2: 3928.93 | H2: =G2-I2 -> 2855.25 | I2: 1073.68 | J2: =F2+G2-I2 -> 266376.27 | K2: 37186.93 | L2: 8471.1827 | M2: 4837.09
B3: 2 | C3: Berger Paints | D3: 520.45 | E3: 116.6 | F3: =D3*E3 -> 60684.47 | G3: 635.13 | H3: =G3-I3 -> 329.82 | I3: 305.31 | J3: =F3+G3-I3 -> 61014.29 | K3: 11880.25 | L3: 2225.1708 | M3: 1128.02
B4: 3 | C4: Kansai Nerolac | D4: 196.74 | E4: 80.87 | F4: =D4*E4 -> 15910.364 | G4: 302.73 | H4: =G4-I4 -> 76.95 | I4: 225.78 | J4: =F4+G4-I4 -> 15987.314 | K4: 8051.91 | L4: 1202.9554 | M4: 575.84
B5: 4 | C5: JSW Dulux | D5: 2938.8 | E5: 4.55 | F5: =D5*E5 -> 13371.54 | G5: 79.1 | H5: =G5-I5 -> -244.6 | I5: 323.7 | J5: =F5+G5-I5 -> 13126.94 | K5: 3599.2 | L5: 584.51008 | M5: 1973.8
B6: 5 | C6: Indigo Paints | D6: 1111.8 | E6: 4.77 | F6: =D6*E6 -> 5303.286 | G6: 18.37 | H6: =G6-I6 -> -10.18 | I6: 28.55 | J6: =F6+G6-I6 -> 5293.106 | K6: 1330.12 | L6: 302.20326 | M6: 145.39
B7: 6 | C7: Sirca Paints | D7: 420.45 | E7: 5.68 | F7: =D7*E7 -> 2388.156 | G7: 32.32 | H7: =G7-I7 -> -25.66 | I7: 57.98 | J7: =F7+G7-I7 -> 2362.496 | K7: 508.26 | L7: 111.30894 | M7: 67.05
B8: 7 | C8: Shalimar Paints | D8: 66.68 | E8: 8.37 | F8: =D8*E8 -> 558.1116 | G8: 164.76 | H8: =G8-I8 -> 117.67 | I8: 47.09 | J8: =F8+G8-I8 -> 675.7816 | K8: 575.63 | L8: -28.20587 | M8: -64.95

Sheet Raw FS
B2: ="Balance Sheet Raw"&" - "&Datasheet!$B$1 -> Balance Sheet Raw - ASIAN PAINTS LTD
B3: Years | C3: 42064 | D3: 42430 | E3: 42795 | F3: 43160 | G3: 43525 | H3: 43891 | I3: 44256 | J3: 44621 | K3: 44986 | L3: 45352 | M3: 45717 | N3: 46082
B4: Equity Capital | C4: 96 | D4: 96 | E4: 96 | F4: 96 | G4: 96 | H4: 96 | I4: 96 | J4: 96 | K4: 96 | L4: 96 | M4: 96 | N4: 96
B5: Reserves | C5: 4646 | D5: 6429 | E5: 7508 | F5: 8314 | G5: 9375 | H5: 10034 | I5: 12710 | J5: 13716 | K5: 15896 | L5: 18632 | M5: 19304 | N5: 21276
B6: Borrowings - | C6: 418 | D6: 323 | E6: 560 | F6: 533 | G6: 1320 | H6: 1118 | I6: 1093 | J6: 1587 | K6: 1933 | L6: 2474 | M6: 2290 | N6: 3929
B7: Long term Borrowings | C7: 78 | D7: 73 | E7: 41 | F7: 28 | G7: 19 | H7: 19 | I7: 15 | J7: 45 | K7: 76 | L7: 54 | M7: 260 | N7: 1247 | S7: 17 | T7: =S7+1 -> 18 | U7: =T7+1 -> 19 | V7: =U7+1 -> 20 | W7: =V7+1 -> 21 | X7: =W7+1 -> 22 | Y7: =X7+1 -> 23 | Z7: =Y7+1 -> 24 | AA7: =Z7+1 -> 25 | AB7: =AA7+1 -> 26
B8: Short term Borrowings | C8: 332 | D8: 231 | E8: 504 | F8: 492 | G8: 597 | H8: 321 | I8: 334 | J8: 731 | K8: 896 | L8: 1053 | M8: 604 | N8: 1046
B9: Lease Liabilities | C9: 0 | D9: 0 | E9: 0 | F9: 0 | G9: 693 | H9: 764 | I9: 745 | J9: 811 | K9: 960 | L9: 1367 | M9: 1427 | N9: 1636 | S9: 504 | T9: 492 | U9: 597 | V9: 321 | W9: 334 | X9: 731 | Y9: 896 | Z9: 1053 | AA9: 604 | AB9: 1046
B10: Other Borrowings | C10: 8 | D10: 20 | E10: 15 | F10: 13 | G10: 11 | H10: 15 | I10: 0 | J10: 0 | K10: 0 | L10: 0 | M10: 0 | N10: 0 | T10: =T9/S9-1 -> -0.023809524 | U10: =U9/T9-1 -> 0.21341463 | V10: =V9/U9-1 -> -0.46231156 | W10: =W9/V9-1 -> 0.040498442 | X10: =X9/W9-1 -> 1.1886228 | Y10: =Y9/X9-1 -> 0.22571819 | Z10: =Z9/Y9-1 -> 0.17522321 | AA10: =AA9/Z9-1 -> -0.42640076 | AB10: =AB9/AA9-1 -> 0.73178808
B11: Other Liabilities - | C11: 3754 | D11: 3711 | E11: 4241 | F11: 4820 | G11: 5459 | H11: 4889 | I11: 6456 | J11: 7560 | K11: 7854 | L11: 8698 | M11: 8665 | N11: 9218
B12: Non controlling int | C12: 264 | D12: 384 | E12: 375 | F12: 328 | G12: 361 | H12: 404 | I12: 423 | J12: 388 | K12: 454 | L12: 695 | M12: 659 | N12: 643 | S12: 41 | T12: 28 | U12: 19 | V12: 19 | W12: 15 | X12: 45 | Y12: 76 | Z12: 54 | AA12: 260 | AB12: 1247
B13: Trade Payables | C13: 1549 | D13: 1565 | E13: 1923 | F13: 2160 | G13: 2394 | H13: 2137 | I13: 3379 | J13: 4164 | K13: 3635 | L13: 3831 | M13: 3848 | N13: 3863 | T13: =T12/S12-1 -> -0.31707317 | U13: =U12/T12-1 -> -0.32142857 | V13: =V12/U12-1 -> 0 | W13: =W12/V12-1 -> -0.21052632 | X13: =X12/W12-1 -> 2 | Y13: =Y12/X12-1 -> 0.68888889 | Z13: =Z12/Y12-1 -> -0.28947368 | AA13: =AA12/Z12-1 -> 3.8148148 | AB13: =AB12/AA12-1 -> 3.7961538
B14: Advance from Customers | C14: 5 | D14: 12 | E14: 17 | F14: 16 | G14: 13 | H14: 29 | I14: 41 | J14: 76 | K14: 108 | L14: 154 | M14: 174 | N14: 107
B15: Other liability items | C15: 1937 | D15: 1750 | E15: 1925 | F15: 2316 | G15: 2690 | H15: 2320 | I15: 2613 | J15: 2932 | K15: 3657 | L15: 4017 | M15: 3984 | N15: 4604 | S15: =SUM(S9,S12) -> 545 | T15: =SUM(T9,T12) -> 520 | U15: =SUM(U9,U12) -> 616 | V15: =SUM(V9,V12) -> 340 | W15: =SUM(W9,W12) -> 349 | X15: =SUM(X9,X12) -> 776 | Y15: =SUM(Y9,Y12) -> 972 | Z15: =SUM(Z9,Z12) -> 1107 | ... AB15: =SUM(AB9,AB12) -> 2293
B16: Total Liabilities | C16: 8914 | D16: 10559 | E16: 12405 | F16: 13763 | G16: 16249 | H16: 16138 | I16: 20355 | J16: 22958 | K16: 25779 | L16: 29901 | M16: 30355 | N16: 34519 | T16: =T15/S15-1 -> -0.04587156 | U16: =U15/T15-1 -> 0.18461538 | V16: =V15/U15-1 -> -0.44805195 | W16: =W15/V15-1 -> 0.026470588 | X16: =X15/W15-1 -> 1.2234957 | Y16: =Y15/X15-1 -> 0.25257732 | Z16: =Z15/Y15-1 -> 0.13888889 | AA16: =AA15/Z15-1 -> -0.2195122 | AB16: =AB15/AA15-1 -> 1.6539352
B17: Fixed Assets - | C17: 2660 | D17: 3416 | E17: 3304 | F17: 3732 | G17: 6497 | H17: 6272 | I17: 5859 | J17: 5519 | K17: 5770 | L17: 7147 | M17: 9220 | N17: 9640
B18: Land | C18: 251 | D18: 429 | E18: 408 | F18: 586 | G18: 605 | H18: 640 | I18: 644 | J18: 644 | K18: 804 | L18: 1126 | M18: 1035 | N18: 1204
B19: Building | C19: 962 | D19: 923 | E19: 931 | F19: 957 | G19: 2402 | H19: 2257 | I19: 2249 | J19: 2325 | K19: 2883 | L19: 3390 | M19: 3771 | N19: 4124
B20: Plant Machinery | C20: 2132 | D20: 1793 | E20: 1980 | F20: 2157 | G20: 4006 | H20: 4208 | I20: 4340 | J20: 4531 | K20: 4825 | L20: 5422 | M20: 7576 | N20: 8210
B21: Equipments | C21: 171 | D21: 97 | E21: 119 | F21: 200 | G21: 221 | H21: 241 | I21: 243 | J21: 253 | K21: 270 | L21: 298 | M21: 325 | N21: 351
B22: Furniture n fittings | C22: 83 | D22: 49 | E22: 59 | F22: 72 | G22: 88 | H22: 94 | I22: 99 | J22: 113 | K22: 146 | L22: 175 | M22: 203 | N22: 216
B23: Vehicles | C23: 18 | D23: 11 | E23: 14 | F23: 27 | G23: 47 | H23: 43 | I23: 38 | J23: 32 | K23: 36 | L23: 40 | M23: 34 | N23: 45
B24: Intangible Assets | C24: 351 | D24: 339 | E24: 276 | F24: 468 | G24: 512 | H24: 505 | I24: 476 | J24: 345 | K24: 422 | L24: 850 | M24: 827 | N24: 833
B25: Other fixed assets | C25: 145 | D25: 103 | E25: 128 | F25: 238 | G25: 261 | H25: 293 | I25: 302 | J25: 294 | K25: 289 | L25: 321 | M25: 328 | N25: 335
B26: Gross Block | C26: 4112 | D26: 3744 | E26: 3914 | F26: 4705 | G26: 8141 | H26: 8282 | I26: 8392 | J26: 8538 | K26: 9676 | L26: 11622 | M26: 14099 | N26: 15316
B27: Accumulated Depreciation | C27: 1452 | D27: 327 | E27: 610 | F27: 973 | G27: 1644 | H27: 2010 | I27: 2533 | J27: 3019 | K27: 3905 | L27: 4475 | M27: 4879 | N27: 5676
B28: CWIP | C28: 196 | D28: 107 | E28: 258 | F28: 1405 | G28: 210 | H28: 140 | I28: 183 | J28: 426 | K28: 1020 | L28: 2698 | M28: 1254 | N28: 1849
... B31: Inventories | C31: 2259 | D31: 1998 | E31: 2627 | F31: 2658 | G31: 3150 | H31: 3390 | I31: 3799 | J31: 6153 | K31: 6211 | L31: 5923 | M31: 6719 | N31: 5744
B32: Trade receivables | C32: 1182 | D32: 1187 | E32: 1447 | F32: 1731 | G32: 1907 | H32: 1795 | I32: 2602 | J32: 3871 | K32: 4637 | L32: 4889 | M32: 4314 | N32: 4462 | P32: =SUM(N31:N32)+N35 -> 14868
B33: Cash Equivalents | C33: 204 | D33: 424 | E33: 801 | F33: 405 | G33: 445 | H33: 783 | I33: 611 | J33: 864 | K33: 844 | L33: 1084 | M33: 782 | N33: 1074 | P33: =SUM(N13,N15) -> 8467
B34: Loans n Advances | C34: 8 | D34: 9 | E34: 14 | F34: 13 | G34: 16 | H34: 12 | I34: 11 | J34: 8 | K34: 12 | L34: 17 | M34: 22 | N34: 27 | P34: =P32-P33 -> 6401
B35: Other asset items | C35: 817 | D35: 705 | E35: 1303 | F35: 1678 | G35: 1456 | H35: 1727 | I35: 2555 | J35: 2869 | K35: 3024 | L35: 3555 | M35: 3319 | N35: 4662
B36: Total Assets | C36: 8914 | D36: 10559 | E36: 12405 | F36: 13763 | G36: 16249 | H36: 16138 | I36: 20355 | J36: 22958 | K36: 25779 | L36: 29901 | M36: 30355 | N36: 34519
B42: ="Cash Flow Raw"&" - "&Datasheet!$B$1 -> Cash Flow Raw - ASIAN PAINTS LTD
B43: Years | C43: 42064 | D43: 42430 | E43: 42795 | F43: 43160 | G43: 43525 | H43: 43891 | I43: 44256 | J43: 44621 | K43: 44986 | L43: 45352 | M43: 45717 | N43: 46082
B44: Cash from Operating Activity - | C44: 1188 | D44: 2243 | E44: 1527 | F44: 2113 | G44: 2470 | H44: 3038 | I44: 3683 | J44: 986 | K44: 4193 | L44: 6104 | M44: 4424 | N44: 7088
B45: Profit from operations | C45: 2271 | D45: 2848 | E45: 3056 | F45: 3274 | G45: 3861 | H45: 4380 | I45: 4970 | J45: 4957 | K45: 6460 | L45: 7929 | M45: 6390 | N45: 7186
B46: Receivables | C46: -155 | D46: -146 | E46: -475 | F46: -483 | G46: -205 | H46: 160 | I46: -849 | J46: -1326 | K46: -834 | L46: -362 | M46: 282 | N46: -274
B47: Inventory | C47: -144 | D47: 202 | E47: -629 | F47: -39 | G47: -492 | H47: -251 | I47: -409 | J47: -2354 | K47: -56 | L47: 315 | M47: -805 | N47: 976
B48: Payables | C48: -151 | D48: 142 | E48: 501 | F48: 442 | G48: 287 | H48: -241 | I48: 1143 | J48: 644 | K48: -539 | L48: 269 | M48: -160 | N48: 396
B49: Other WC items | C49: 0 | D49: 0 | E49: 0 | F49: 0 | G49: 0 | H49: 0 | I49: -92 | J49: 242 | K49: 657 | L49: -212 | M49: 114 | N49: 378
B50: Working capital changes | C50: -450 | D50: 198 | E50: -603 | F50: -80 | G50: -410 | H50: -331 | I50: -206 | J50: -2795 | K50: -772 | L50: 10 | M50: -570 | N50: 1476
B51: Direct taxes | C51: -633 | D51: -802 | E51: -925 | F51: -1081 | G51: -982 | H51: -1011 | I51: -1080 | J51: -1176 | K51: -1494 | L51: -1835 | M51: -1396 | N51: -1574
B52: Cash from Investing Activity - | C52: -465 | D52: -866 | E52: -681 | F52: -1556 | G52: -918 | H52: -518 | I52: -541 | J52: -317 | K52: -1282 | L52: -2548 | M52: -941 | N52: -1328 | R52: 15061.99 | S52: 16824.55 | T52: 19240.13 | U52: 20211.25 | V52: 21712.79 | W52: 29101.28 | X52: 34488.59 | Y52: 35494.73 | Z52: 33905.62 | AA52: 35583.54
B53: Fixed assets purchased | C53: -454 | D53: -817 | E53: -684 | F53: -1426 | G53: -1151 | H53: -414 | I53: -289 | J53: -551 | K53: -1446 | L53: -2496 | M53: -1830 | N53: -1487 | P53: =ABS(C53) -> 454 | Q53: =ABS(D53) -> 817 | R53: =ABS(E53) -> 684 | S53: =ABS(F53) -> 1426 | T53: =ABS(G53) -> 1151 | U53: =ABS(H53) -> 414 | V53: =ABS(I53) -> 289 | W53: =ABS(J53) -> 551 | ... AB53: =ABS(O53) -> 0
B54: Fixed assets sold | C54: 16 | D54: 15 | E54: 17 | F54: 17 | G54: 17 | H54: 37 | I54: 28 | J54: 40 | K54: 26 | L54: 5 | M54: 10 | N54: 3 | R54: =R53/R52 -> 0.045412326 | S54: =S53/S52 -> 0.084757096 | T54: =T53/T52 -> 0.059822881 | U54: =U53/U52 -> 0.020483642 | V54: =V53/V52 -> 0.013310127 | W54: =W53/W52 -> 0.018933875 | X54: =X53/X52 -> 0.04192691 | Y54: =Y53/Y52 -> 0.070320298 | ... AA54: =AA53/AA52 -> 0.041788984 | AB54: =AVERAGE(V54:AA54) -> 0.040042258
B55: Investments purchased | C55: -243 | D55: -282 | E55: -153 | F55: -320 | G55: -573 | H55: -25 | I55: -140 | J55: 0 | K55: -146 | L55: -212 | M55: -1 | N55: 0
B56: Investments sold | C56: 278 | D56: 205 | E56: 357 | F56: 362 | G56: 733 | H56: 118 | I56: 272 | J56: 207 | K56: 446 | L56: 240 | M56: 421 | N56: 1197
B57: Interest received | C57: 11 | D57: 15 | E57: 32 | F57: 39 | G57: 40 | H57: 65 | I57: 73 | J57: 77 | K57: 87 | L57: 135 | M57: 155 | N57: 153
B58: Dividends received | C58: 71 | D58: 69 | E58: 74 | F58: 38 | G58: 40 | H58: 27 | I58: 8 | J58: 15 | K58: 56 | L58: 129 | M58: 136 | N58: 118
B59: Investment in group cos | C59: 0 | D59: 0 | E59: 0 | F59: 0 | G59: 0 | H59: 0 | I59: 0 | J59: 0 | K59: -180 | L59: 0 | M59: 0 | N59: 0
B60: Redemp n Canc of Shares | C60: 0 | D60: 0 | E60: 0 | F60: 141 | G60: 0 | H60: 17 | I60: 0 | J60: 0 | K60: 0 | L60: 0 | M60: 38 | N60: 0
B61: Acquisition of companies | C61: 0 | D61: 0 | E61: 0 | F61: -525 | G61: 0 | H61: 0 | I61: 0 | J61: 0 | K61: 0 | L61: 0 | M61: 0 | N61: 0
B62: Other investing items | C62: -144 | D62: -70 | E62: -324 | F62: 118 | G62: -24 | H62: -343 | I62: -493 | J62: -105 | K62: -126 | L62: -350 | M62: 130 | N62: -1312
B63: Cash from Financing Activity - | C63: -576 | D63: -849 | E63: -756 | F63: -1379 | G63: -1117 | H63: -2871 | I63: -650 | J63: -1808 | K63: -2140 | L63: -2982 | M63: -3753 | N63: -2377
B64: Proceeds from shares | C64: 0 | D64: 0 | E64: 0 | F64: 0 | G64: 0 | H64: 0 | I64: 0 | J64: 0 | K64: 0 | L64: 1 | M64: 0 | N64: 0
B65: Proceeds from borrowings | C65: 239 | D65: 8 | E65: 271 | F65: 10 | G65: 243 | H65: 18 | I65: 155 | J65: 418 | K65: 254 | L65: 101 | M65: 415 | N65: 1279
B66: Repayment of borrowings | C66: -86 | D66: -119 | E66: -58 | F66: -54 | G66: -26 | H66: -482 | I66: -14 | J66: -8 | K66: -25 | L66: -98 | M66: -428 | N66: -452
... B72: Free Cash Flow | C72: 750 | D72: 1441 | E72: 860 | F72: 705 | G72: 1336 | H72: 2661 | I72: 3422 | J72: 475 | K72: 2774 | L72: 3613 | M72: 2604 | N72: 5604

Sheet Football Field Analysis
B2: ="Football Field Analysis"&" - "&Datasheet!$B$1 -> Football Field Analysis - ASIAN PAINTS LTD
L4: Football Field Analysis
N5: OpenLow | O5: Low | P5: OpenHigh | Q5: High
L6: Comps | N6: 1513.0021 | O6: 1513.0021 | P6: 1844.6919 | Q6: 1844.6919
L7: DCF Bear | N7: 226.64819 | O7: =DCF!M21 -> 308.93302 | P7: 284.93298 | Q7: =DCF!M26 -> 390.6451
L8: DCF Base | N8: 478.66803 | O8: 478.66803 | P8: 1029.0814 | Q8: 1029.0814
L9: DCF Bull | N9: 694.73918 | O9: 694.73918 | P9: 4141.4803 | Q9: 4141.4803
L10: 52W H/L | N10: 2115 | O10: 2115 | P10: 2985.7 | Q10: 2985.7

Sheet PPE Schedule
B2: PPE Schedule
B3: Years | C3: 2022 | D3: =C3+1 -> 2023 | E3: =D3+1 -> 2024 | F3: =E3+1 -> 2025 | G3: =F3+1 -> 2026 | H3: =G3+1 -> 2027 | I3: =H3+1 -> 2028 | J3: =I3+1 -> 2029 | K3: =J3+1 -> 2030 | L3: =K3+1 -> 2031
B4: Opening Gross PPE | C4: ='Raw FS'!I26 -> 8392 | D4: =C7 -> 8903 | E4: =D7 -> 10323 | F4: =E7 -> 12814 | G4: =F7 -> 14634 | H4: =G7 -> 16118 | I4: =H7 -> 17777.616 | J4: =I7 -> 19536.81 | K4: =J7 -> 21419.146 | L4: =K7 -> 23433.247
B5: Add: Capex | C5: =ABS('Raw FS'!J53) -> 551 | D5: =ABS('Raw FS'!K53) -> 1446 | E5: =ABS('Raw FS'!L53) -> 2496 | F5: =ABS('Raw FS'!M53) -> 1830 | G5: =ABS('Raw FS'!N53) -> 1487 | H5: ='Forecast(Explicit)'!C39 -> 1659.6163 | I5: ='Forecast(Explicit)'!D39 -> 1759.1933 | J5: ='Forecast(Explicit)'!E39 -> 1882.3368 | K5: ='Forecast(Explicit)'!F39 -> 2014.1004 | L5: ='Forecast(Explicit)'!G39 -> 2155.0874
B6: Less: Disposal | C6: =-'Raw FS'!J54 -> -40 | D6: =-'Raw FS'!K54 -> -26 | E6: =-'Raw FS'!L54 -> -5 | F6: =-'Raw FS'!M54 -> -10 | G6: =-'Raw FS'!N54 -> -3 | H6: 0 | I6: 0 | J6: 0 | K6: 0 | L6: 0
B7: Closing Gross PPE | C7: =SUM(C4:C6) -> 8903 | D7: =SUM(D4:D6) -> 10323 | E7: =SUM(E4:E6) -> 12814 | F7: =SUM(F4:F6) -> 14634 | G7: =SUM(G4:G6) -> 16118 | H7: =SUM(H4:H6) -> 17777.616 | I7: =SUM(I4:I6) -> 19536.81 | J7: =SUM(J4:J6) -> 21419.146 | ... L7: =SUM(L4:L6) -> 25588.334
B8: Average Gross PPE | D8: =AVERAGE(C7:D7) -> 9613 | E8: =AVERAGE(D7:E7) -> 11568.5 | F8: =AVERAGE(E7:F7) -> 13724 | G8: =AVERAGE(F7:G7) -> 15376 | H8: =AVERAGE(G7:H7) -> 16947.808 | I8: =AVERAGE(H7:I7) -> 18657.213 | J8: =AVERAGE(I7:J7) -> 20477.978 | K8: =AVERAGE(J7:K7) -> 22426.197 | L8: =AVERAGE(K7:L7) -> 24510.791
B9: Depreciation Rate | D9: =D10/D8 -> 0.089256216 | E9: =E10/E8 -> 0.073734711 | F9: =F10/F8 -> 0.074784319 | G9: =G10/G8 -> 0.079920005 | H9: =AVERAGE(D9:G9) -> 0.079423813 | I9: =AVERAGE(E9:H9) -> 0.076965712 | J9: =AVERAGE(F9:I9) -> 0.077773462 | K9: =AVERAGE(G9:J9) -> 0.078520748 | L9: =AVERAGE(H9:K9) -> 0.078170934
B10: Depreciation Amount | C10: =HistoricalFS!H24 -> 816.36 | D10: =HistoricalFS!I24 -> 858.02 | E10: =HistoricalFS!J24 -> 853 | F10: =HistoricalFS!K24 -> 1026.34 | G10: =HistoricalFS!L24 -> 1228.85 | H10: =H9*H8 -> 1346.0595 | I10: =I9*I8 -> 1435.9657 | J10: =J9*J8 -> 1592.6433 | K10: =K9*K8 -> 1760.9217 | L10: =L9*L8 -> 1916.0314
B12: Capital Expenditure Schedule
B13: Years | C13: 2027 | D13: =C13+1 -> 2028 | E13: =D13+1 -> 2029 | F13: =E13+1 -> 2030 | G13: =F13+1 -> 2031 | H13: Total
B14: VAM-VAE | C14: 500 | D14: 300 | E14: 100 | F14: 0 | G14: 0 | H14: =SUM(C14:G14) -> 900
B15: Pithampur Water based | C15: 100 | D15: 700 | E15: 800 | F15: 400 | G15: 0 | H15: =SUM(C15:G15) -> 2000
B16: Total Capex | C16: =SUM(C14:C15) -> 600 | D16: =SUM(D14:D15) -> 1000 | E16: =SUM(E14:E15) -> 900 | F16: =SUM(F14:F15) -> 400 | G16: 0 | H16: =SUM(C16:G16) -> 2900

Sheet Sheet2
